Workbook

Sheet 会员总表
A1: 序号 | B1: 加入时间 | C1: 会籍时间 | D1: 姓名 | E1: 性别 | F1: 面试官 | G1: 推荐人 | H1: 推荐人分会 | I1: 推荐大类 | J1: 是否更新 | K1: 地区 | L1: 所在位置 | M1: 公司 | N1: 职位 | O1: 会员类型 | P1: 会员编号 | Q1: 是否入组 | R1: 新会员接待 | S1: 新会员培训时间 | T1: 培训师 | U1: 上线官网 | V1: 新学员见面直播 | W1: 是否续费 | X1: 备注 | Y1: 出海 | Z1: 加入时长 | AA1: 过期 | AB1: 续费金额 | AC1: 推荐人 | AD1: 推荐大类 | AE1: 邮箱 | AF1: 备注 | AG1: 饭团 | AH1: 分会活动 | AI1: 累计 | AJ1: 活跃度打分
A2: 1 | B2: 42129 | C2: 46203 | D2: 艾芙（徐雁斐） | E2: 女 | G2: 暂无 | I2: 暂无 | J2: 1 | K2: 深圳 | M2: 暂无 | N2: 暂无 | O2: 标准会员 | P2: 1 | S2: - | T2: - | U2: 1 | AE2: elfe1021@gmail.com
A3: 2 | B3: 42132 | C3: 46203 | D3: 郭理靖 | E3: 男 | G3: 暂无 | I3: 暂无 | J3: 1 | K3: 杭州 | M3: 奈雪的茶 | N3: CTO | O3: 标准会员 | P3: 2 | S3: - | T3: - | U3: 1 | X3: 1 | Y3: 1 | AE3: guolijing@gmail.com
A4: 3 | B4: 42139 | C4: 46203 | D4: 陈锡言 | E4: 男 | G4: 暂无 | I4: 暂无 | J4: 无信息0 | K4: 北京 | M4: 一览科技 | N4: 联合创始人 | O4: 标准会员 | P4: 5 | Q4: 北京0组 | R4: 0 | S4: - | T4: - | U4: 1 | Y4: 1 | AB4: 已续费 | AE4: cccsmoking@sina.com | AG4: 1 | AH4: 2 | AI4: 3 | AJ4: B
A5: 4 | B5: 42146 | C5: 46203 | D5: 汪威 | E5: 男 | G5: 暂无 | I5: 暂无 | J5: 1 | K5: 北京 | M5: 心语未来 | N5: CEO | O5: 高级会员 | P5: 12 | Q5: 北京0组 | R5: 0 | S5: - | T5: - | U5: 1 | Y5: 1 | AB5: 已续费 | AE5: wangcash@gmail.com | AG5: 0 | AH5: 0 | AI5: 0 | AJ5: D
A6: 5 | B6: 42147 | C6: 46203 | D6: 唐小浙 | E6: 男 | G6: 暂无 | I6: 暂无 | J6: 1 | K6: 上海 | M6: 墨誉科技 | N6: 技术vp | O6: 标准会员 | P6: 13 | S6: - | T6: - | U6: 1 | Y6: 1 | AE6: tangxz@gmail.com
A7: 6 | B7: 42150 | C7: 46203 | D7: 邹光先 | E7: 男 | G7: 暂无 | I7: 暂无 | J7: 0 | K7: 广州 | M7: 其他 | N7: 其他 | O7: 标准会员 | P7: 14 | S7: - | T7: - | U7: 1 | Y7: 1 | AE7: zouguangxian@163.com
A8: 7 | B8: 42160 | C8: 46203 | D8: 黄良懿 | E8: 男 | G8: 暂无 | I8: 暂无 | J8: 1 | K8: 深圳 | M8: 高仙机器人 | N8: 研发VP | O8: 标准会员 | P8: 17 | S8: - | T8: - | U8: 1 | Y8: 1 | AE8: codeant@hotmail.com
A9: 8 | B9: 42171 | C9: 46203 | D9: 史海峰 | E9: 男 | G9: 暂无 | I9: 暂无 | J9: 1 | K9: 北京 | M9: 方正证券 | N9: 架构平台负责人 | O9: 标准会员 | P9: 23 | Q9: 北京2组 | R9: 0 | S9: - | T9: - | U9: 1 | X9: 1 | Y9: 1 | AB9: 已续费 | AE9: shihf_dc@163.com | AG9: 17 | AH9: 9 | AI9: 26 | AJ9: A
A10: 9 | B10: 42180 | C10: 46203 | D10: 梁宇鹏 | E10: 男 | G10: 暂无 | I10: 暂无 | J10: 0 | K10: 北京 | M10: 蓝莺IM | N10: CEO | O10: 标准会员 | P10: 24 | Q10: 北京2组 | R10: 0 | S10: - | T10: - | U10: 1 | Y10: 1 | AB10: 已续费 | AE10: eric.l.2046@gmail.com | AG10: 11 | AH10: 5 | AI10: 16 | AJ10: A
A11: 10 | B11: 42202 | C11: 46203 | D11: 熊昌伟 | E11: 男 | G11: 暂无 | I11: 暂无 | J11: 1 | K11: 北京 | M11: 畅捷通信息技术有限公司 | N11: 助理总裁 | O11: 标准会员 | P11: 29 | Q11: 北京0组 | R11: 0 | S11: - | T11: - | U11: 1 | Y11: 1 | AB11: 已续费 | AE11: xcw@chanjet.com | AG11: 1 | AH11: 3 | AI11: 4 | AJ11: B
A12: 11 | B12: 42209 | C12: 46203 | D12: 丁宁 | E12: 男 | G12: 暂无 | I12: 暂无 | J12: 无公司 | K12: 新加坡 | M12: 荔枝集团 | N12: CTO | O12: 高级会员 | P12: 30 | S12: - | T12: - | U12: 1 | X12: 1 | Y12: 1 | AE12: dingning@lizhi.fm
A13: 12 | B13: 42219 | C13: 46203 | D13: 陈靖华 | E13: 男 | G13: 暂无 | I13: 暂无 | J13: 1 | K13: 北京 | M13: 北京基调网络股份有限公司 | N13: CEO | O13: 标准会员 | P13: 34 | Q13: 北京2组 | R13: 0 | S13: - | T13: - | U13: 1 | Y13: 1 | AB13: 已续费 | AE13: wood@tingyun.com | AG13: 0 | AH13: 1 | AI13: 1 | AJ13: C
A14: 13 | B14: 42221 | C14: 46203 | D14: 侯冬雯 | E14: 女 | G14: 暂无 | I14: 暂无 | J14: 无公司 | K14: 北京 | M14: 北京微梦传媒 | N14: CTO | O14: 高级会员 | P14: 38 | Q14: 北京0组 | R14: 0 | S14: - | T14: - | U14: 1 | Y14: 1 | AB14: 已续费 | AE14: dongwen@microdreams.com.cn | AG14: 0 | AH14: 0 | AI14: 0 | AJ14: D
A15: 14 | B15: 42246 | C15: 46203 | D15: 黄彬彬 | E15: 男 | G15: 暂无 | I15: 暂无 | J15: 1 | K15: 上海 | M15: 多云转晴 | N15: 架构师 | O15: 高级会员 | P15: 44 | S15: - | T15: - | U15: 1 | Y15: 1 | AE15: 118733@qq.com
A16: 15 | B16: 42248 | C16: 46203 | D16: 王立博 | E16: 男 | G16: 暂无 | I16: 暂无 | J16: 1 | K16: 上海 | M16: 未来保贝 | N16: 合伙人&CTO | O16: 标准会员 | P16: 48 | S16: - | T16: - | U16: 1 | Y16: 1 | AE16: w803007@163.com
A17: 16 | B17: 42256 | C17: 46203 | D17: 胡震 | E17: 男 | G17: 暂无 | I17: 暂无 | J17: 1 | K17: 上海 | M17: 某公链基金会 | N17: 投研负责人 | O17: 标准会员 | P17: 58 | S17: - | T17: - | U17: 1 | Y17: 1 | AE17: huzhencn@163.com
A18: 17 | B18: 42275 | C18: 46203 | D18: 洪强宁 | E18: 男 | G18: 暂无 | I18: 暂无 | J18: 1 | K18: 北京 | M18: 雅识科技 | N18: 联合创始人兼CTO | O18: 标准会员 | P18: 65 | Q18: 北京2组 | R18: 0 | S18: - | T18: - | U18: 1 | Y18: 1 | AB18: 已续费 | AE18: hongqn@gmail.com | AG18: 0 | AH18: 0 | AI18: 0 | AJ18: C
A19: 18 | B19: 42298 | C19: 46203 | D19: 李道兵 | E19: 男 | G19: 暂无 | I19: 暂无 | J19: 1 | K19: 北京 | M19: Fortinet Principal Embedded Software Developer | N19: 创始人 | O19: 标准会员 | P19: 70 | Q19: 北京0组 | R19: 0 | S19: - | T19: - | U19: 1 | Y19: 1 | AB19: 无需续费 | AE19: lidaobing@gmail.com | AG19: 0 | AH19: 0 | AI19: 0 | AJ19: D
A20: 19 | B20: 42300 | C20: 46203 | D20: 张海龙 | E20: 男 | G20: 暂无 | I20: 暂无 | J20: 1 | K20: 苏州 | M20: 同程旅行 | N20: 技术委员会主任 | O20: 标准会员 | P20: 72 | S20: - | T20: - | U20: 1 | X20: 1 | Y20: 1 | AE20: zhanghailong@coding.net
A21: 20 | B21: 42300 | C21: 46203 | D21: 王晓波 | E21: 男 | G21: 暂无 | I21: 暂无 | J21: 0 | K21: 苏州 | M21: 同程旅行 | N21: AVP&出行事业群 CTO | O21: 标准会员 | P21: 71 | S21: - | T21: - | U21: 1 | Y21: 1 | AE21: wxb09195@ly.com
A22: 21 | B22: 42318 | C22: 46203 | D22: 林华根 | E22: 男 | G22: 暂无 | I22: 暂无 | J22: 1 | K22: 深圳 | M22: 安徽超远信息技术有限公司 | N22: 副总工程师 | O22: 标准会员 | P22: 78 | S22: - | T22: - | U22: 1 | Y22: 1 | AE22: lhg@cychina.cn
A23: 22 | B23: 42334 | C23: 46203 | D23: 魏吉贺 | E23: 男 | G23: 暂无 | I23: 暂无 | J23: 1 | K23: 深圳 | M23: 深圳市残友软件股份有限公司 | N23: 技术总监 | O23: 标准会员 | P23: 91 | S23: - | T23: - | U23: 1 | Y23: 1 | AE23: wjh@canyou.cn
A24: 23 | B24: 42339 | C24: 46203 | D24: 龚银 | E24: 男 | G24: 暂无 | I24: 暂无 | J24: 1 | K24: 深圳 | M24: 安克创新 | N24: CIO | O24: 标准会员 | P24: 95 | S24: - | T24: - | U24: 1 | Y24: 1 | AE24: gongyin@126.com
A25: 24 | B25: 42361 | C25: 46203 | D25: 华健 | E25: 男 | G25: 暂无 | I25: 暂无 | J25: 1 | K25: 北京 | M25: 北京梦诚科技 | N25: CTO | O25: 标准会员 | P25: 102 | Q25: 北京2组 | R25: 0 | S25: - | T25: - | U25: 1 | Y25: 1 | AB25: 已续费 | AE25: huaj1101@qq.com | AG25: 0 | AH25: 2 | AI25: 2 | AJ25: C
A26: 25 | B26: 42427 | C26: 46203 | D26: 何世友 | E26: 男 | G26: 暂无 | I26: 暂无 | J26: 1 | K26: 广州 | M26: 腾讯云 | N26: Serverless 产品负责人 | O26: 标准会员 | P26: 114 | S26: - | T26: - | U26: 1 | Y26: 1 | AE26: shiyou.he@gmail.com
A27: 26 | B27: 42433 | C27: 46203 | D27: 李玉福 | E27: 男 | G27: 暂无 | I27: 暂无 | J27: 1 | K27: 北京 | M27: 农信互联 | N27: 副总裁 | O27: 标准会员 | P27: 117 | Q27: 北京15组 | R27: 0 | S27: - | T27: - | U27: 1 | Y27: 1 | AB27: 已续费 | AE27: liyufu@nxin.com | AG27: 2 | AH27: 2 | AI27: 4 | AJ27: B
A28: 27 | B28: 42451 | C28: 46203 | D28: 曾冠东 | E28: 男 | G28: 暂无 | I28: 暂无 | J28: 0 | K28: 广州 | M28: 酷狗音乐 | N28: 繁星网研发总监 | O28: 标准会员 | P28: 123 | S28: - | T28: - | U28: 1 | X28: 1 | Y28: 1 | AE28: popeast@gmail.com
A29: 28 | B29: 42451 | C29: 46203 | D29: 路文杰 | E29: 男 | G29: 暂无 | I29: 暂无 | J29: 1 | K29: 广州 | M29: 甘果科技 | N29: CEO | O29: 标准会员 | P29: 121 | S29: - | T29: - | U29: 1 | AE29: cngump@gmail.com
A30: 29 | B30: 42473 | C30: 46203 | D30: 高楚涛 | E30: 男 | G30: 暂无 | I30: 暂无 | J30: 1 | K30: 深圳 | M30: 深圳市嘉立创科技发展有限公司 | N30: CIO | O30: 标准会员 | P30: 135 | S30: - | T30: - | U30: 1 | Y30: 1 | AE30: gaochutao@163.com
A31: 30 | B31: 42480 | C31: 46203 | D31: 刘建国 | E31: 男 | G31: 暂无 | I31: 暂无 | J31: 1 | K31: 广州 | L31: 1 | M31: 伊智信息科技 | N31: CEO | O31: 标准会员 | P31: 26 | S31: - | T31: - | U31: 1 | Y31: 1 | AE31: yijshu@gmail.com
A32: 31 | B32: 42482 | C32: 46203 | D32: 万林涛 | E32: 男 | G32: 暂无 | I32: 暂无 | J32: 1 | K32: 上海 | M32: 上海蔚星数据 | N32: 副总裁兼首席数据官 | O32: 标准会员 | P32: 140 | S32: - | T32: - | U32: 1 | Y32: 1 | AE32: lintao.wan@outlook.com
A33: 32 | B33: 42482 | C33: 46203 | D33: 徐翎 | E33: 男 | G33: 暂无 | I33: 暂无 | J33: 1 | K33: 上海 | M33: 上海数达物流科技有限公司 | N33: CTO | O33: 标准会员 | P33: 139 | S33: - | T33: - | U33: 1 | AE33: xlshcn@hotmail.com
A34: 33 | B34: 42495 | C34: 46203 | D34: 肖颖 | E34: 男 | G34: 暂无 | I34: 暂无 | J34: １ | K34: 上海 | M34: 上海澄廓信息科技有限公司 | N34: CEO | O34: 标准会员 | P34: 144 | S34: - | T34: - | U34: 1 | AE34: 18049722632@163.com
A35: 34 | B35: 42524 | C35: 46203 | D35: 张剑伟 | E35: 男 | G35: 暂无 | I35: 暂无 | J35: １ | K35: 上海 | M35: 百安居 | N35: CTO | O35: 标准会员 | P35: 160 | S35: - | T35: - | U35: 1 | AE35: zjwsoft@gmail.com
A36: 35 | B36: 42536 | C36: 46203 | D36: 苏煦烽 | E36: 男 | G36: 暂无 | I36: 暂无 | J36: １ | K36: 广州 | L36: 1 | M36: 亲邻科技 | N36: 技术总监 | O36: 标准会员 | P36: 167 | S36: - | T36: - | U36: 1 | Y36: 1 | AE36: suxufeng@qq.com
A37: 36 | B37: 42537 | C37: 46203 | D37: 孙其瑞 | E37: 男 | G37: 暂无 | I37: 暂无 | J37: １ | K37: 杭州 | M37: 苏州优频科技有限公司 | N37: CTO | O37: 标准会员 | P37: 171 | S37: - | T37: - | U37: 1 | Y37: 1 | AE37: sqr@detu.com
A38: 37 | B38: 42552 | C38: 46203 | D38: 芦宇峰 | E38: 男 | G38: 暂无 | I38: 暂无 | J38: １ | K38: 杭州 | M38: 上海擎路科技 | N38: 联合创始人 & CTO | O38: 标准会员 | P38: 178 | S38: - | T38: - | U38: 1 | Y38: 1 | AE38: xiao_ys@163.com
A39: 38 | B39: 42556 | C39: 46203 | D39: 陈杰 | E39: 男 | G39: 暂无 | I39: 暂无 | J39: １ | K39: 上海 | M39: 上海领健信息技术有限公司 | N39: CTO | O39: 标准会员 | P39: 188 | S39: - | T39: - | U39: 0 | AE39: alan.chen@linkedcare.cn
A40: 39 | B40: 42559 | C40: 46203 | D40: 黄伟坚 | E40: 男 | G40: 暂无 | I40: 暂无 | J40: １ | K40: 广州 | L40: 1 | M40: mobvista汇量科技 | N40: 联合创始人 | O40: 标准会员 | P40: 190 | S40: - | T40: - | U40: 1 | Y40: 1 | AE40: hwjian@126.com
A41: 40 | B41: 42559 | C41: 46203 | D41: 黄勇 | E41: 男 | G41: 暂无 | I41: 暂无 | J41: １ | K41: 上海 | M41: 阅流 | N41: CTO | O41: 标准会员 | P41: 191 | S41: - | T41: - | U41: 1 | Y41: 1 | AE41: hy_think@163.com
A42: 41 | B42: 42562 | C42: 46203 | D42: 奚铭皋 | E42: 男 | G42: 暂无 | I42: 暂无 | J42: １ | K42: 上海 | M42: 比图科技 | N42: Tech Lead | O42: 标准会员 | P42: 193 | S42: - | T42: - | U42: 1 | AE42: minggao.xi@gmail.com
A43: 42 | B43: 42562 | C43: 46203 | D43: 陆云昆 | E43: 男 | G43: 暂无 | I43: 暂无 | J43: １ | K43: 上海 | M43: 上海钢蜂信息科技有限公司 | N43: CTO | O43: 标准会员 | P43: 194 | S43: - | T43: - | U43: 1 | Y43: 1 | AE43: ykdoubles@hotmail.com
A44: 43 | B44: 42576 | C44: 45838 | D44: 陈峰 | E44: 男 | G44: 暂无 | I44: 暂无 | J44: １ | K44: 北京 | M44: Red Hat | N44: 研发经理 | O44: 标准会员 | P44: 521 | R44: 0 | S44: - | T44: - | U44: 1 | Y44: 1 | AB44: 待定 | AE44: bitchenfeng@vip.sina.com | AG44: 0 | AH44: 0 | AI44: =AG44+AH44 -> 0
A45: 44 | B45: 42589 | C45: 46203 | D45: 张志合 | E45: 男 | G45: 暂无 | I45: 暂无 | J45: １ | K45: 广州 | M45: 广州卓越教育 | N45: 资深IT总监 | O45: 标准会员 | P45: 210 | S45: - | T45: - | U45: 1 | X45: 1 | AE45: kaffeel@163.com
A46: 45 | B46: 42597 | C46: 46203 | D46: 谢金牛 | E46: 男 | G46: 暂无 | I46: 暂无 | J46: １ | K46: 广州 | M46: 深圳风信计算机服务有限公司 | N46: 总经理 | O46: 标准会员 | P46: 222 | S46: - | T46: - | U46: 1 | Y46: 1 | AE46: 115617486@qq.com
A47: 46 | B47: 42613 | C47: 46203 | D47: 廖雄杰 | E47: 男 | G47: 暂无 | I47: 暂无 | J47: １ | K47: 北京 | M47: 基调听云 | N47: 研发总监 | O47: 标准会员 | P47: 233 | Q47: 北京0组 | R47: 0 | S47: - | T47: - | U47: 1 | AB47: 已续费 | AE47: liaoxj@tingyun.com | AG47: 0 | AH47: 0 | AI47: 0 | AJ47: D
A48: 47 | B48: 42631 | C48: 46203 | D48: 伍涛 | E48: 男 | G48: 暂无 | I48: 暂无 | J48: １ | K48: 上海 | M48: Funplus | N48: Co-CTO | O48: 标准会员 | P48: 242 | S48: - | T48: - | U48: 1 | X48: 1 | Y48: 1 | AE48: tonywutao@gmail.com
A49: 48 | B49: 42657 | C49: 46203 | D49: 张飞 | E49: 男 | G49: 暂无 | I49: 暂无 | J49: １ | K49: 上海 | M49: vivo | N49: 部门总经理 | O49: 标准会员 | P49: 253 | S49: - | T49: - | U49: 1 | X49: 1 | Y49: 1 | AE49: zgfi@163.com
A50: 49 | B50: 42667 | C50: 46203 | D50: 卢亿雷 | E50: 男 | G50: 暂无 | I50: 暂无 | J50: １ | K50: 北京 | M50: 白海科技 | N50: 创始人兼CEO | O50: 高级会员 | P50: 258 | Q50: 北京24组 | R50: 0 | S50: - | T50: - | U50: 1 | Y50: 1 | AB50: 无需续费 | AE50: johnlya@163.com | AG50: 2 | AH50: 0 | AI50: 2 | AJ50: A
A51: 50 | B51: 42667 | C51: 46203 | D51: 洪倍 | E51: 男 | G51: 暂无 | I51: 暂无 | J51: １ | K51: 上海 | M51: ValueZ智库 | N51: 创始人、合伙人 | O51: 标准会员 | P51: 259 | S51: - | T51: - | U51: 1 | AE51: bh@roomwits.com
A52: 51 | B52: 42695 | C52: 46203 | D52: 王河生 | E52: 男 | G52: 暂无 | I52: 暂无 | J52: 无公司 | K52: 南京 | M52: 南京四维向量科技有限公司 | N52: 创始人&CEO | O52: 标准会员 | P52: 268 | S52: - | T52: - | U52: 1 | AE52: 4005958@qq.com
A53: 52 | B53: 42698 | C53: 46203 | D53: 何德照 | E53: 男 | G53: 暂无 | I53: 暂无 | J53: １ | K53: 深圳 | M53: AfterShip | N53: 技术VP | O53: 标准会员 | P53: 269 | S53: - | T53: - | U53: 1 | Y53: 1 | AE53: dezhaohe@qq.com
A54: 53 | B54: 42706 | C54: 46203 | D54: 张呈刚 | E54: 男 | G54: 暂无 | I54: 暂无 | J54: １ | K54: 深圳 | M54: AWS | N54: 架构师经理 | O54: 标准会员 | P54: 273 | S54: - | T54: - | U54: 1 | Y54: 1 | AE54: 470344500@qq.com
A55: 54 | B55: 42723 | C55: 46203 | D55: 练海荣 | E55: 男 | G55: 暂无 | I55: 暂无 | J55: １ | K55: 苏州 | M55: 龙石数据 | N55: 总经理 | O55: 标准会员 | P55: 283 | S55: - | T55: - | U55: 1 | Y55: 1 | AE55: hairong_lian@163.com
A56: 55 | B56: 42730 | C56: 46203 | D56: 冯斌 | E56: 男 | G56: 暂无 | I56: 暂无 | J56: １ | K56: 深圳 | M56: ONES | N56: CTO | O56: 高级会员 | P56: 295 | S56: - | T56: - | U56: 1 | X56: 1 | Y56: 1 | AE56: 13918821015@139.com
A57: 56 | B57: 42730 | C57: 46934 | D57: 朱攀 | E57: 男 | G57: 暂无 | I57: 暂无 | J57: １ | K57: 上海 | M57: 阿旅科技 | N57: CEO | O57: 标准会员 | P57: 292 | S57: - | T57: - | U57: 1 | AE57: panos.zhu@qq.com
A58: 57 | B58: 42730 | C58: 46203 | D58: 贾锦杰 | E58: 男 | G58: 暂无 | I58: 暂无 | J58: １ | K58: 广州 | M58: KEEP | N58: 战略 & PMO leader | O58: 标准会员 | P58: 291 | Q58: 北京0组 | S58: - | T58: - | U58: 1 | X58: 1 | AB58: 已续费 | AE58: jiajinjie@gmail.com
A59: 58 | B59: 42731 | C59: 46203 | D59: 李卓 | E59: 男 | G59: 暂无 | I59: 暂无 | J59: １ | K59: 杭州 | M59: 道富信息科技 | N59: 董事总经理 | O59: 高级会员 | P59: 297 | S59: - | T59: - | U59: 1 | AE59: me@milanello1998.com
A60: 59 | B60: 42733 | C60: 45838 | D60: 吴永强 | E60: 男 | G60: 暂无 | I60: 暂无 | J60: 0 | K60: 北京 | M60: 便利蜂 | N60: 技术负责人 | O60: 标准会员 | P60: 300 | R60: 0 | S60: - | T60: - | U60: 1 | X60: 1 | AB60: 不续费 | AE60: david.wu@zebraglobalcap.com | AG60: 0 | AH60: 0 | AI60: =AG60+AH60 -> 0
A61: 60 | B61: 42734 | C61: 46203 | D61: 宋书俊 | E61: 男 | G61: 暂无 | I61: 暂无 | J61: １ | K61: 深圳 | M61: 广州爆米科技有限公司 | N61: CTO | O61: 标准会员 | P61: 305 | S61: - | T61: - | U61: 1 | AE61: ssjsj@126.com
A62: 61 | B62: 42739 | C62: 46568 | D62: 孙斌 | E62: 男 | G62: 暂无 | I62: 暂无 | J62: １ | K62: 北京 | M62: 去哪儿网 | N62: 副总裁 | O62: 高级会员 | P62: 308 | Q62: 北京12组 | R62: 0 | S62: - | T62: - | U62: 1 | X62: 1 | AB62: 已续费 | AE62: redboynono@163.com | AG62: 0 | AH62: 0 | AI62: 0 | AJ62: C
A63: 62 | B63: 42758 | C63: 46203 | D63: 杨冀龙 | E63: 男 | G63: 暂无 | I63: 暂无 | J63: 0 | K63: 北京 | M63: 北京知道创宇信息技术有限公司 | N63: CTO+COO | O63: 标准会员 | P63: 318 | Q63: 北京0组 | R63: 0 | S63: - | T63: - | U63: 1 | AB63: 已续费 | AE63: yang@knownsec.com | AG63: 0 | AH63: 0 | AI63: 0 | AJ63: D
A64: 63 | B64: 42779 | C64: 46203 | D64: 余峰 | E64: 男 | G64: 暂无 | I64: 暂无 | J64: １ | K64: 北京 | M64: 汉迪移动互联网科技股份有限公司 | N64: 商业化平台事业部负责人 | O64: 标准会员 | P64: 324 | Q64: 北京13组 | R64: 0 | S64: - | T64: - | U64: 1 | AB64: 已续费 | AE64: feng.yu@ewp-group.com | AG64: 0 | AH64: 0 | AI64: 0 | AJ64: C
A65: 64 | B65: 42782 | C65: 46568 | D65: 陈晨 | E65: 男 | G65: 暂无 | I65: 暂无 | J65: １ | K65: 上海 | M65: 上海慧度至明信息科技有限公司 | N65: 总经理 | O65: 标准会员 | P65: 325 | S65: - | T65: - | U65: 1 | AE65: cchome2002@hotmail.com
A66: 65 | B66: 42783 | C66: 46203 | D66: 林佳齐 | E66: 男 | G66: 暂无 | I66: 暂无 | J66: １ | K66: 杭州 | M66: 西阿爱木 | N66: CEO | O66: 标准会员 | P66: 327 | S66: - | T66: - | U66: 1 | AE66: linjiaqi86@gmail.com
A67: 66 | B67: 42789 | C67: 46203 | D67: 焦洋 | E67: 男 | G67: 暂无 | I67: 暂无 | J67: １ | K67: 北京 | M67: 盖亚互娱 | N67: CTO | O67: 标准会员 | P67: 329 | Q67: 北京12组 | R67: 0 | S67: - | T67: - | U67: 1 | X67: 1 | AB67: 已续费 | AE67: jiao.yang.bupt@gmail.com | AG67: 7 | AH67: 8 | AI67: 15 | AJ67: A
A68: 67 | B68: 42793 | C68: 46203 | D68: 张觅 | E68: 男 | G68: 暂无 | I68: 暂无 | J68: １ | K68: 北京 | M68: 况客科技（北京）有限公司 | N68: 技术总监 | O68: 标准会员 | P68: 332 | Q68: 北京13组 | R68: 0 | S68: - | T68: - | U68: 1 | AB68: 已续费 | AE68: zhm83@163.com | AG68: 0 | AH68: 2 | AI68: 2 | AJ68: C
A69: 68 | B69: 42800 | C69: 46203 | D69: 陈颖棠 | E69: 男 | G69: 暂无 | I69: 暂无 | J69: １ | K69: 广州 | M69: 论客科技（广州）有限公司 | N69: 首席架构师 | O69: 高级会员 | P69: 337 | S69: - | T69: - | U69: 1 | AE69: cyt@mailtech.cn
A70: 69 | B70: 42801 | C70: 46203 | D70: 黎宏伟 | E70: 男 | G70: 暂无 | I70: 暂无 | J70: １ | K70: 成都 | M70: 中科院山地所 | N70: 博士在读 | O70: 标准会员 | P70: 333 | S70: - | T70: - | U70: 1 | AE70: lhwdev@qq.com
A71: 70 | B71: 42807 | C71: 46203 | D71: 李伟辰 | E71: 男 | G71: 暂无 | I71: 暂无 | J71: １ | K71: 北京 | M71: 知道创宇 | N71: 技术VP | O71: 标准会员 | P71: 336 | Q71: 北京12组 | R71: 0 | S71: - | T71: - | U71: 1 | AB71: 已续费 | AE71: liwc@knownsec.com | AG71: 0 | AH71: 0 | AI71: 0 | AJ71: C
A72: 71 | B72: 42807 | C72: 46568 | D72: 郭炜 | E72: 男 | G72: 暂无 | I72: 暂无 | J72: １ | K72: 北京 | M72: 白鲸开源 | N72: CEO | O72: 标准会员 | P72: 335 | Q72: 北京12组 | R72: 0 | S72: - | T72: - | U72: 1 | AB72: 无需续费 | AE72: william.kwok@139.com | AG72: 5 | AH72: 3 | AI72: 8 | AJ72: A
A73: 72 | B73: 42815 | C73: 46203 | D73: 崔浩波 | E73: 男 | G73: 暂无 | I73: 暂无 | J73: １ | K73: 北京 | M73: 嗨学 | N73: CTO | O73: 标准会员 | P73: 340 | Q73: 北京12组 | R73: 0 | S73: - | T73: - | U73: 1 | X73: 1 | AB73: 已续费 | AE73: cuihaobo@gmail.com | AG73: 0 | AH73: 2 | AI73: 2 | AJ73: C
A74: 73 | B74: 42838 | C74: 46568 | D74: 黄玉飞 | E74: 男 | G74: 暂无 | I74: 暂无 | J74: １ | K74: 上海 | M74: 浙江太美医疗科技有限公司 | N74: 副总裁 | O74: 标准会员 | P74: 348 | S74: - | T74: - | U74: 1 | AE74: yufei.huang@mobilemd.cn
A75: 74 | B75: 42838 | C75: 46203 | D75: 任腾 | E75: 男 | G75: 暂无 | I75: 暂无 | J75: １ | K75: 硅谷 | M75: AI Rudder | N75: CEO | O75: 标准会员 | P75: 346 | S75: - | T75: - | U75: 1 | AE75: teng.ren@airudder.com
A76: 75 | B76: 42839 | C76: 46203 | D76: 李晨丰 | E76: 男 | G76: 暂无 | I76: 暂无 | J76: １ | K76: 深圳 | L76: 1 | M76: 深圳米筐科技有限公司 | N76: COO | O76: 标准会员 | P76: 347 | S76: - | T76: - | U76: 1 | AE76: kangol@ricequant.com
A77: 76 | B77: 42849 | C77: 46203 | D77: 钱小军 | E77: 男 | G77: 暂无 | I77: 暂无 | J77: １ | K77: 上海 | M77: 安永中国咨询 | N77: 金融科技咨询经理 | O77: 标准会员 | P77: 349 | S77: - | T77: - | U77: 1 | AE77: abelqian@vip.sina.com
A78: 77 | B78: 42866 | C78: 46203 | D78: 王翱宇 | E78: 男 | G78: 暂无 | I78: 暂无 | J78: １ | K78: 杭州 | M78: 杭州谐云科技有限公司 | N78: CEO | O78: 标准会员 | P78: 356 | S78: - | T78: - | U78: 1 | AE78: way@harmonycloud.cn
A79: 78 | B79: 42912 | C79: 46203 | D79: 徐庆新 | E79: 男 | G79: 暂无 | I79: 暂无 | J79: １ | K79: 苏州 | M79: 苏州乐佰图信息技术有限公司 | N79: 产品总监 | O79: 标准会员 | P79: 3700 | S79: - | T79: - | U79: 1 | AE79: xuqingxin@gmail.com
A80: 79 | B80: 42874 | C80: 46203 | D80: 暨家愉 | E80: 男 | G80: 暂无 | I80: 暂无 | J80: １ | K80: 广州 | M80: 腾讯 | N80: 专家架构师 | O80: 标准会员 | P80: 361 | S80: - | T80: - | U80: 1 | X80: 1 | AE80: jiayu.ji@gmail.com
A81: 80 | B81: 42886 | C81: 46203 | D81: 肖毅 | E81: 男 | G81: 暂无 | I81: 暂无 | J81: １ | K81: 成都 | M81: 成都智客科技有限公司 | N81: CEO | O81: 标准会员 | P81: 362 | S81: - | T81: - | U81: 1 | AE81: xiaoyi@aoasp.com
A82: 81 | B82: 42927 | C82: 46203 | D82: 曹祖鹏 | E82: 男 | G82: 暂无 | I82: 暂无 | J82: １ | K82: 南京 | M82: 南京知亦行信息技术有限公司 | N82: CTO | O82: 标准会员 | P82: 376 | S82: - | T82: - | U82: 1 | AE82: caozupeng@139.com
A83: 82 | B83: 42935 | C83: 46203 | D83: 杨振东 | E83: 男 | G83: 暂无 | I83: 暂无 | J83: １ | K83: 上海 | M83: 上海方亿信息科技有限公司 | N83: 联合创始人&CTO | O83: 高级会员 | P83: 383 | S83: - | T83: - | U83: 1 | AE83: yzd@aso360.com
A84: 83 | B84: 42936 | C84: 46203 | D84: 张志成 | E84: 男 | G84: 暂无 | I84: 暂无 | J84: １ | K84: 杭州 | M84: 阿里巴巴达摩院 | N84: 高级技术专家 | O84: 标准会员 | P84: 388 | S84: - | T84: - | U84: 1 | AE84: zczhang.hvac@gmail.com
A85: 84 | B85: 42940 | C85: 46568 | D85: 任剑钢 | E85: 男 | G85: 暂无 | I85: 暂无 | J85: 无公司 | K85: 上海 | M85: 哔哩哔哩 | N85: 高级技术总监 | O85: 高级会员 | P85: 391 | S85: - | T85: - | U85: 1 | X85: 1 | AE85: renjiangang@bilibili.com
A86: 85 | B86: 42941 | C86: 46203 | D86: 杨红光 | E86: 男 | G86: 暂无 | I86: 暂无 | J86: １ | K86: 北京 | M86: 玲珑卓越科技 | N86: CEO | O86: 标准会员 | P86: 394 | Q86: 北京15组 | R86: 0 | S86: - | T86: - | U86: 1 | AB86: 已续费 | AE86: njyhg@163.com | AG86: 0 | AH86: 1 | AI86: 1 | AJ86: C
A87: 86 | B87: 42954 | C87: 46203 | D87: 杨帅麒 | E87: 男 | G87: 暂无 | I87: 暂无 | J87: １ | K87: 上海 | M87: 上海盛大汽车服务集团 | N87: CTO | O87: 标准会员 | P87: 402 | S87: - | T87: - | U87: 1 | W87: 无地址 | AE87: 408482214@qq.com
A88: 87 | B88: 42957 | C88: 46203 | D88: 胡继伟 | E88: 男 | G88: 暂无 | I88: 暂无 | J88: １ | K88: 北京 | M88: 合思 | N88: 高级技术总监 | O88: 标准会员 | P88: 404 | Q88: 北京15组 | R88: 0 | S88: - | T88: - | U88: 1 | X88: 1 | AB88: 已续费 | AE88: hu_jiwei@foxmail.com | AG88: 2 | AH88: 7 | AI88: 9 | AJ88: B
A89: 88 | B89: 42964 | C89: 46568 | D89: 黄杲 | E89: 男 | G89: 暂无 | I89: 暂无 | J89: １ | K89: 上海 | M89: 上海卓盟信息科技有限公司 | N89: CEO | O89: 标准会员 | P89: 406 | S89: - | T89: - | U89: 1 | AE89: huanggao@excelliance.cn
A90: 89 | B90: 42970 | C90: 46203 | D90: 沈旸 | E90: 男 | G90: 暂无 | I90: 暂无 | J90: 0 | K90: 北京 | M90: 联易融 | N90: 副总裁 | O90: 标准会员 | P90: 407 | Q90: 北京12组 | R90: 0 | S90: - | T90: - | U90: 1 | AB90: 已续费 | AE90: yang.shen.it@gmail.com | AG90: 0 | AH90: 0 | AI90: 0 | AJ90: C
A91: 90 | B91: 42988 | C91: 46203 | D91: 杨威 | E91: 男 | G91: 暂无 | I91: 暂无 | J91: １ | K91: 北京 | M91: 明略科技 | N91: 副总裁 | O91: 标准会员 | P91: 81 | Q91: 北京0组 | R91: 0 | S91: - | T91: - | U91: 1 | AB91: 已续费 | AE91: yangwei@rongcloud.cn | AG91: 0 | AH91: 1 | AI91: 1 | AJ91: D
A92: 91 | B92: 42991 | C92: 46568 | D92: 解安亮 | E92: 男 | G92: 暂无 | I92: 暂无 | J92: １ | K92: 上海 | M92: 谱域科技 | N92: 创始人兼CEO | O92: 标准会员 | P92: 411 | S92: - | T92: - | U92: 1 | AE92: 6123272@qq.com
A93: 92 | B93: 43000 | C93: 46203 | D93: 褚亮 | E93: 男 | G93: 暂无 | I93: 暂无 | J93: １ | K93: 杭州 | M93: 杭州咿啦科技有限公司 | N93: 联合创始人 & CTO | O93: 标准会员 | P93: 418 | S93: - | T93: - | U93: 1 | X93: 1 | AE93: chuliang@ellabook.cn
A94: 93 | B94: 43004 | C94: 46203 | D94: 沈淦 | E94: 男 | G94: 暂无 | I94: 暂无 | J94: １ | K94: 杭州 | M94: 杭州正马软件科技有限公司 | N94: CTO | O94: 标准会员 | P94: 419 | S94: - | T94: - | U94: 1 | AE94: floatin@sina.com
A95: 94 | B95: 43006 | C95: 46203 | D95: 蒋宏飞 | E95: 男 | G95: 暂无 | I95: 暂无 | J95: １ | K95: 北京 | M95: 作业帮 | N95: 高级研发工程师 | O95: 标准会员 | P95: 423 | Q95: 北京16组 | R95: 0 | S95: - | T95: - | U95: 1 | X95: 1 | AB95: 已续费 | AE95: hf.jiang@qq.com | AG95: 0 | AH95: 1 | AI95: 1 | AJ95: C
A96: 95 | B96: 43017 | C96: 46203 | D96: 苏锐 | E96: 男 | G96: 暂无 | I96: 暂无 | J96: １ | K96: 北京 | M96: Juicedata | N96: 合伙人 | O96: 标准会员 | P96: 424 | Q96: 北京0组 | R96: 0 | S96: - | T96: - | U96: 1 | AB96: 已续费 | AE96: suave.su@gmail.com | AG96: 0 | AH96: 1 | AI96: 1 | AJ96: D
A97: 96 | B97: 43051 | C97: 46203 | D97: 王志刚 | E97: 男 | G97: 暂无 | I97: 暂无 | J97: １ | K97: 深圳 | M97: 招商基金 | N97: 副总监 | O97: 标准会员 | P97: 433 | S97: - | T97: - | U97: 1 | X97: 1 | AE97: zhigang78@163.com
A98: 97 | B98: 43069 | C98: 46203 | D98: 欧文盛 | E98: 男 | G98: 暂无 | I98: 暂无 | J98: １ | K98: 北京 | M98: 北京泰迪未来科技股份有限公司 | N98: CTO | O98: 高级会员 | P98: 439 | Q98: 北京33组 | R98: 0 | S98: - | T98: - | U98: 1 | AB98: 已续费 | AE98: ouwensheng@teddymobile.cn | AG98: 0 | AH98: 0 | AI98: 0 | AJ98: C
A99: 98 | B99: 43080 | C99: 46203 | D99: 王浩 | E99: 男 | G99: 暂无 | I99: 暂无 | J99: 0 | K99: 上海 | M99: 贵州小爱机器人科技有限公司 | N99: CTO | O99: 标准会员 | P99: 443 | S99: - | T99: - | U99: 1 | AE99: wanghao@metasigncloud.com
A100: 99 | B100: 43082 | C100: 46203 | D100: 樊伟伟 | E100: 男 | G100: 暂无 | I100: 暂无 | J100: １ | K100: 南京 | M100: 微鲤 | N100: 技术总监 | O100: 标准会员 | P100: 444 | S100: - | T100: - | U100: 1 | AE100: fanweiwei@weli.cn
...

Sheet 会员总表（副本）
A1: 序号 | B1: 加入时间 | C1: 会籍时间 | D1: 姓名 | E1: 性别 | F1: 面试官 | G1: 推荐人 | H1: 推荐大类 | I1: 是否更新 | J1: 地区 | K1: 所在位置 | L1: 公司 | M1: 职位 | N1: 会员类型 | O1: 会员编号 | P1: 是否入组 | Q1: 新会员接待 | R1: 新会员培训时间 | S1: 上线官网 | T1: 新学员见面直播 | U1: 是否续费 | V1: 备注 | W1: 出海 | X1: 加入时长 | Y1: 过期 | Z1: 续费金额 | AA1: 推荐人 | AB1: 推荐大类 | AC1: 邮箱 | AD1: 备注
A2: =ROW()-1 -> 1 | B2: 42129 | C2: 46203 | D2: 艾芙（徐雁斐） | E2: 女 | I2: 1 | J2: 深圳 | L2: 暂无 | M2: 暂无 | N2: 标准会员 | O2: 1 | S2: 1 | X2: =DATEDIF(B2,"2025-6-30","y") -> 10 | AC2: elfe1021@gmail.com
A3: =ROW()-1 -> 2 | B3: 42132 | C3: 46203 | D3: 郭理靖 | E3: 男 | I3: 1 | J3: 杭州 | L3: 奈雪的茶 | M3: CTO | N3: 标准会员 | O3: 2 | R3: - | S3: 1 | V3: 1 | W3: 1 | X3: =DATEDIF(B3,"2025-6-30","y") -> 10 | AC3: guolijing@gmail.com
A4: =ROW()-1 -> 3 | B4: 42139 | C4: 46203 | D4: 陈锡言 | E4: 男 | I4: 无信息0 | J4: 北京 | L4: 一览科技 | M4: CTO | N4: 标准会员 | O4: 5 | P4: 北京0组 | Q4: 0 | R4: - | S4: 1 | W4: 1 | X4: =DATEDIF(B4,"2025-6-30","y") -> 10 | Z4: 已续费 | AC4: cccsmoking@sina.com
A5: =ROW()-1 -> 4 | B5: 42146 | C5: 46203 | D5: 汪威 | E5: 男 | I5: 1 | J5: 北京 | L5: 摩点众筹 | M5: 技术总监 | N5: 高级会员 | O5: 12 | P5: 北京0组 | Q5: 0 | R5: 45120 | S5: 1 | W5: 1 | X5: =DATEDIF(B5,"2025-6-30","y") -> 10 | Z5: 已续费 | AC5: wangcash@gmail.com
A6: =ROW()-1 -> 5 | B6: 42147 | C6: 46203 | D6: 唐小浙 | E6: 男 | I6: 1 | J6: 上海 | L6: 墨誉科技 | M6: 技术vp | N6: 标准会员 | O6: 13 | R6: - | S6: 1 | W6: 1 | X6: =DATEDIF(B6,"2025-6-30","y") -> 10 | AC6: tangxz@gmail.com
A7: =ROW()-1 -> 6 | B7: 42150 | C7: 46203 | D7: 邹光先 | E7: 男 | I7: 0 | J7: 广州 | L7: 其他 | M7: 其他 | N7: 标准会员 | O7: 14 | R7: - | S7: 1 | W7: 1 | X7: =DATEDIF(B7,"2025-6-30","y") -> 10 | AC7: zouguangxian@163.com
A8: =ROW()-1 -> 7 | B8: 42160 | C8: 46203 | D8: 黄良懿 | E8: 男 | I8: 1 | J8: 深圳 | L8: 高仙机器人 | M8: 研发VP | N8: 标准会员 | O8: 17 | R8: - | S8: 1 | W8: 1 | X8: =DATEDIF(B8,"2025-6-30","y") -> 10 | AC8: codeant@hotmail.com
A9: =ROW()-1 -> 8 | B9: 42171 | C9: 46203 | D9: 史海峰 | E9: 男 | I9: 1 | J9: 北京 | L9: 方正证券 | M9: 架构平台负责人 | N9: 标准会员 | O9: 23 | P9: 北京2组 | Q9: 0 | R9: - | S9: 1 | V9: 1 | W9: 1 | X9: =DATEDIF(B9,"2025-6-30","y") -> 10 | Z9: 已续费 | AC9: shihf_dc@163.com
A10: =ROW()-1 -> 9 | B10: 42180 | C10: 46203 | D10: 梁宇鹏 | E10: 男 | I10: 0 | J10: 北京 | L10: 蓝莺IM | M10: CEO | N10: 标准会员 | O10: 24 | P10: 北京2组 | Q10: 0 | R10: - | S10: 1 | W10: 1 | X10: =DATEDIF(B10,"2025-6-30","y") -> 10 | Z10: 已续费 | AC10: eric.l.2046@gmail.com
A11: =ROW()-1 -> 10 | B11: 42202 | C11: 46203 | D11: 熊昌伟 | E11: 男 | I11: 1 | J11: 北京 | L11: 畅捷通信息技术股份有限公司 | M11: 助理总裁 | N11: 标准会员 | O11: 29 | P11: 北京0组 | Q11: 0 | R11: - | S11: 1 | W11: 1 | X11: =DATEDIF(B11,"2025-6-30","y") -> 9 | Z11: 已续费 | AC11: xcw@chanjet.com
A12: =ROW()-1 -> 11 | B12: 42209 | C12: 46203 | D12: 丁宁 | E12: 男 | I12: 无公司 | J12: 新加坡 | L12: 荔枝集团 | M12: CTO | N12: 高级会员 | O12: 30 | R12: 45154 | S12: 1 | V12: 1 | W12: 1 | X12: =DATEDIF(B12,"2025-6-30","y") -> 9 | AC12: dingning@lizhi.fm
A13: =ROW()-1 -> 12 | B13: 42219 | C13: 46203 | D13: 陈靖华 | E13: 男 | I13: 1 | J13: 北京 | L13: 基调听云 | M13: 产品VP | N13: 标准会员 | O13: 34 | P13: 北京2组 | Q13: 0 | R13: - | S13: 1 | W13: 1 | X13: =DATEDIF(B13,"2025-6-30","y") -> 9 | Z13: 已续费 | AC13: wood@tingyun.com
A14: =ROW()-1 -> 13 | B14: 42221 | C14: 46203 | D14: 侯冬雯 | E14: 女 | I14: 无公司 | J14: 北京 | L14: 北京微梦传媒股份有限公司 | M14: CTO | N14: 高级会员 | O14: 38 | P14: 北京0组 | Q14: 0 | R14: - | S14: 1 | W14: 1 | X14: =DATEDIF(B14,"2025-6-30","y") -> 9 | Z14: 已续费 | AC14: dongwen@microdreams.com.cn
A15: =ROW()-1 -> 14 | B15: 42246 | C15: 46203 | D15: 黄彬彬 | E15: 男 | I15: 1 | J15: 上海 | L15: 多云转晴 | M15: 架构师 | N15: 高级会员 | O15: 44 | R15: - | S15: 1 | W15: 1 | X15: =DATEDIF(B15,"2025-6-30","y") -> 9 | AC15: 118733@qq.com
A16: =ROW()-1 -> 15 | B16: 42248 | C16: 46203 | D16: 王立博 | E16: 男 | I16: 1 | J16: 上海 | L16: 未来保贝 | M16: 合伙人&CTO | N16: 标准会员 | O16: 48 | R16: - | S16: 1 | W16: 1 | X16: =DATEDIF(B16,"2025-6-30","y") -> 9 | AC16: w803007@163.com
A17: =ROW()-1 -> 16 | B17: 42256 | C17: 46203 | D17: 胡震 | E17: 男 | I17: 1 | J17: 上海 | L17: 某公链基金会 | M17: 投研负责人 | N17: 标准会员 | O17: 58 | R17: - | S17: 1 | W17: 1 | X17: =DATEDIF(B17,"2025-6-30","y") -> 9 | AC17: huzhencn@163.com
A18: =ROW()-1 -> 17 | B18: 42275 | C18: 46203 | D18: 洪强宁 | E18: 男 | I18: 1 | J18: 北京 | L18: 雅识科技联合 | M18: 创始人兼CTO | N18: 标准会员 | O18: 65 | P18: 北京2组 | Q18: 0 | R18: - | S18: 1 | W18: 1 | X18: =DATEDIF(B18,"2025-6-30","y") -> 9 | Z18: 已续费 | AC18: hongqn@gmail.com
A19: =ROW()-1 -> 18 | B19: 42298 | C19: 46203 | D19: 李道兵 | E19: 男 | I19: 1 | J19: 北京 | L19: Principal Embedded Software Developer | M19: 未登记 | N19: 标准会员 | O19: 70 | P19: 北京13组 | Q19: 0 | R19: - | S19: 1 | W19: 1 | X19: =DATEDIF(B19,"2025-6-30","y") -> 9 | Z19: 无需续费 | AC19: lidaobing@gmail.com
A20: =ROW()-1 -> 19 | B20: 42300 | C20: 46203 | D20: 张海龙 | E20: 男 | I20: 1 | J20: 苏州 | L20: 同程旅行 | M20: 技术委员会主任 | N20: 标准会员 | O20: 72 | R20: - | S20: 1 | V20: 1 | W20: 1 | X20: =DATEDIF(B20,"2025-6-30","y") -> 9 | AC20: zhanghailong@coding.net
A21: =ROW()-1 -> 20 | B21: 42300 | C21: 46203 | D21: 王晓波 | E21: 男 | I21: 0 | J21: 苏州 | L21: 同程旅行 | M21: AVP&出行事业群 CTO | N21: 标准会员 | O21: 71 | R21: - | S21: 1 | W21: 1 | X21: =DATEDIF(B21,"2025-6-30","y") -> 9 | AC21: wxb09195@ly.com
A22: =ROW()-1 -> 21 | B22: 42318 | C22: 46203 | D22: 林华根 | E22: 男 | I22: 1 | J22: 深圳 | L22: 安徽超远信息技术有限公司 | M22: 副总工程师 | N22: 标准会员 | O22: 78 | R22: - | S22: 1 | W22: 1 | X22: =DATEDIF(B22,"2025-6-30","y") -> 9 | AC22: lhg@cychina.cn
A23: =ROW()-1 -> 22 | B23: 42334 | C23: 46203 | D23: 魏吉贺 | E23: 男 | I23: 1 | J23: 深圳 | L23: 深圳市残友软件股份有限公司 | M23: 技术总监 | N23: 标准会员 | O23: 91 | R23: - | S23: 1 | W23: 1 | X23: =DATEDIF(B23,"2025-6-30","y") -> 9 | AC23: wjh@canyou.cn
A24: =ROW()-1 -> 23 | B24: 42339 | C24: 46203 | D24: 龚银 | E24: 男 | I24: 1 | J24: 深圳 | L24: 安克创新 | M24: CIO | N24: 标准会员 | O24: 95 | R24: - | S24: 1 | W24: 1 | X24: =DATEDIF(B24,"2025-6-30","y") -> 9 | AC24: gongyin@126.com
A25: =ROW()-1 -> 24 | B25: 42361 | C25: 46203 | D25: 华健 | E25: 男 | I25: 1 | J25: 北京 | L25: 梦诚科技 | M25: 创始人&CTO | N25: 标准会员 | O25: 102 | P25: 北京2组 | Q25: 0 | R25: - | S25: 1 | W25: 1 | X25: =DATEDIF(B25,"2025-6-30","y") -> 9 | Z25: 已续费 | AC25: huaj1101@qq.com
A26: =ROW()-1 -> 25 | B26: 42427 | C26: 46203 | D26: 何世友 | E26: 男 | I26: 1 | J26: 广州 | L26: 腾讯云 | M26: Serverless 产品负责人 | N26: 标准会员 | O26: 114 | R26: - | S26: 1 | W26: 1 | X26: =DATEDIF(B26,"2025-6-30","y") -> 9 | AC26: shiyou.he@gmail.com
A27: =ROW()-1 -> 26 | B27: 42433 | C27: 46203 | D27: 李玉福 | E27: 男 | I27: 1 | J27: 北京 | L27: 北京农信互联科技有限公司 | M27: 副总裁 | N27: 标准会员 | O27: 117 | P27: 北京15组 | Q27: 0 | R27: - | S27: 1 | W27: 1 | X27: =DATEDIF(B27,"2025-6-30","y") -> 9 | Z27: 已续费 | AC27: liyufu@nxin.com
A28: =ROW()-1 -> 27 | B28: 42451 | C28: 46203 | D28: 曾冠东 | E28: 男 | I28: 0 | J28: 广州 | L28: 酷狗音乐 | M28: 繁星网研发总监 | N28: 标准会员 | O28: 123 | R28: - | S28: 1 | V28: 1 | W28: 1 | X28: =DATEDIF(B28,"2025-6-30","y") -> 9 | AC28: popeast@gmail.com
A29: =ROW()-1 -> 28 | B29: 42451 | C29: 46203 | D29: 路文杰 | E29: 男 | I29: 1 | J29: 广州 | L29: 甘果科技 | M29: CEO | N29: 标准会员 | O29: 121 | R29: - | S29: 1 | X29: =DATEDIF(B29,"2025-6-30","y") -> 9 | AC29: cngump@gmail.com
A30: =ROW()-1 -> 29 | B30: 42473 | C30: 46203 | D30: 高楚涛 | E30: 男 | I30: 1 | J30: 深圳 | L30: 深圳市嘉立创科技发展有限公司 | M30: CIO | N30: 标准会员 | O30: 135 | R30: - | S30: 1 | W30: 1 | X30: =DATEDIF(B30,"2025-6-30","y") -> 9 | AC30: gaochutao@163.com
A31: =ROW()-1 -> 30 | B31: 42480 | C31: 46203 | D31: 刘建国 | E31: 男 | I31: 1 | J31: 广州 | K31: 1 | L31: 伊智信息科技 | M31: CEO | N31: 标准会员 | O31: 26 | R31: - | S31: 1 | W31: 1 | X31: =DATEDIF(B31,"2025-6-30","y") -> 9 | AC31: yijshu@gmail.com
A32: =ROW()-1 -> 31 | B32: 42482 | C32: 46203 | D32: 万林涛 | E32: 男 | I32: 1 | J32: 上海 | L32: 上海蔚星数据 | M32: 副总裁兼首席数据官 | N32: 标准会员 | O32: 140 | R32: - | S32: 1 | W32: 1 | X32: =DATEDIF(B32,"2025-6-30","y") -> 9 | AC32: lintao.wan@outlook.com
A33: =ROW()-1 -> 32 | B33: 42482 | C33: 46203 | D33: 徐翎 | E33: 男 | I33: 1 | J33: 上海 | L33: 上海数达物流科技有限公司 | M33: CTO | N33: 标准会员 | O33: 139 | R33: - | S33: 1 | X33: =DATEDIF(B33,"2025-6-30","y") -> 9 | AC33: xlshcn@hotmail.com
A34: =ROW()-1 -> 33 | B34: 42495 | C34: 46203 | D34: 肖颖 | E34: 男 | I34: １ | J34: 上海 | L34: 上海澄廓信息科技有限公司 | M34: CEO | N34: 标准会员 | O34: 144 | R34: - | S34: 1 | X34: =DATEDIF(B34,"2025-6-30","y") -> 9 | AC34: 18049722632@163.com
A35: =ROW()-1 -> 34 | B35: 42524 | C35: 46203 | D35: 张剑伟 | E35: 男 | I35: １ | J35: 上海 | L35: 百安居 | M35: CTO | N35: 标准会员 | O35: 160 | R35: - | S35: 1 | X35: =DATEDIF(B35,"2025-6-30","y") -> 9 | AC35: zjwsoft@gmail.com
A36: =ROW()-1 -> 35 | B36: 42536 | C36: 46203 | D36: 苏煦烽 | E36: 男 | I36: １ | J36: 广州 | K36: 1 | L36: 亲邻科技 | M36: 技术总监 | N36: 标准会员 | O36: 167 | R36: - | S36: 1 | W36: 1 | X36: =DATEDIF(B36,"2025-6-30","y") -> 9 | AC36: suxufeng@qq.com
A37: =ROW()-1 -> 36 | B37: 42537 | C37: 46203 | D37: 孙其瑞 | E37: 男 | I37: １ | J37: 杭州 | L37: 苏州优频科技有限公司 | M37: CTO | N37: 标准会员 | O37: 171 | R37: - | S37: 1 | W37: 1 | X37: =DATEDIF(B37,"2025-6-30","y") -> 9 | AC37: sqr@detu.com
A38: =ROW()-1 -> 37 | B38: 42552 | C38: 46203 | D38: 芦宇峰 | E38: 男 | I38: １ | J38: 杭州 | L38: 上海擎路科技 | M38: 联合创始人 & CTO | N38: 标准会员 | O38: 178 | R38: - | S38: 1 | W38: 1 | X38: =DATEDIF(B38,"2025-6-30","y") -> 8 | AC38: xiao_ys@163.com
A39: =ROW()-1 -> 38 | B39: 42556 | C39: 46203 | D39: 陈杰 | E39: 男 | I39: １ | J39: 上海 | L39: 上海领健信息技术有限公司 | M39: CTO | N39: 标准会员 | O39: 188 | R39: - | S39: 0 | X39: =DATEDIF(B39,"2025-6-30","y") -> 8 | AC39: alan.chen@linkedcare.cn
A40: =ROW()-1 -> 39 | B40: 42559 | C40: 46203 | D40: 黄伟坚 | E40: 男 | I40: １ | J40: 广州 | K40: 1 | L40: mobvista汇量科技 | M40: 联合创始人 | N40: 标准会员 | O40: 190 | R40: - | S40: 1 | W40: 1 | X40: =DATEDIF(B40,"2025-6-30","y") -> 8 | AC40: hwjian@126.com
A41: =ROW()-1 -> 40 | B41: 42559 | C41: 46203 | D41: 黄勇 | E41: 男 | I41: １ | J41: 上海 | L41: 阅流 | M41: CTO | N41: 标准会员 | O41: 191 | R41: - | S41: 1 | W41: 1 | X41: =DATEDIF(B41,"2025-6-30","y") -> 8 | AC41: hy_think@163.com
A42: =ROW()-1 -> 41 | B42: 42562 | C42: 46203 | D42: 奚铭皋 | E42: 男 | I42: １ | J42: 上海 | L42: 比图科技 | M42: Tech Lead | N42: 标准会员 | O42: 193 | R42: - | S42: 1 | X42: =DATEDIF(B42,"2025-6-30","y") -> 8 | AC42: minggao.xi@gmail.com
A43: =ROW()-1 -> 42 | B43: 42562 | C43: 46203 | D43: 陆云昆 | E43: 男 | I43: １ | J43: 上海 | L43: 上海钢蜂信息科技有限公司 | M43: CTO | N43: 标准会员 | O43: 194 | R43: - | S43: 1 | W43: 1 | X43: =DATEDIF(B43,"2025-6-30","y") -> 8 | AC43: ykdoubles@hotmail.com
A44: =ROW()-1 -> 43 | B44: 42576 | C44: 45838 | D44: 陈峰 | E44: 男 | I44: １ | J44: 北京 | L44: Red Hat | M44: 研发经理 | N44: 标准会员 | O44: 521 | Q44: 0 | R44: - | S44: 1 | W44: 1 | X44: =DATEDIF(B44,"2025-6-30","y") -> 8 | Z44: 待定 | AC44: bitchenfeng@vip.sina.com
A45: =ROW()-1 -> 44 | B45: 42589 | C45: 46203 | D45: 张志合 | E45: 男 | I45: １ | J45: 广州 | L45: 广州卓越教育 | M45: 资深IT总监 | N45: 标准会员 | O45: 210 | R45: - | S45: 1 | V45: 1 | X45: =DATEDIF(B45,"2025-6-30","y") -> 8 | AC45: kaffeel@163.com
A46: =ROW()-1 -> 45 | B46: 42597 | C46: 46203 | D46: 谢金牛 | E46: 男 | I46: １ | J46: 广州 | L46: 深圳风信计算机服务有限公司 | M46: 总经理 | N46: 标准会员 | O46: 222 | R46: - | S46: 1 | W46: 1 | X46: =DATEDIF(B46,"2025-6-30","y") -> 8 | AC46: 115617486@qq.com
A47: =ROW()-1 -> 46 | B47: 42613 | C47: 46203 | D47: 廖雄杰 | E47: 男 | I47: １ | J47: 北京 | L47: 北京基调网络股份有限公司 | M47: 研发副总裁 | N47: 标准会员 | O47: 233 | P47: 北京0组 | Q47: 0 | R47: - | S47: 1 | X47: =DATEDIF(B47,"2025-6-30","y") -> 8 | Z47: 已续费 | AC47: liaoxj@tingyun.com
A48: =ROW()-1 -> 47 | B48: 42631 | C48: 46203 | D48: 伍涛 | E48: 男 | I48: １ | J48: 上海 | L48: Funplus | M48: Co-CTO | N48: 标准会员 | O48: 242 | R48: - | S48: 1 | V48: 1 | W48: 1 | X48: =DATEDIF(B48,"2025-6-30","y") -> 8 | AC48: tonywutao@gmail.com
A49: =ROW()-1 -> 48 | B49: 42657 | C49: 46203 | D49: 张飞 | E49: 男 | I49: １ | J49: 上海 | L49: vivo | M49: 部门总经理 | N49: 标准会员 | O49: 253 | R49: - | S49: 1 | V49: 1 | W49: 1 | X49: =DATEDIF(B49,"2025-6-30","y") -> 8 | AC49: zgfi@163.com
A50: =ROW()-1 -> 49 | B50: 42667 | C50: 46203 | D50: 卢亿雷 | E50: 男 | I50: １ | J50: 北京 | L50: 北京白海科技有限公司 | M50: 创始人&CEO | N50: 高级会员 | O50: 258 | P50: 北京24组 | Q50: 0 | R50: - | S50: 1 | W50: 1 | X50: =DATEDIF(B50,"2025-6-30","y") -> 8 | Z50: 无需续费 | AC50: johnlya@163.com
A51: =ROW()-1 -> 50 | B51: 42667 | C51: 46203 | D51: 洪倍 | E51: 男 | I51: １ | J51: 上海 | L51: ValueZ智库 | M51: 创始人、合伙人 | N51: 标准会员 | O51: 259 | R51: - | S51: 1 | X51: =DATEDIF(B51,"2025-6-30","y") -> 8 | AC51: bh@roomwits.com
A52: =ROW()-1 -> 51 | B52: 42695 | C52: 46203 | D52: 王河生 | E52: 男 | I52: 无公司 | J52: 南京 | L52: 南京四维向量科技有限公司 | M52: 创始人&CEO | N52: 标准会员 | O52: 268 | R52: - | S52: 1 | X52: =DATEDIF(B52,"2025-6-30","y") -> 8 | AC52: 4005958@qq.com
A53: =ROW()-1 -> 52 | B53: 42698 | C53: 46203 | D53: 何德照 | E53: 男 | I53: １ | J53: 深圳 | L53: AfterShip | M53: 技术VP | N53: 标准会员 | O53: 269 | R53: - | S53: 1 | W53: 1 | X53: =DATEDIF(B53,"2025-6-30","y") -> 8 | AC53: dezhaohe@qq.com
A54: =ROW()-1 -> 53 | B54: 42706 | C54: 45838 | D54: 张呈刚 | E54: 男 | I54: １ | J54: 深圳 | L54: AWS | M54: 架构师经理 | N54: 标准会员 | O54: 273 | R54: - | S54: 1 | W54: 1 | X54: =DATEDIF(B54,"2025-6-30","y") -> 8 | AC54: 470344500@qq.com
A55: =ROW()-1 -> 54 | B55: 42723 | C55: 46203 | D55: 练海荣 | E55: 男 | I55: １ | J55: 苏州 | L55: 龙石数据 | M55: 总经理 | N55: 标准会员 | O55: 283 | R55: - | S55: 1 | W55: 1 | X55: =DATEDIF(B55,"2025-6-30","y") -> 8 | AC55: hairong_lian@163.com
A56: =ROW()-1 -> 55 | B56: 42730 | C56: 46203 | D56: 冯斌 | E56: 男 | I56: １ | J56: 深圳 | L56: ONES | M56: CTO | N56: 高级会员 | O56: 295 | R56: - | S56: 1 | V56: 1 | W56: 1 | X56: =DATEDIF(B56,"2025-6-30","y") -> 8 | AC56: 13918821015@139.com
A57: =ROW()-1 -> 56 | B57: 42730 | C57: 46934 | D57: 朱攀 | E57: 男 | I57: １ | J57: 上海 | L57: 阿旅科技 | M57: CEO | N57: 标准会员 | O57: 292 | R57: - | S57: 1 | X57: =DATEDIF(B57,"2025-6-30","y") -> 8 | AC57: panos.zhu@qq.com
A58: =ROW()-1 -> 57 | B58: 42730 | C58: 46203 | D58: 贾锦杰 | E58: 男 | I58: １ | J58: 广州 | L58: KEEP | M58: 战略 & PMO leader | N58: 标准会员 | O58: 291 | P58: 北京0组 | R58: - | S58: 1 | V58: 1 | X58: =DATEDIF(B58,"2025-6-30","y") -> 8 | Z58: 已续费 | AC58: jiajinjie@gmail.com
A59: =ROW()-1 -> 58 | B59: 42731 | C59: 46203 | D59: 李卓 | E59: 男 | I59: １ | J59: 杭州 | L59: 道富信息科技 | M59: 董事总经理 | N59: 高级会员 | O59: 297 | R59: - | S59: 1 | X59: =DATEDIF(B59,"2025-6-30","y") -> 8 | AC59: me@milanello1998.com
A60: =ROW()-1 -> 59 | B60: 42733 | C60: 45838 | D60: 吴永强 | E60: 男 | I60: 0 | J60: 北京 | L60: 便利蜂 | M60: 技术负责人 | N60: 标准会员 | O60: 300 | Q60: 0 | R60: - | S60: 1 | V60: 1 | X60: =DATEDIF(B60,"2025-6-30","y") -> 8 | Z60: 不续费 | AC60: david.wu@zebraglobalcap.com
A61: =ROW()-1 -> 60 | B61: 42734 | C61: 46203 | D61: 宋书俊 | E61: 男 | I61: １ | J61: 深圳 | L61: 广州爆米科技有限公司 | M61: CTO | N61: 标准会员 | O61: 305 | R61: - | S61: 1 | X61: =DATEDIF(B61,"2025-6-30","y") -> 8 | AC61: ssjsj@126.com
A62: =ROW()-1 -> 61 | B62: 42739 | C62: 46568 | D62: 孙斌 | E62: 男 | I62: １ | J62: 北京 | L62: 去哪儿网 | M62: 副总裁 | N62: 高级会员 | O62: 308 | P62: 北京12组 | Q62: 0 | R62: - | S62: 1 | V62: 1 | X62: =DATEDIF(B62,"2025-6-30","y") -> 8 | Z62: 已续费 | AC62: redboynono@163.com
A63: =ROW()-1 -> 62 | B63: 42758 | C63: 46203 | D63: 杨冀龙 | E63: 男 | I63: 0 | J63: 北京 | L63: 北京知道创宇信息技术有限公司 | M63: CTO+COO | N63: 标准会员 | O63: 318 | P63: 北京0组 | Q63: 0 | R63: - | S63: 1 | X63: =DATEDIF(B63,"2025-6-30","y") -> 8 | Z63: 已续费 | AC63: yang@knownsec.com
A64: =ROW()-1 -> 63 | B64: 42779 | C64: 46203 | D64: 余峰 | E64: 男 | I64: １ | J64: 北京 | L64: 汉迪科技 | M64: 商业化平台事业部负责人 | N64: 标准会员 | O64: 324 | P64: 北京13组 | Q64: 0 | R64: - | S64: 1 | X64: =DATEDIF(B64,"2025-6-30","y") -> 8 | Z64: 已续费 | AC64: feng.yu@ewp-group.com
A65: =ROW()-1 -> 64 | B65: 42782 | C65: 46568 | D65: 陈晨 | E65: 男 | I65: １ | J65: 上海 | L65: 上海慧度至明信息科技有限公司 | M65: 总经理 | N65: 标准会员 | O65: 325 | R65: - | S65: 1 | X65: =DATEDIF(B65,"2025-6-30","y") -> 8 | AC65: cchome2002@hotmail.com
A66: =ROW()-1 -> 65 | B66: 42783 | C66: 46203 | D66: 林佳齐 | E66: 男 | I66: １ | J66: 杭州 | L66: 西阿爱木 | M66: CEO | N66: 标准会员 | O66: 327 | R66: - | S66: 1 | X66: =DATEDIF(B66,"2025-6-30","y") -> 8 | AC66: linjiaqi86@gmail.com
A67: =ROW()-1 -> 66 | B67: 42789 | C67: 46203 | D67: 焦洋 | E67: 男 | I67: １ | J67: 北京 | L67: 盖娅互娱 | M67: CTO | N67: 标准会员 | O67: 329 | P67: 北京12组 | Q67: 0 | R67: - | S67: 1 | V67: 1 | X67: =DATEDIF(B67,"2025-6-30","y") -> 8 | Z67: 已续费 | AC67: jiao.yang.bupt@gmail.com
A68: =ROW()-1 -> 67 | B68: 42793 | C68: 46203 | D68: 张觅 | E68: 男 | I68: １ | J68: 北京 | L68: 况客科技 | M68: 技术合伙人 | N68: 标准会员 | O68: 332 | P68: 北京13组 | Q68: 0 | R68: - | S68: 1 | X68: =DATEDIF(B68,"2025-6-30","y") -> 8 | Z68: 已续费 | AC68: zhm83@163.com
A69: =ROW()-1 -> 68 | B69: 42800 | C69: 46203 | D69: 陈颖棠 | E69: 男 | I69: １ | J69: 广州 | L69: 论客科技（广州）有限公司 | M69: 首席架构师 | N69: 高级会员 | O69: 337 | R69: - | S69: 1 | X69: =DATEDIF(B69,"2025-6-30","y") -> 8 | AC69: cyt@mailtech.cn
A70: =ROW()-1 -> 69 | B70: 42801 | C70: 46203 | D70: 黎宏伟 | E70: 男 | I70: １ | J70: 成都 | L70: 成都市美幻科技有限公司 | M70: 技术总监 | N70: 标准会员 | O70: 333 | R70: - | S70: 1 | X70: =DATEDIF(B70,"2025-6-30","y") -> 8 | AC70: lhwdev@qq.com
A71: =ROW()-1 -> 70 | B71: 42807 | C71: 46203 | D71: 李伟辰 | E71: 男 | I71: １ | J71: 北京 | L71: 北京知道创宇信息技术有限公司 | M71: 技术VP | N71: 标准会员 | O71: 336 | P71: 北京12组 | Q71: 0 | R71: - | S71: 1 | X71: =DATEDIF(B71,"2025-6-30","y") -> 8 | Z71: 已续费 | AC71: liwc@knownsec.com
A72: =ROW()-1 -> 71 | B72: 42807 | C72: 46568 | D72: 郭炜 | E72: 男 | I72: １ | J72: 北京 | L72: 白鲸开源 | M72: CEO | N72: 标准会员 | O72: 335 | P72: 北京12组 | Q72: 0 | R72: - | S72: 1 | X72: =DATEDIF(B72,"2025-6-30","y") -> 8 | Z72: 无需续费 | AC72: william.kwok@139.com
A73: =ROW()-1 -> 72 | B73: 42815 | C73: 46203 | D73: 崔浩波 | E73: 男 | I73: １ | J73: 北京 | L73: 北京嗨学网教育科技有限公司 | M73: CTO | N73: 标准会员 | O73: 340 | P73: 北京12组 | Q73: 0 | R73: - | S73: 1 | V73: 1 | X73: =DATEDIF(B73,"2025-6-30","y") -> 8 | Z73: 已续费 | AC73: cuihaobo@gmail.com
A74: =ROW()-1 -> 73 | B74: 42838 | C74: 46568 | D74: 黄玉飞 | E74: 男 | I74: １ | J74: 上海 | L74: 浙江太美医疗科技有限公司 | M74: 副总裁 | N74: 标准会员 | O74: 348 | R74: - | S74: 1 | X74: =DATEDIF(B74,"2025-6-30","y") -> 8 | AC74: yufei.huang@mobilemd.cn
A75: =ROW()-1 -> 74 | B75: 42838 | C75: 46203 | D75: 任腾 | E75: 男 | I75: １ | J75: 硅谷 | L75: AI Rudder | M75: CEO | N75: 标准会员 | O75: 346 | R75: - | S75: 1 | X75: =DATEDIF(B75,"2025-6-30","y") -> 8 | AC75: teng.ren@airudder.com
A76: =ROW()-1 -> 75 | B76: 42839 | C76: 46203 | D76: 李晨丰 | E76: 男 | I76: １ | J76: 深圳 | K76: 1 | L76: 深圳米筐科技有限公司 | M76: COO | N76: 标准会员 | O76: 347 | R76: - | S76: 1 | X76: =DATEDIF(B76,"2025-6-30","y") -> 8 | AC76: kangol@ricequant.com
A77: =ROW()-1 -> 76 | B77: 42849 | C77: 46203 | D77: 钱小军 | E77: 男 | I77: １ | J77: 上海 | L77: 安永中国咨询 | M77: 金融科技咨询经理 | N77: 标准会员 | O77: 349 | R77: - | S77: 1 | X77: =DATEDIF(B77,"2025-6-30","y") -> 8 | AC77: abelqian@vip.sina.com
A78: =ROW()-1 -> 77 | B78: 42866 | C78: 46203 | D78: 王翱宇 | E78: 男 | I78: １ | J78: 杭州 | L78: 杭州谐云科技有限公司 | M78: CEO | N78: 标准会员 | O78: 356 | R78: - | S78: 1 | X78: =DATEDIF(B78,"2025-6-30","y") -> 8 | AC78: way@harmonycloud.cn
A79: =ROW()-1 -> 78 | B79: 42912 | C79: 46203 | D79: 徐庆新 | E79: 男 | I79: １ | J79: 苏州 | L79: 苏州乐佰图信息技术有限公司 | M79: 产品总监 | N79: 标准会员 | O79: 3700 | R79: - | S79: 1 | X79: =DATEDIF(B79,"2025-6-30","y") -> 8 | AC79: xuqingxin@gmail.com
A80: =ROW()-1 -> 79 | B80: 42874 | C80: 46203 | D80: 暨家愉 | E80: 男 | I80: １ | J80: 广州 | L80: 腾讯 | M80: 专家架构师 | N80: 标准会员 | O80: 361 | R80: - | S80: 1 | V80: 1 | X80: =DATEDIF(B80,"2025-6-30","y") -> 8 | AC80: jiayu.ji@gmail.com
A81: =ROW()-1 -> 80 | B81: 42886 | C81: 46203 | D81: 肖毅 | E81: 男 | I81: １ | J81: 成都 | L81: 成都智客科技有限公司 | M81: CEO | N81: 标准会员 | O81: 362 | R81: - | S81: 1 | X81: =DATEDIF(B81,"2025-6-30","y") -> 8 | AC81: xiaoyi@aoasp.com
A82: =ROW()-1 -> 81 | B82: 42927 | C82: 46203 | D82: 曹祖鹏 | E82: 男 | I82: １ | J82: 南京 | L82: 南京知亦行信息技术有限公司 | M82: CTO | N82: 标准会员 | O82: 376 | R82: - | S82: 1 | X82: =DATEDIF(B82,"2025-6-30","y") -> 7 | AC82: caozupeng@139.com
A83: =ROW()-1 -> 82 | B83: 42935 | C83: 46203 | D83: 杨振东 | E83: 男 | I83: １ | J83: 上海 | L83: 上海方亿信息科技有限公司 | M83: 联合创始人&CTO | N83: 高级会员 | O83: 383 | R83: - | S83: 1 | X83: =DATEDIF(B83,"2025-6-30","y") -> 7 | AC83: yzd@aso360.com
A84: =ROW()-1 -> 83 | B84: 42936 | C84: 46203 | D84: 张志成 | E84: 男 | I84: １ | J84: 杭州 | L84: 阿里巴巴达摩院 | M84: 高级技术专家 | N84: 标准会员 | O84: 388 | R84: - | S84: 1 | X84: =DATEDIF(B84,"2025-6-30","y") -> 7 | AC84: zczhang.hvac@gmail.com
A85: =ROW()-1 -> 84 | B85: 42940 | C85: 46568 | D85: 任剑钢 | E85: 男 | I85: 无公司 | J85: 上海 | L85: 哔哩哔哩 | M85: 高级技术总监 | N85: 高级会员 | O85: 391 | R85: - | S85: 1 | V85: 1 | X85: =DATEDIF(B85,"2025-6-30","y") -> 7 | AC85: renjiangang@bilibili.com
A86: =ROW()-1 -> 85 | B86: 42941 | C86: 46203 | D86: 杨红光 | E86: 男 | I86: １ | J86: 北京 | L86: 1Box | M86: CTO | N86: 标准会员 | O86: 394 | P86: 北京15组 | Q86: 0 | R86: - | S86: 1 | X86: =DATEDIF(B86,"2025-6-30","y") -> 7 | Z86: 已续费 | AC86: njyhg@163.com
A87: =ROW()-1 -> 86 | B87: 42954 | C87: 46203 | D87: 杨帅麒 | E87: 男 | I87: １ | J87: 上海 | L87: 上海盛大汽车服务集团 | M87: CTO | N87: 标准会员 | O87: 402 | R87: - | S87: 1 | U87: 无地址 | X87: =DATEDIF(B87,"2025-6-30","y") -> 7 | AC87: 408482214@qq.com
A88: =ROW()-1 -> 87 | B88: 42957 | C88: 46203 | D88: 胡继伟 | E88: 男 | I88: １ | J88: 北京 | L88: 合思 | M88: 架构师 | N88: 标准会员 | O88: 404 | P88: 北京15组 | Q88: 0 | R88: - | S88: 1 | V88: 1 | X88: =DATEDIF(B88,"2025-6-30","y") -> 7 | Z88: 已续费 | AC88: hu_jiwei@foxmail.com
A89: =ROW()-1 -> 88 | B89: 42964 | C89: 46568 | D89: 黄杲 | E89: 男 | I89: １ | J89: 上海 | L89: 上海卓盟信息科技有限公司 | M89: CEO | N89: 标准会员 | O89: 406 | R89: - | S89: 1 | X89: =DATEDIF(B89,"2025-6-30","y") -> 7 | AC89: huanggao@excelliance.cn
A90: =ROW()-1 -> 89 | B90: 42970 | C90: 46203 | D90: 沈旸 | E90: 男 | I90: 0 | J90: 北京 | L90: 联易融 | M90: 副总裁 | N90: 标准会员 | O90: 407 | P90: 北京12组 | Q90: 0 | R90: - | S90: 1 | X90: =DATEDIF(B90,"2025-6-30","y") -> 7 | Z90: 已续费 | AC90: yang.shen.it@gmail.com
A91: =ROW()-1 -> 90 | B91: 42988 | C91: 46203 | D91: 杨威 | E91: 男 | I91: １ | J91: 北京 | L91: 明略科技 | M91: 技术副总裁 | N91: 标准会员 | O91: 81 | P91: 北京0组 | Q91: 0 | R91: - | S91: 1 | X91: =DATEDIF(B91,"2025-6-30","y") -> 7 | Z91: 已续费 | AC91: yangwei@rongcloud.cn
A92: =ROW()-1 -> 91 | B92: 42991 | C92: 46568 | D92: 解安亮 | E92: 男 | I92: １ | J92: 上海 | L92: 谱域科技 | M92: 创始人兼CEO | N92: 标准会员 | O92: 411 | R92: - | S92: 1 | X92: =DATEDIF(B92,"2025-6-30","y") -> 7 | AC92: 6123272@qq.com
A93: =ROW()-1 -> 92 | B93: 43000 | C93: 46203 | D93: 褚亮 | E93: 男 | I93: １ | J93: 杭州 | L93: 杭州咿啦科技有限公司 | M93: 联合创始人 & CTO | N93: 标准会员 | O93: 418 | R93: - | S93: 1 | V93: 1 | X93: =DATEDIF(B93,"2025-6-30","y") -> 7 | AC93: chuliang@ellabook.cn
A94: =ROW()-1 -> 93 | B94: 43004 | C94: 46203 | D94: 沈淦 | E94: 男 | I94: １ | J94: 杭州 | L94: 杭州正马软件科技有限公司 | M94: CTO | N94: 标准会员 | O94: 419 | R94: - | S94: 1 | X94: =DATEDIF(B94,"2025-6-30","y") -> 7 | AC94: floatin@sina.com
A95: =ROW()-1 -> 94 | B95: 43006 | C95: 46203 | D95: 蒋宏飞 | E95: 男 | I95: １ | J95: 北京 | L95: 作业帮 | M95: 研究员 | N95: 标准会员 | O95: 423 | P95: 北京16组 | Q95: 0 | R95: - | S95: 1 | V95: 1 | X95: =DATEDIF(B95,"2025-6-30","y") -> 7 | Z95: 已续费 | AC95: hf.jiang@qq.com
A96: =ROW()-1 -> 95 | B96: 43017 | C96: 46203 | D96: 苏锐 | E96: 男 | I96: １ | J96: 北京 | L96: Juicedata, Inc | M96: 合伙人 | N96: 标准会员 | O96: 424 | P96: 北京0组 | Q96: 0 | R96: - | S96: 1 | X96: =DATEDIF(B96,"2025-6-30","y") -> 7 | Z96: 已续费 | AC96: suave.su@gmail.com
A97: =ROW()-1 -> 96 | B97: 43051 | C97: 46203 | D97: 王志刚 | E97: 男 | I97: １ | J97: 深圳 | L97: 招商基金 | M97: 副总监 | N97: 标准会员 | O97: 433 | R97: - | S97: 1 | V97: 1 | X97: =DATEDIF(B97,"2025-6-30","y") -> 7 | AC97: zhigang78@163.com
A98: =ROW()-1 -> 97 | B98: 43069 | C98: 46203 | D98: 欧文盛 | E98: 男 | I98: １ | J98: 北京 | L98: 北京泰迪熊移动科技有限公司 | M98: CTO | N98: 高级会员 | O98: 439 | P98: 北京33组 | Q98: 0 | R98: - | S98: 1 | X98: =DATEDIF(B98,"2025-6-30","y") -> 7 | Z98: 已续费 | AC98: ouwensheng@teddymobile.cn
A99: =ROW()-1 -> 98 | B99: 43080 | C99: 46203 | D99: 王浩 | E99: 男 | I99: 0 | J99: 上海 | L99: 贵州小爱机器人科技有限公司 | M99: CTO | N99: 标准会员 | O99: 443 | R99: - | S99: 1 | X99: =DATEDIF(B99,"2025-6-30","y") -> 7 | AC99: wanghao@metasigncloud.com
A100: =ROW()-1 -> 99 | B100: 43082 | C100: 46203 | D100: 樊伟伟 | E100: 男 | I100: １ | J100: 南京 | L100: 微鲤 | M100: 技术总监 | N100: 标准会员 | O100: 444 | R100: - | S100: 1 | X100: =DATEDIF(B100,"2025-6-30","y") -> 7 | AC100: fanweiwei@weli.cn
...

Sheet 会员推荐
A1: 加入时间 - 年份 | B1: (全部)
A2: 加入时间 - 月份 | B2: (全部)
A4: 推荐人 | B4: 地区 | C4: 计数:姓名
A5: 暂无 | B5: 北京 | C5: 157
A6: 暂无 汇总 | C6: 157
A7: 杨攀 | B7: 北京 | C7: 17
A8: 杨攀 汇总 | C8: 17
A9: infoQ | B9: 北京 | C9: 12
A10: infoQ 汇总 | C10: 12
A11: 郭子龙 | B11: 北京 | C11: 7
A12: 郭子龙 汇总 | C12: 7
A13: 陈肃 | B13: 北京 | C13: 5
A14: 陈肃 汇总 | C14: 5
A15: Kevin | B15: 北京 | C15: 5
A16: Kevin 汇总 | C16: 5
A17: 高驰涛 | B17: 北京 | C17: 4
A18: 高驰涛 汇总 | C18: 4
A19: 裴晟 | B19: 北京 | C19: 4
A20: 裴晟 汇总 | C20: 4
A21: 宜博 | B21: 北京 | C21: 4
A22: 宜博 汇总 | C22: 4
A23: 自然流量-官网 | B23: 北京 | C23: 4
A24: 自然流量-官网 汇总 | C24: 4
A25: 杨扬 | B25: 北京 | C25: 3
A26: 杨扬 汇总 | C26: 3
A27: 于游 | B27: 北京 | C27: 3
A28: 于游 汇总 | C28: 3
A29: 王电轻 | B29: 北京 | C29: 3
A30: 王电轻 汇总 | C30: 3
A31: GTLC | B31: 北京 | C31: 3
A32: GTLC 汇总 | C32: 3
A33: 自然流量-朋友 | B33: 北京 | C33: 3
A34: 自然流量-朋友 汇总 | C34: 3
A35: 郭炜 | B35: 北京 | C35: 3
A36: 郭炜 汇总 | C36: 3
A37: 梁宇鹏 | B37: 北京 | C37: 2
A38: 梁宇鹏 汇总 | C38: 2
A39: 唐春林 | B39: 北京 | C39: 2
A40: 唐春林 汇总 | C40: 2
A41: 陈靖华 | B41: 北京 | C41: 2
A42: 陈靖华 汇总 | C42: 2
A43: 房晓乐 | B43: 北京 | C43: 2
A44: 房晓乐 汇总 | C44: 2
A45: 方光权益 | B45: 北京 | C45: 1
A46: 方光权益 汇总 | C46: 1
A47: maggie | B47: 北京 | C47: 1
A48: maggie 汇总 | C48: 1
A49: 史昕炜 | B49: 北京 | C49: 1
A50: 史昕炜 汇总 | C50: 1
A51: 朋友推荐 | B51: 北京 | C51: 1
A52: 朋友推荐 汇总 | C52: 1
A53: 朋友 | B53: 北京 | C53: 1
A54: 朋友 汇总 | C54: 1
A55: 海报宣传 | B55: 北京 | C55: 1
A56: 海报宣传 汇总 | C56: 1
A57: 张越（已过期） | B57: 北京 | C57: 1
A58: 张越（已过期） 汇总 | C58: 1
A59: 叶经纬 | B59: 北京 | C59: 1
A60: 叶经纬 汇总 | C60: 1
A61: 张林安 | B61: 北京 | C61: 1
A62: 张林安 汇总 | C62: 1
A63: 公司-首都在线 | B63: 北京 | C63: 1
A64: 公司-首都在线 汇总 | C64: 1
A65: 王平（已过期） | B65: 北京 | C65: 1
A66: 王平（已过期） 汇总 | C66: 1
A67: 公司-九章云极 | B67: 北京 | C67: 1
A68: 公司-九章云极 汇总 | C68: 1
A69: 汪何兵 | B69: 北京 | C69: 1
A70: 汪何兵 汇总 | C70: 1
A71: 韩岳岐 | B71: 北京 | C71: 1
A72: 韩岳岐 汇总 | C72: 1
A73: 杜仲（肖劲青） | B73: 北京 | C73: 1
A74: 杜仲（肖劲青） 汇总 | C74: 1
A75: 高琦 | B75: 北京 | C75: 1
A76: 高琦 汇总 | C76: 1
A77: 沈剑 | B77: 北京 | C77: 1
A78: 沈剑 汇总 | C78: 1
A79: 刘小红 | B79: 北京 | C79: 1
A80: 刘小红 汇总 | C80: 1
A81: 姜春生 | B81: 北京 | C81: 1
A82: 姜春生 汇总 | C82: 1
A83: 王鹏 | B83: 北京 | C83: 1
A84: 王鹏 汇总 | C84: 1
A85: 王海华 | B85: 北京 | C85: 1
A86: 王海华 汇总 | C86: 1
A87: 张骏峰 | B87: 北京 | C87: 1
A88: 张骏峰 汇总 | C88: 1
A89: 吕睿韬 | B89: 北京 | C89: 1
A90: 吕睿韬 汇总 | C90: 1
A91: 自然流量-deepseek | B91: 北京 | C91: 1
A92: 自然流量-deepseek 汇总 | C92: 1
A93: 王波 | B93: 北京 | C93: 1
A94: 王波 汇总 | C94: 1
A95: 李世勇 | B95: 北京 | C95: 1
A96: 李世勇 汇总 | C96: 1
A97: 自然流量 | B97: 北京 | C97: 1
A98: 自然流量 汇总 | C98: 1
A99: 张呈刚 | B99: 北京 | C99: 1
A100: 张呈刚 汇总 | C100: 1
A101: 张越 | B101: 北京 | C101: 1
...

Sheet 26年续费-含十年
A1: 序号 | B1: 加入时间 | C1: 会籍时间 | D1: 姓名 | E1: 性别 | F1: 是否更新 | G1: 地区 | H1: 所在位置 | I1: 公司 | J1: 职位 | K1: 会员类型 | L1: 续费金额 | M1: 会员编号 | N1: 是否入组 | O1: 新会员培训时间 | P1: 上线官网 | Q1: 新学员见面直播 | R1: 是否续费 | S1: 备注 | T1: 出海 | U1: 加入时长 | V1: 过期 | W1: 续费金额 | X1: 推荐人 | Y1: 推荐大类 | Z1: 邮箱 | AA1: 备注
A2: =ROW()-1 -> 1 | B2: 42129 | C2: 46203 | D2: 艾芙（徐雁斐） | E2: 女 | F2: 1 | G2: 深圳 | I2: 暂无 | J2: 暂无 | K2: 标准会员 | M2: 1 | P2: 1 | U2: =DATEDIF(B2,"2025-6-30","y") -> 10 | Z2: elfe1021@gmail.com
A3: =ROW()-1 -> 2 | B3: 42132 | C3: 46203 | D3: 郭理靖 | E3: 男 | F3: 1 | G3: 杭州 | I3: 奈雪的茶 | J3: CTO | K3: 标准会员 | M3: 2 | O3: - | P3: 1 | S3: 1 | T3: 1 | U3: =DATEDIF(B3,"2025-6-30","y") -> 10 | Z3: guolijing@gmail.com
A4: =ROW()-1 -> 3 | B4: 42139 | C4: 46203 | D4: 陈锡言 | E4: 男 | F4: 无信息0 | G4: 北京 | I4: 一览科技 | J4: CTO | K4: 标准会员 | M4: 5 | N4: 北京0组 | O4: - | P4: 1 | T4: 1 | U4: =DATEDIF(B4,"2025-6-30","y") -> 10 | W4: 已续费 | Z4: cccsmoking@sina.com
A5: =ROW()-1 -> 4 | B5: 42146 | C5: 46203 | D5: 汪威 | E5: 男 | F5: 1 | G5: 北京 | I5: 摩点众筹 | J5: 技术总监 | K5: 高级会员 | M5: 12 | N5: 北京0组 | O5: 45120 | P5: 1 | T5: 1 | U5: =DATEDIF(B5,"2025-6-30","y") -> 10 | W5: 已续费 | Z5: wangcash@gmail.com
A6: =ROW()-1 -> 5 | B6: 42147 | C6: 46203 | D6: 唐小浙 | E6: 男 | F6: 1 | G6: 上海 | I6: 墨誉科技 | J6: 技术vp | K6: 标准会员 | M6: 13 | O6: - | P6: 1 | T6: 1 | U6: =DATEDIF(B6,"2025-6-30","y") -> 10 | Z6: tangxz@gmail.com
A7: =ROW()-1 -> 6 | B7: 42150 | C7: 46203 | D7: 邹光先 | E7: 男 | F7: 0 | G7: 广州 | I7: 其他 | J7: 其他 | K7: 标准会员 | M7: 14 | O7: - | P7: 1 | T7: 1 | U7: =DATEDIF(B7,"2025-6-30","y") -> 10 | Z7: zouguangxian@163.com
A8: =ROW()-1 -> 7 | B8: 42160 | C8: 46203 | D8: 黄良懿 | E8: 男 | F8: 1 | G8: 深圳 | I8: 高仙机器人 | J8: 研发VP | K8: 标准会员 | M8: 17 | O8: - | P8: 1 | T8: 1 | U8: =DATEDIF(B8,"2025-6-30","y") -> 10 | Z8: codeant@hotmail.com
A9: =ROW()-1 -> 8 | B9: 42171 | C9: 46203 | D9: 史海峰 | E9: 男 | F9: 1 | G9: 北京 | I9: 方正证券 | J9: 架构平台负责人 | K9: 标准会员 | M9: 23 | N9: 北京2组 | O9: - | P9: 1 | S9: 1 | T9: 1 | U9: =DATEDIF(B9,"2025-6-30","y") -> 10 | W9: 已续费 | Z9: shihf_dc@163.com
A10: =ROW()-1 -> 9 | B10: 42180 | C10: 46203 | D10: 梁宇鹏 | E10: 男 | F10: 0 | G10: 北京 | I10: 蓝莺IM | J10: CEO | K10: 标准会员 | M10: 24 | N10: 北京2组 | O10: - | P10: 1 | T10: 1 | U10: =DATEDIF(B10,"2025-6-30","y") -> 10 | W10: 已续费 | Z10: eric.l.2046@gmail.com
A11: =ROW()-1 -> 10 | B11: 42202 | C11: 46203 | D11: 熊昌伟 | E11: 男 | F11: 1 | G11: 北京 | I11: 畅捷通信息技术股份有限公司 | J11: 助理总裁 | K11: 标准会员 | M11: 29 | N11: 北京0组 | O11: - | P11: 1 | T11: 1 | U11: =DATEDIF(B11,"2025-6-30","y") -> 9 | W11: 已续费 | Z11: xcw@chanjet.com
A12: =ROW()-1 -> 11 | B12: 42209 | C12: 46203 | D12: 丁宁 | E12: 男 | F12: 无公司 | G12: 新加坡 | I12: 荔枝集团 | J12: CTO | K12: 高级会员 | M12: 30 | O12: 45154 | P12: 1 | S12: 1 | T12: 1 | U12: =DATEDIF(B12,"2025-6-30","y") -> 9 | Z12: dingning@lizhi.fm
A13: =ROW()-1 -> 12 | B13: 42219 | C13: 46203 | D13: 陈靖华 | E13: 男 | F13: 1 | G13: 北京 | I13: 基调听云 | J13: 产品VP | K13: 标准会员 | M13: 34 | N13: 北京2组 | O13: - | P13: 1 | T13: 1 | U13: =DATEDIF(B13,"2025-6-30","y") -> 9 | W13: 已续费 | Z13: wood@tingyun.com
A14: =ROW()-1 -> 13 | B14: 42221 | C14: 46203 | D14: 侯冬雯 | E14: 女 | F14: 无公司 | G14: 北京 | I14: 北京微梦传媒股份有限公司 | J14: CTO | K14: 高级会员 | M14: 38 | N14: 北京0组 | O14: - | P14: 1 | T14: 1 | U14: =DATEDIF(B14,"2025-6-30","y") -> 9 | W14: 已续费 | Z14: dongwen@microdreams.com.cn
A15: =ROW()-1 -> 14 | B15: 42246 | C15: 46203 | D15: 黄彬彬 | E15: 男 | F15: 1 | G15: 上海 | I15: 多云转晴 | J15: 架构师 | K15: 高级会员 | M15: 44 | O15: - | P15: 1 | T15: 1 | U15: =DATEDIF(B15,"2025-6-30","y") -> 9 | Z15: 118733@qq.com
A16: =ROW()-1 -> 15 | B16: 42248 | C16: 46203 | D16: 王立博 | E16: 男 | F16: 1 | G16: 上海 | I16: 未来保贝 | J16: 合伙人&CTO | K16: 标准会员 | M16: 48 | O16: - | P16: 1 | T16: 1 | U16: =DATEDIF(B16,"2025-6-30","y") -> 9 | Z16: w803007@163.com
A17: =ROW()-1 -> 16 | B17: 42256 | C17: 46203 | D17: 胡震 | E17: 男 | F17: 1 | G17: 上海 | I17: 某公链基金会 | J17: 投研负责人 | K17: 标准会员 | M17: 58 | O17: - | P17: 1 | T17: 1 | U17: =DATEDIF(B17,"2025-6-30","y") -> 9 | Z17: huzhencn@163.com
A18: =ROW()-1 -> 17 | B18: 42275 | C18: 46203 | D18: 洪强宁 | E18: 男 | F18: 1 | G18: 北京 | I18: 雅识科技联合 | J18: 创始人兼CTO | K18: 标准会员 | M18: 65 | N18: 北京2组 | O18: - | P18: 1 | T18: 1 | U18: =DATEDIF(B18,"2025-6-30","y") -> 9 | W18: 已续费 | Z18: hongqn@gmail.com
A19: =ROW()-1 -> 18 | B19: 42298 | C19: 46203 | D19: 李道兵 | E19: 男 | F19: 1 | G19: 北京 | I19: Principal Embedded Software Developer | J19: 未登记 | K19: 标准会员 | M19: 70 | N19: 北京13组 | O19: - | P19: 1 | T19: 1 | U19: =DATEDIF(B19,"2025-6-30","y") -> 9 | W19: 无需续费 | Z19: lidaobing@gmail.com
A20: =ROW()-1 -> 19 | B20: 42300 | C20: 46203 | D20: 张海龙 | E20: 男 | F20: 1 | G20: 苏州 | I20: 同程旅行 | J20: 技术委员会主任 | K20: 标准会员 | M20: 72 | O20: - | P20: 1 | S20: 1 | T20: 1 | U20: =DATEDIF(B20,"2025-6-30","y") -> 9 | Z20: zhanghailong@coding.net
A21: =ROW()-1 -> 20 | B21: 42300 | C21: 46203 | D21: 王晓波 | E21: 男 | F21: 0 | G21: 苏州 | I21: 同程旅行 | J21: AVP&出行事业群 CTO | K21: 标准会员 | M21: 71 | O21: - | P21: 1 | T21: 1 | U21: =DATEDIF(B21,"2025-6-30","y") -> 9 | Z21: wxb09195@ly.com
A22: =ROW()-1 -> 21 | B22: 42318 | C22: 46203 | D22: 林华根 | E22: 男 | F22: 1 | G22: 深圳 | I22: 安徽超远信息技术有限公司 | J22: 副总工程师 | K22: 标准会员 | M22: 78 | O22: - | P22: 1 | T22: 1 | U22: =DATEDIF(B22,"2025-6-30","y") -> 9 | Z22: lhg@cychina.cn
A23: =ROW()-1 -> 22 | B23: 42334 | C23: 46203 | D23: 魏吉贺 | E23: 男 | F23: 1 | G23: 深圳 | I23: 深圳市残友软件股份有限公司 | J23: 技术总监 | K23: 标准会员 | M23: 91 | O23: - | P23: 1 | T23: 1 | U23: =DATEDIF(B23,"2025-6-30","y") -> 9 | Z23: wjh@canyou.cn
A24: =ROW()-1 -> 23 | B24: 42339 | C24: 46203 | D24: 龚银 | E24: 男 | F24: 1 | G24: 深圳 | I24: 安克创新 | J24: CIO | K24: 标准会员 | M24: 95 | O24: - | P24: 1 | T24: 1 | U24: =DATEDIF(B24,"2025-6-30","y") -> 9 | Z24: gongyin@126.com
A25: =ROW()-1 -> 24 | B25: 42361 | C25: 46203 | D25: 华健 | E25: 男 | F25: 1 | G25: 北京 | I25: 梦诚科技 | J25: 创始人&CTO | K25: 标准会员 | M25: 102 | N25: 北京2组 | O25: - | P25: 1 | T25: 1 | U25: =DATEDIF(B25,"2025-6-30","y") -> 9 | W25: 已续费 | Z25: huaj1101@qq.com
A26: =ROW()-1 -> 25 | B26: 42427 | C26: 46203 | D26: 何世友 | E26: 男 | F26: 1 | G26: 广州 | I26: 腾讯云 | J26: Serverless 产品负责人 | K26: 标准会员 | M26: 114 | O26: - | P26: 1 | T26: 1 | U26: =DATEDIF(B26,"2025-6-30","y") -> 9 | Z26: shiyou.he@gmail.com
A27: =ROW()-1 -> 26 | B27: 42433 | C27: 46203 | D27: 李玉福 | E27: 男 | F27: 1 | G27: 北京 | I27: 北京农信互联科技有限公司 | J27: 副总裁 | K27: 标准会员 | M27: 117 | N27: 北京13组 | O27: - | P27: 1 | T27: 1 | U27: =DATEDIF(B27,"2025-6-30","y") -> 9 | W27: 已续费 | Z27: liyufu@nxin.com
A28: =ROW()-1 -> 27 | B28: 42451 | C28: 46203 | D28: 曾冠东 | E28: 男 | F28: 0 | G28: 广州 | I28: 酷狗音乐 | J28: 繁星网研发总监 | K28: 标准会员 | M28: 123 | O28: - | P28: 1 | S28: 1 | T28: 1 | U28: =DATEDIF(B28,"2025-6-30","y") -> 9 | Z28: popeast@gmail.com
A29: =ROW()-1 -> 28 | B29: 42451 | C29: 46203 | D29: 路文杰 | E29: 男 | F29: 1 | G29: 广州 | I29: 甘果科技 | J29: CEO | K29: 标准会员 | M29: 121 | O29: - | P29: 1 | U29: =DATEDIF(B29,"2025-6-30","y") -> 9 | Z29: cngump@gmail.com
A30: =ROW()-1 -> 29 | B30: 42473 | C30: 46203 | D30: 高楚涛 | E30: 男 | F30: 1 | G30: 深圳 | I30: 深圳市嘉立创科技发展有限公司 | J30: CIO | K30: 标准会员 | M30: 135 | O30: - | P30: 1 | T30: 1 | U30: =DATEDIF(B30,"2025-6-30","y") -> 9 | Z30: gaochutao@163.com
A31: =ROW()-1 -> 30 | B31: 42480 | C31: 46203 | D31: 刘建国 | E31: 男 | F31: 1 | G31: 广州 | H31: 1 | I31: 伊智信息科技 | J31: CEO | K31: 标准会员 | M31: 26 | O31: - | P31: 1 | T31: 1 | U31: =DATEDIF(B31,"2025-6-30","y") -> 9 | Z31: yijshu@gmail.com
A32: =ROW()-1 -> 31 | B32: 42482 | C32: 46203 | D32: 万林涛 | E32: 男 | F32: 1 | G32: 上海 | I32: 上海蔚星数据 | J32: 副总裁兼首席数据官 | K32: 标准会员 | M32: 140 | O32: - | P32: 1 | T32: 1 | U32: =DATEDIF(B32,"2025-6-30","y") -> 9 | Z32: lintao.wan@outlook.com
A33: =ROW()-1 -> 32 | B33: 42482 | C33: 46203 | D33: 徐翎 | E33: 男 | F33: 1 | G33: 上海 | I33: 上海数达物流科技有限公司 | J33: CTO | K33: 标准会员 | M33: 139 | O33: - | P33: 1 | U33: =DATEDIF(B33,"2025-6-30","y") -> 9 | Z33: xlshcn@hotmail.com
A34: =ROW()-1 -> 33 | B34: 42495 | C34: 46203 | D34: 肖颖 | E34: 男 | F34: １ | G34: 上海 | I34: 上海澄廓信息科技有限公司 | J34: CEO | K34: 标准会员 | M34: 144 | O34: - | P34: 1 | U34: =DATEDIF(B34,"2025-6-30","y") -> 9 | Z34: 18049722632@163.com
A35: =ROW()-1 -> 34 | B35: 42524 | C35: 46203 | D35: 张剑伟 | E35: 男 | F35: １ | G35: 上海 | I35: 百安居 | J35: CTO | K35: 标准会员 | M35: 160 | O35: - | P35: 1 | U35: =DATEDIF(B35,"2025-6-30","y") -> 9 | Z35: zjwsoft@gmail.com
A36: =ROW()-1 -> 35 | B36: 42536 | C36: 46203 | D36: 苏煦烽 | E36: 男 | F36: １ | G36: 广州 | H36: 1 | I36: 亲邻科技 | J36: 技术总监 | K36: 标准会员 | M36: 167 | O36: - | P36: 1 | T36: 1 | U36: =DATEDIF(B36,"2025-6-30","y") -> 9 | Z36: suxufeng@qq.com
A37: =ROW()-1 -> 36 | B37: 42537 | C37: 46203 | D37: 孙其瑞 | E37: 男 | F37: １ | G37: 杭州 | I37: 苏州优频科技有限公司 | J37: CTO | K37: 标准会员 | M37: 171 | O37: - | P37: 1 | T37: 1 | U37: =DATEDIF(B37,"2025-6-30","y") -> 9 | Z37: sqr@detu.com
A38: =ROW()-1 -> 37 | B38: 42552 | C38: 46203 | D38: 芦宇峰 | E38: 男 | F38: １ | G38: 杭州 | I38: 上海擎路科技 | J38: 联合创始人 & CTO | K38: 标准会员 | M38: 178 | O38: - | P38: 1 | T38: 1 | U38: =DATEDIF(B38,"2025-6-30","y") -> 8 | Z38: xiao_ys@163.com
A39: =ROW()-1 -> 38 | B39: 42556 | C39: 46203 | D39: 陈杰 | E39: 男 | F39: １ | G39: 上海 | I39: 上海领健信息技术有限公司 | J39: CTO | K39: 标准会员 | M39: 188 | O39: - | P39: 0 | U39: =DATEDIF(B39,"2025-6-30","y") -> 8 | Z39: alan.chen@linkedcare.cn
A40: =ROW()-1 -> 39 | B40: 42559 | C40: 46203 | D40: 黄伟坚 | E40: 男 | F40: １ | G40: 广州 | H40: 1 | I40: mobvista汇量科技 | J40: 联合创始人 | K40: 标准会员 | M40: 190 | O40: - | P40: 1 | T40: 1 | U40: =DATEDIF(B40,"2025-6-30","y") -> 8 | Z40: hwjian@126.com
A41: =ROW()-1 -> 40 | B41: 42559 | C41: 46203 | D41: 黄勇 | E41: 男 | F41: １ | G41: 上海 | I41: 阅流 | J41: CTO | K41: 标准会员 | M41: 191 | O41: - | P41: 1 | T41: 1 | U41: =DATEDIF(B41,"2025-6-30","y") -> 8 | Z41: hy_think@163.com
A42: =ROW()-1 -> 41 | B42: 42562 | C42: 46203 | D42: 奚铭皋 | E42: 男 | F42: １ | G42: 上海 | I42: 比图科技 | J42: Tech Lead | K42: 标准会员 | M42: 193 | O42: - | P42: 1 | U42: =DATEDIF(B42,"2025-6-30","y") -> 8 | Z42: minggao.xi@gmail.com
A43: =ROW()-1 -> 42 | B43: 42562 | C43: 46203 | D43: 陆云昆 | E43: 男 | F43: １ | G43: 上海 | I43: 上海钢蜂信息科技有限公司 | J43: CTO | K43: 标准会员 | M43: 194 | O43: - | P43: 1 | T43: 1 | U43: =DATEDIF(B43,"2025-6-30","y") -> 8 | Z43: ykdoubles@hotmail.com
A44: =ROW()-1 -> 43 | B44: 42589 | C44: 46203 | D44: 张志合 | E44: 男 | F44: １ | G44: 广州 | I44: 广州卓越教育 | J44: 资深IT总监 | K44: 标准会员 | M44: 210 | O44: - | P44: 1 | S44: 1 | U44: =DATEDIF(B44,"2025-6-30","y") -> 8 | Z44: kaffeel@163.com
A45: =ROW()-1 -> 44 | B45: 42597 | C45: 46203 | D45: 谢金牛 | E45: 男 | F45: １ | G45: 广州 | I45: 深圳风信计算机服务有限公司 | J45: 总经理 | K45: 标准会员 | M45: 222 | O45: - | P45: 1 | T45: 1 | U45: =DATEDIF(B45,"2025-6-30","y") -> 8 | Z45: 115617486@qq.com
A46: =ROW()-1 -> 45 | B46: 42613 | C46: 46203 | D46: 廖雄杰 | E46: 男 | F46: １ | G46: 北京 | I46: 北京基调网络股份有限公司 | J46: 研发副总裁 | K46: 标准会员 | M46: 233 | N46: 北京0组 | O46: - | P46: 1 | U46: =DATEDIF(B46,"2025-6-30","y") -> 8 | W46: 已续费 | Z46: liaoxj@tingyun.com
A47: =ROW()-1 -> 46 | B47: 42631 | C47: 46203 | D47: 伍涛 | E47: 男 | F47: １ | G47: 上海 | I47: Funplus | J47: Co-CTO | K47: 标准会员 | M47: 242 | O47: - | P47: 1 | S47: 1 | T47: 1 | U47: =DATEDIF(B47,"2025-6-30","y") -> 8 | Z47: tonywutao@gmail.com
A48: =ROW()-1 -> 47 | B48: 42657 | C48: 46203 | D48: 张飞 | E48: 男 | F48: １ | G48: 上海 | I48: vivo | J48: 部门总经理 | K48: 标准会员 | M48: 253 | O48: - | P48: 1 | S48: 1 | T48: 1 | U48: =DATEDIF(B48,"2025-6-30","y") -> 8 | Z48: zgfi@163.com
A49: =ROW()-1 -> 48 | B49: 42667 | C49: 46203 | D49: 卢亿雷 | E49: 男 | F49: １ | G49: 北京 | I49: 北京白海科技有限公司 | J49: 创始人&CEO | K49: 高级会员 | M49: 258 | N49: 北京24组 | O49: - | P49: 1 | T49: 1 | U49: =DATEDIF(B49,"2025-6-30","y") -> 8 | W49: 无需续费 | Z49: johnlya@163.com
A50: =ROW()-1 -> 49 | B50: 42667 | C50: 46203 | D50: 洪倍 | E50: 男 | F50: １ | G50: 上海 | I50: ValueZ智库 | J50: 创始人、合伙人 | K50: 标准会员 | M50: 259 | O50: - | P50: 1 | U50: =DATEDIF(B50,"2025-6-30","y") -> 8 | Z50: bh@roomwits.com
A51: =ROW()-1 -> 50 | B51: 42695 | C51: 46203 | D51: 王河生 | E51: 男 | F51: 无公司 | G51: 南京 | I51: 南京四维向量科技有限公司 | J51: 创始人&CEO | K51: 标准会员 | M51: 268 | O51: - | P51: 1 | U51: =DATEDIF(B51,"2025-6-30","y") -> 8 | Z51: 4005958@qq.com
A52: =ROW()-1 -> 51 | B52: 42698 | C52: 46203 | D52: 何德照 | E52: 男 | F52: １ | G52: 深圳 | I52: AfterShip | J52: 技术VP | K52: 标准会员 | M52: 269 | O52: - | P52: 1 | T52: 1 | U52: =DATEDIF(B52,"2025-6-30","y") -> 8 | Z52: dezhaohe@qq.com
A53: =ROW()-1 -> 52 | B53: 42723 | C53: 46203 | D53: 练海荣 | E53: 男 | F53: １ | G53: 苏州 | I53: 龙石数据 | J53: 总经理 | K53: 标准会员 | M53: 283 | O53: - | P53: 1 | T53: 1 | U53: =DATEDIF(B53,"2025-6-30","y") -> 8 | Z53: hairong_lian@163.com
A54: =ROW()-1 -> 53 | B54: 42730 | C54: 46203 | D54: 冯斌 | E54: 男 | F54: １ | G54: 深圳 | I54: ONES | J54: CTO | K54: 高级会员 | M54: 295 | O54: - | P54: 1 | S54: 1 | T54: 1 | U54: =DATEDIF(B54,"2025-6-30","y") -> 8 | Z54: 13918821015@139.com
A55: =ROW()-1 -> 54 | B55: 42730 | C55: 46203 | D55: 贾锦杰 | E55: 男 | F55: １ | G55: 广州 | I55: KEEP | J55: 战略 & PMO leader | K55: 标准会员 | M55: 291 | N55: 北京0组 | O55: - | P55: 1 | S55: 1 | U55: =DATEDIF(B55,"2025-6-30","y") -> 8 | W55: 已续费 | Z55: jiajinjie@gmail.com
A56: =ROW()-1 -> 55 | B56: 42731 | C56: 46203 | D56: 李卓 | E56: 男 | F56: １ | G56: 杭州 | I56: 道富信息科技 | J56: 董事总经理 | K56: 高级会员 | M56: 297 | O56: - | P56: 1 | U56: =DATEDIF(B56,"2025-6-30","y") -> 8 | Z56: me@milanello1998.com
A57: =ROW()-1 -> 56 | B57: 42734 | C57: 46203 | D57: 宋书俊 | E57: 男 | F57: １ | G57: 深圳 | I57: 广州爆米科技有限公司 | J57: CTO | K57: 标准会员 | M57: 305 | O57: - | P57: 1 | U57: =DATEDIF(B57,"2025-6-30","y") -> 8 | Z57: ssjsj@126.com
A58: =ROW()-1 -> 57 | B58: 42758 | C58: 46203 | D58: 杨冀龙 | E58: 男 | F58: 0 | G58: 北京 | I58: 北京知道创宇信息技术有限公司 | J58: CTO+COO | K58: 标准会员 | L58: 5400 | M58: 318 | N58: 北京0组 | O58: - | P58: 1 | U58: =DATEDIF(B58,"2025-6-30","y") -> 8 | W58: 已续费 | Z58: yang@knownsec.com
A59: =ROW()-1 -> 58 | B59: 42779 | C59: 46203 | D59: 余峰 | E59: 男 | F59: １ | G59: 北京 | I59: 汉迪科技 | J59: 商业化平台事业部负责人 | K59: 标准会员 | L59: 5400 | M59: 324 | N59: 北京13组 | O59: - | P59: 1 | U59: =DATEDIF(B59,"2025-6-30","y") -> 8 | W59: 已续费 | Z59: feng.yu@ewp-group.com
A60: =ROW()-1 -> 59 | B60: 42783 | C60: 46203 | D60: 林佳齐 | E60: 男 | F60: １ | G60: 杭州 | I60: 西阿爱木 | J60: CEO | K60: 标准会员 | L60: 5400 | M60: 327 | O60: - | P60: 1 | U60: =DATEDIF(B60,"2025-6-30","y") -> 8 | Z60: linjiaqi86@gmail.com
A61: =ROW()-1 -> 60 | B61: 42789 | C61: 46203 | D61: 焦洋 | E61: 男 | F61: １ | G61: 北京 | I61: 盖娅互娱 | J61: CTO | K61: 标准会员 | L61: 5400 | M61: 329 | N61: 北京12组 | O61: - | P61: 1 | S61: 1 | U61: =DATEDIF(B61,"2025-6-30","y") -> 8 | W61: 已续费 | Z61: jiao.yang.bupt@gmail.com
A62: =ROW()-1 -> 61 | B62: 42793 | C62: 46203 | D62: 张觅 | E62: 男 | F62: １ | G62: 北京 | I62: 况客科技 | J62: 技术合伙人 | K62: 标准会员 | L62: 5400 | M62: 332 | N62: 北京13组 | O62: - | P62: 1 | U62: =DATEDIF(B62,"2025-6-30","y") -> 8 | W62: 已续费 | Z62: zhm83@163.com
A63: =ROW()-1 -> 62 | B63: 42800 | C63: 46203 | D63: 陈颖棠 | E63: 男 | F63: １ | G63: 广州 | I63: 论客科技（广州）有限公司 | J63: 首席架构师 | K63: 高级会员 | L63: 9216 | M63: 337 | O63: - | P63: 1 | U63: =DATEDIF(B63,"2025-6-30","y") -> 8 | Z63: cyt@mailtech.cn
A64: =ROW()-1 -> 63 | B64: 42801 | C64: 46203 | D64: 黎宏伟 | E64: 男 | F64: １ | G64: 成都 | I64: 成都市美幻科技有限公司 | J64: 技术总监 | K64: 标准会员 | L64: 5400 | M64: 333 | O64: - | P64: 1 | U64: =DATEDIF(B64,"2025-6-30","y") -> 8 | Z64: lhwdev@qq.com
A65: =ROW()-1 -> 64 | B65: 42807 | C65: 46203 | D65: 李伟辰 | E65: 男 | F65: １ | G65: 北京 | I65: 北京知道创宇信息技术有限公司 | J65: 技术VP | K65: 标准会员 | L65: 5400 | M65: 336 | N65: 北京12组 | O65: - | P65: 1 | U65: =DATEDIF(B65,"2025-6-30","y") -> 8 | W65: 已续费 | Z65: liwc@knownsec.com
A66: =ROW()-1 -> 65 | B66: 42815 | C66: 46203 | D66: 崔浩波 | E66: 男 | F66: １ | G66: 北京 | I66: 北京嗨学网教育科技有限公司 | J66: CTO | K66: 标准会员 | L66: 5400 | M66: 340 | N66: 北京12组 | O66: - | P66: 1 | S66: 1 | U66: =DATEDIF(B66,"2025-6-30","y") -> 8 | W66: 已续费 | Z66: cuihaobo@gmail.com
A67: =ROW()-1 -> 66 | B67: 42838 | C67: 46203 | D67: 任腾 | E67: 男 | F67: １ | G67: 硅谷 | I67: AI Rudder | J67: CEO | K67: 标准会员 | L67: 5400 | M67: 346 | O67: - | P67: 1 | U67: =DATEDIF(B67,"2025-6-30","y") -> 8 | Z67: teng.ren@airudder.com
A68: =ROW()-1 -> 67 | B68: 42839 | C68: 46203 | D68: 李晨丰 | E68: 男 | F68: １ | G68: 深圳 | H68: 1 | I68: 深圳米筐科技有限公司 | J68: COO | K68: 标准会员 | L68: 5400 | M68: 347 | O68: - | P68: 1 | U68: =DATEDIF(B68,"2025-6-30","y") -> 8 | Z68: kangol@ricequant.com
A69: =ROW()-1 -> 68 | B69: 42849 | C69: 46203 | D69: 钱小军 | E69: 男 | F69: １ | G69: 上海 | I69: 安永中国咨询 | J69: 金融科技咨询经理 | K69: 标准会员 | L69: 5400 | M69: 349 | O69: - | P69: 1 | U69: =DATEDIF(B69,"2025-6-30","y") -> 8 | Z69: abelqian@vip.sina.com
A70: =ROW()-1 -> 69 | B70: 42866 | C70: 46203 | D70: 王翱宇 | E70: 男 | F70: １ | G70: 杭州 | I70: 杭州谐云科技有限公司 | J70: CEO | K70: 标准会员 | L70: 5400 | M70: 356 | O70: - | P70: 1 | U70: =DATEDIF(B70,"2025-6-30","y") -> 8 | Z70: way@harmonycloud.cn
A71: =ROW()-1 -> 70 | B71: 42912 | C71: 46203 | D71: 徐庆新 | E71: 男 | F71: １ | G71: 苏州 | I71: 苏州乐佰图信息技术有限公司 | J71: 产品总监 | K71: 标准会员 | L71: 5400 | M71: 3700 | O71: - | P71: 1 | U71: =DATEDIF(B71,"2025-6-30","y") -> 8 | Z71: xuqingxin@gmail.com
A72: =ROW()-1 -> 71 | B72: 42874 | C72: 46203 | D72: 暨家愉 | E72: 男 | F72: １ | G72: 广州 | I72: 腾讯 | J72: 专家架构师 | K72: 标准会员 | L72: 5400 | M72: 361 | O72: - | P72: 1 | S72: 1 | U72: =DATEDIF(B72,"2025-6-30","y") -> 8 | Z72: jiayu.ji@gmail.com
A73: =ROW()-1 -> 72 | B73: 42886 | C73: 46203 | D73: 肖毅 | E73: 男 | F73: １ | G73: 成都 | I73: 成都智客科技有限公司 | J73: CEO | K73: 标准会员 | L73: 5400 | M73: 362 | O73: - | P73: 1 | U73: =DATEDIF(B73,"2025-6-30","y") -> 8 | Z73: xiaoyi@aoasp.com
A74: =ROW()-1 -> 73 | B74: 42927 | C74: 46203 | D74: 曹祖鹏 | E74: 男 | F74: １ | G74: 南京 | I74: 南京知亦行信息技术有限公司 | J74: CTO | K74: 标准会员 | L74: 5400 | M74: 376 | O74: - | P74: 1 | U74: =DATEDIF(B74,"2025-6-30","y") -> 7 | Z74: caozupeng@139.com
A75: =ROW()-1 -> 74 | B75: 42935 | C75: 46203 | D75: 杨振东 | E75: 男 | F75: １ | G75: 上海 | I75: 上海方亿信息科技有限公司 | J75: 联合创始人&CTO | K75: 高级会员 | L75: 9216 | M75: 383 | O75: - | P75: 1 | U75: =DATEDIF(B75,"2025-6-30","y") -> 7 | Z75: yzd@aso360.com
A76: =ROW()-1 -> 75 | B76: 42936 | C76: 46203 | D76: 张志成 | E76: 男 | F76: １ | G76: 杭州 | I76: 阿里巴巴达摩院 | J76: 高级技术专家 | K76: 标准会员 | L76: 5400 | M76: 388 | O76: - | P76: 1 | U76: =DATEDIF(B76,"2025-6-30","y") -> 7 | Z76: zczhang.hvac@gmail.com
A77: =ROW()-1 -> 76 | B77: 42941 | C77: 46203 | D77: 杨红光 | E77: 男 | F77: １ | G77: 北京 | I77: 1Box | J77: CTO | K77: 标准会员 | L77: 5400 | M77: 394 | N77: 北京13组 | O77: - | P77: 1 | U77: =DATEDIF(B77,"2025-6-30","y") -> 7 | W77: 已续费 | Z77: njyhg@163.com
A78: =ROW()-1 -> 77 | B78: 42954 | C78: 46203 | D78: 杨帅麒 | E78: 男 | F78: １ | G78: 上海 | I78: 上海盛大汽车服务集团 | J78: CTO | K78: 标准会员 | L78: 5400 | M78: 402 | O78: - | P78: 1 | R78: 无地址 | U78: =DATEDIF(B78,"2025-6-30","y") -> 7 | Z78: 408482214@qq.com
A79: =ROW()-1 -> 78 | B79: 42957 | C79: 46203 | D79: 胡继伟 | E79: 男 | F79: １ | G79: 北京 | I79: 合思 | J79: 架构师 | K79: 标准会员 | L79: 5400 | M79: 404 | N79: 北京13组 | O79: - | P79: 1 | S79: 1 | U79: =DATEDIF(B79,"2025-6-30","y") -> 7 | W79: 已续费 | Z79: hu_jiwei@foxmail.com
A80: =ROW()-1 -> 79 | B80: 42970 | C80: 46203 | D80: 沈旸 | E80: 男 | F80: 0 | G80: 北京 | I80: 联易融 | J80: 副总裁 | K80: 标准会员 | L80: 5400 | M80: 407 | N80: 北京12组 | O80: - | P80: 1 | U80: =DATEDIF(B80,"2025-6-30","y") -> 7 | W80: 已续费 | Z80: yang.shen.it@gmail.com
A81: =ROW()-1 -> 80 | B81: 42988 | C81: 46203 | D81: 杨威 | E81: 男 | F81: １ | G81: 北京 | I81: 明略科技 | J81: 技术副总裁 | K81: 标准会员 | L81: 5400 | M81: 81 | N81: 北京0组 | O81: - | P81: 1 | U81: =DATEDIF(B81,"2025-6-30","y") -> 7 | W81: 已续费 | Z81: yangwei@rongcloud.cn
A82: =ROW()-1 -> 81 | B82: 43000 | C82: 46203 | D82: 褚亮 | E82: 男 | F82: １ | G82: 杭州 | I82: 杭州咿啦科技有限公司 | J82: 联合创始人 & CTO | K82: 标准会员 | L82: 5400 | M82: 418 | O82: - | P82: 1 | S82: 1 | U82: =DATEDIF(B82,"2025-6-30","y") -> 7 | Z82: chuliang@ellabook.cn
A83: =ROW()-1 -> 82 | B83: 43004 | C83: 46203 | D83: 沈淦 | E83: 男 | F83: １ | G83: 杭州 | I83: 杭州正马软件科技有限公司 | J83: CTO | K83: 标准会员 | L83: 5400 | M83: 419 | O83: - | P83: 1 | U83: =DATEDIF(B83,"2025-6-30","y") -> 7 | Z83: floatin@sina.com
A84: =ROW()-1 -> 83 | B84: 43006 | C84: 46203 | D84: 蒋宏飞 | E84: 男 | F84: １ | G84: 北京 | I84: 作业帮 | J84: 研究员 | K84: 标准会员 | L84: 5400 | M84: 423 | N84: 北京16组 | O84: - | P84: 1 | S84: 1 | U84: =DATEDIF(B84,"2025-6-30","y") -> 7 | W84: 已续费 | Z84: hf.jiang@qq.com
A85: =ROW()-1 -> 84 | B85: 43017 | C85: 46203 | D85: 苏锐 | E85: 男 | F85: １ | G85: 北京 | I85: Juicedata, Inc | J85: 合伙人 | K85: 标准会员 | L85: 5400 | M85: 424 | N85: 北京0组 | O85: - | P85: 1 | U85: =DATEDIF(B85,"2025-6-30","y") -> 7 | W85: 已续费 | Z85: suave.su@gmail.com
A86: =ROW()-1 -> 85 | B86: 43051 | C86: 46203 | D86: 王志刚 | E86: 男 | F86: １ | G86: 深圳 | I86: 招商基金 | J86: 副总监 | K86: 标准会员 | L86: 5400 | M86: 433 | O86: - | P86: 1 | S86: 1 | U86: =DATEDIF(B86,"2025-6-30","y") -> 7 | Z86: zhigang78@163.com
A87: =ROW()-1 -> 86 | B87: 43069 | C87: 46203 | D87: 欧文盛 | E87: 男 | F87: １ | G87: 北京 | I87: 北京泰迪熊移动科技有限公司 | J87: CTO | K87: 高级会员 | L87: 9216 | M87: 439 | N87: 北京33组 | O87: - | P87: 1 | U87: =DATEDIF(B87,"2025-6-30","y") -> 7 | W87: 已续费 | Z87: ouwensheng@teddymobile.cn
A88: =ROW()-1 -> 87 | B88: 43080 | C88: 46203 | D88: 王浩 | E88: 男 | F88: 0 | G88: 上海 | I88: 贵州小爱机器人科技有限公司 | J88: CTO | K88: 标准会员 | L88: 5400 | M88: 443 | O88: - | P88: 1 | U88: =DATEDIF(B88,"2025-6-30","y") -> 7 | Z88: wanghao@metasigncloud.com
A89: =ROW()-1 -> 88 | B89: 43082 | C89: 46203 | D89: 樊伟伟 | E89: 男 | F89: １ | G89: 南京 | I89: 微鲤 | J89: 技术总监 | K89: 标准会员 | L89: 5400 | M89: 444 | O89: - | P89: 1 | U89: =DATEDIF(B89,"2025-6-30","y") -> 7 | Z89: fanweiwei@weli.cn
A90: =ROW()-1 -> 89 | B90: 43095 | C90: 46203 | D90: 肖剑涛 | E90: 男 | F90: １ | G90: 北京 | I90: 成绎半导体 | J90: 联合创始人 | K90: 标准会员 | L90: 5400 | M90: 449 | N90: 北京22组 | O90: - | P90: 1 | U90: =DATEDIF(B90,"2025-6-30","y") -> 7 | W90: 已续费 | Z90: xiaojiantao@vip.sina.com
A91: =ROW()-1 -> 90 | B91: 43095 | C91: 46203 | D91: 李少春 | E91: 男 | F91: １ | G91: 广州 | I91: 广州博泰数据有限公司 | J91: 总经理 | K91: 标准会员 | L91: 5400 | M91: 451 | O91: - | P91: 1 | U91: =DATEDIF(B91,"2025-6-30","y") -> 7 | Z91: cylsc@163.com
A92: =ROW()-1 -> 91 | B92: 43096 | C92: 46203 | D92: 于君泽 | E92: 男 | F92: １ | G92: 成都 | I92: 中生代技术 | J92: 创始人 | K92: 标准会员 | L92: 5400 | M92: 452 | O92: - | P92: 1 | U92: =DATEDIF(B92,"2025-6-30","y") -> 7 | Z92: 5581012@qq.com
A93: =ROW()-1 -> 92 | B93: 43098 | C93: 46203 | D93: 李列为 | E93: 男 | F93: １ | G93: 南京 | I93: 江苏华博实业集团有限公司 | J93: CTO | K93: 标准会员 | L93: 5400 | M93: 453 | O93: - | P93: 1 | U93: =DATEDIF(B93,"2025-6-30","y") -> 7 | Z93: 7538350@qq.com
A94: =ROW()-1 -> 93 | B94: 43117 | C94: 46203 | D94: 邹永强 | E94: 男 | F94: 0 | G94: 北京 | I94: 云账户 | J94: 联合创始人兼CTO | K94: 高级会员 | L94: 9216 | M94: 456 | N94: 北京24组 | O94: - | P94: 1 | S94: 1 | U94: =DATEDIF(B94,"2025-6-30","y") -> 7 | W94: 已续费 | Z94: yongqiangzou@gmail.com
A95: =ROW()-1 -> 94 | B95: 43128 | C95: 46203 | D95: 马力遥 | E95: 男 | F95: １ | G95: 成都 | I95: 互联极简网络科技成都有限公司 | J95: 联合创始人 CTO | K95: 标准会员 | L95: 5400 | M95: 460 | O95: - | P95: 1 | U95: =DATEDIF(B95,"2025-6-30","y") -> 7 | Z95: nelson.ma@gsafer.com
A96: =ROW()-1 -> 95 | B96: 43132 | C96: 46203 | D96: 吴传兵 | E96: 男 | F96: １ | G96: 广州 | I96: 广州味美优品食品科技有限公司 | J96: CTO | K96: 标准会员 | L96: 5400 | M96: 462 | O96: - | P96: 1 | U96: =DATEDIF(B96,"2025-6-30","y") -> 7 | Z96: whueric@gmail.com
A97: =ROW()-1 -> 96 | B97: 43159 | C97: 46203 | D97: 崔俊涛 | E97: 男 | F97: 0 | G97: 上海 | I97: 上海万位数字技术有限公司 | J97: CTO | K97: 高级会员 | L97: 9216 | M97: 468 | O97: - | P97: 1 | U97: =DATEDIF(B97,"2025-6-30","y") -> 7 | Z97: juntaocui@gmail.com
A98: =ROW()-1 -> 97 | B98: 43172 | C98: 46203 | D98: 黄振华 | E98: 男 | F98: １ | G98: 北京 | I98: 华策影视集团 | J98: 总助兼科技数字中心总经理 | K98: 标准会员 | L98: 5400 | M98: 479 | N98: 北京13组 | O98: - | P98: 1 | U98: =DATEDIF(B98,"2025-6-30","y") -> 7 | W98: 已续费 | Z98: zhenhua_edward@qq.com
A99: =ROW()-1 -> 98 | B99: 43178 | C99: 46203 | D99: 尹雯玉 | E99: 女 | F99: １ | G99: 北京 | I99: 北京搜狐新媒体信息技术有限公司 | J99: 高级技术经理 | K99: 标准会员 | L99: 5400 | M99: 484 | N99: 北京0组 | O99: - | P99: 1 | S99: 1 | U99: =DATEDIF(B99,"2025-6-30","y") -> 7 | W99: 无需续费 | Z99: amaaanda@163.com
A100: =ROW()-1 -> 99 | B100: 43178 | C100: 46203 | D100: 陈海 | E100: 男 | F100: １ | G100: 北京 | I100: 中信银行 | J100: 处长 | K100: 标准会员 | L100: 5400 | M100: 486 | N100: 北京13组 | O100: - | P100: 1 | S100: 1 | U100: =DATEDIF(B100,"2025-6-30","y") -> 7 | W100: 已续费 | Z100: chenhai@citicbank.com
...

Sheet 26年续费底表-不含十年
A1: 序号 | B1: 加入时间 | C1: 会籍时间 | D1: 姓名 | E1: 性别 | F1: 是否更新 | G1: 地区 | H1: 所在位置 | I1: 公司 | J1: 职位 | K1: 会员类型 | L1: 续费金额 | M1: 会员编号 | N1: 是否入组 | O1: 新会员培训时间 | P1: 上线官网 | Q1: 新学员见面直播 | R1: 是否续费 | S1: 备注 | T1: 出海 | U1: 加入时长 | V1: 过期 | W1: 续费金额 | X1: 推荐人 | Y1: 推荐大类 | Z1: 邮箱 | AA1: 备注
A2: =ROW()-1 -> 1 | B2: 42758 | C2: 46203 | D2: 杨冀龙 | E2: 男 | F2: 0 | G2: 北京 | I2: 北京知道创宇信息技术有限公司 | J2: CTO+COO | K2: 标准会员 | L2: 5400 | M2: 318 | N2: 北京0组 | O2: - | P2: 1 | U2: =DATEDIF(B2,"2025-6-30","y") -> 8 | W2: 已续费 | Z2: yang@knownsec.com
A3: =ROW()-1 -> 2 | B3: 42779 | C3: 46203 | D3: 余峰 | E3: 男 | F3: １ | G3: 北京 | I3: 汉迪科技 | J3: 商业化平台事业部负责人 | K3: 标准会员 | L3: 5400 | M3: 324 | N3: 北京13组 | O3: - | P3: 1 | U3: =DATEDIF(B3,"2025-6-30","y") -> 8 | W3: 已续费 | Z3: feng.yu@ewp-group.com
A4: =ROW()-1 -> 3 | B4: 42783 | C4: 46203 | D4: 林佳齐 | E4: 男 | F4: １ | G4: 杭州 | I4: 西阿爱木 | J4: CEO | K4: 标准会员 | L4: 5400 | M4: 327 | O4: - | P4: 1 | U4: =DATEDIF(B4,"2025-6-30","y") -> 8 | Z4: linjiaqi86@gmail.com
A5: =ROW()-1 -> 4 | B5: 42789 | C5: 46203 | D5: 焦洋 | E5: 男 | F5: １ | G5: 北京 | I5: 盖娅互娱 | J5: CTO | K5: 标准会员 | L5: 5400 | M5: 329 | N5: 北京12组 | O5: - | P5: 1 | S5: 1 | U5: =DATEDIF(B5,"2025-6-30","y") -> 8 | W5: 已续费 | Z5: jiao.yang.bupt@gmail.com
A6: =ROW()-1 -> 5 | B6: 42793 | C6: 46203 | D6: 张觅 | E6: 男 | F6: １ | G6: 北京 | I6: 况客科技 | J6: 技术合伙人 | K6: 标准会员 | L6: 5400 | M6: 332 | N6: 北京13组 | O6: - | P6: 1 | U6: =DATEDIF(B6,"2025-6-30","y") -> 8 | W6: 已续费 | Z6: zhm83@163.com
A7: =ROW()-1 -> 6 | B7: 42800 | C7: 46203 | D7: 陈颖棠 | E7: 男 | F7: １ | G7: 广州 | I7: 论客科技（广州）有限公司 | J7: 首席架构师 | K7: 高级会员 | L7: 9216 | M7: 337 | O7: - | P7: 1 | U7: =DATEDIF(B7,"2025-6-30","y") -> 8 | Z7: cyt@mailtech.cn
A8: =ROW()-1 -> 7 | B8: 42801 | C8: 46203 | D8: 黎宏伟 | E8: 男 | F8: １ | G8: 成都 | I8: 成都市美幻科技有限公司 | J8: 技术总监 | K8: 标准会员 | L8: 5400 | M8: 333 | O8: - | P8: 1 | U8: =DATEDIF(B8,"2025-6-30","y") -> 8 | Z8: lhwdev@qq.com
A9: =ROW()-1 -> 8 | B9: 42807 | C9: 46203 | D9: 李伟辰 | E9: 男 | F9: １ | G9: 北京 | I9: 北京知道创宇信息技术有限公司 | J9: 技术VP | K9: 标准会员 | L9: 5400 | M9: 336 | N9: 北京12组 | O9: - | P9: 1 | U9: =DATEDIF(B9,"2025-6-30","y") -> 8 | W9: 已续费 | Z9: liwc@knownsec.com
A10: =ROW()-1 -> 9 | B10: 42815 | C10: 46203 | D10: 崔浩波 | E10: 男 | F10: １ | G10: 北京 | I10: 北京嗨学网教育科技有限公司 | J10: CTO | K10: 标准会员 | L10: 5400 | M10: 340 | N10: 北京12组 | O10: - | P10: 1 | S10: 1 | U10: =DATEDIF(B10,"2025-6-30","y") -> 8 | W10: 已续费 | Z10: cuihaobo@gmail.com
A11: =ROW()-1 -> 10 | B11: 42838 | C11: 46203 | D11: 任腾 | E11: 男 | F11: １ | G11: 硅谷 | I11: AI Rudder | J11: CEO | K11: 标准会员 | L11: 5400 | M11: 346 | O11: - | P11: 1 | U11: =DATEDIF(B11,"2025-6-30","y") -> 8 | Z11: teng.ren@airudder.com
A12: =ROW()-1 -> 11 | B12: 42839 | C12: 46203 | D12: 李晨丰 | E12: 男 | F12: １ | G12: 深圳 | H12: 1 | I12: 深圳米筐科技有限公司 | J12: COO | K12: 标准会员 | L12: 5400 | M12: 347 | O12: - | P12: 1 | U12: =DATEDIF(B12,"2025-6-30","y") -> 8 | Z12: kangol@ricequant.com
A13: =ROW()-1 -> 12 | B13: 42849 | C13: 46203 | D13: 钱小军 | E13: 男 | F13: １ | G13: 上海 | I13: 安永中国咨询 | J13: 金融科技咨询经理 | K13: 标准会员 | L13: 5400 | M13: 349 | O13: - | P13: 1 | U13: =DATEDIF(B13,"2025-6-30","y") -> 8 | Z13: abelqian@vip.sina.com
A14: =ROW()-1 -> 13 | B14: 42866 | C14: 46203 | D14: 王翱宇 | E14: 男 | F14: １ | G14: 杭州 | I14: 杭州谐云科技有限公司 | J14: CEO | K14: 标准会员 | L14: 5400 | M14: 356 | O14: - | P14: 1 | U14: =DATEDIF(B14,"2025-6-30","y") -> 8 | Z14: way@harmonycloud.cn
A15: =ROW()-1 -> 14 | B15: 42912 | C15: 46203 | D15: 徐庆新 | E15: 男 | F15: １ | G15: 苏州 | I15: 苏州乐佰图信息技术有限公司 | J15: 产品总监 | K15: 标准会员 | L15: 5400 | M15: 3700 | O15: - | P15: 1 | U15: =DATEDIF(B15,"2025-6-30","y") -> 8 | Z15: xuqingxin@gmail.com
A16: =ROW()-1 -> 15 | B16: 42874 | C16: 46203 | D16: 暨家愉 | E16: 男 | F16: １ | G16: 广州 | I16: 腾讯 | J16: 专家架构师 | K16: 标准会员 | L16: 5400 | M16: 361 | O16: - | P16: 1 | S16: 1 | U16: =DATEDIF(B16,"2025-6-30","y") -> 8 | Z16: jiayu.ji@gmail.com
A17: =ROW()-1 -> 16 | B17: 42886 | C17: 46203 | D17: 肖毅 | E17: 男 | F17: １ | G17: 成都 | I17: 成都智客科技有限公司 | J17: CEO | K17: 标准会员 | L17: 5400 | M17: 362 | O17: - | P17: 1 | U17: =DATEDIF(B17,"2025-6-30","y") -> 8 | Z17: xiaoyi@aoasp.com
A18: =ROW()-1 -> 17 | B18: 42927 | C18: 46203 | D18: 曹祖鹏 | E18: 男 | F18: １ | G18: 南京 | I18: 南京知亦行信息技术有限公司 | J18: CTO | K18: 标准会员 | L18: 5400 | M18: 376 | O18: - | P18: 1 | U18: =DATEDIF(B18,"2025-6-30","y") -> 7 | Z18: caozupeng@139.com
A19: =ROW()-1 -> 18 | B19: 42935 | C19: 46203 | D19: 杨振东 | E19: 男 | F19: １ | G19: 上海 | I19: 上海方亿信息科技有限公司 | J19: 联合创始人&CTO | K19: 高级会员 | L19: 9216 | M19: 383 | O19: - | P19: 1 | U19: =DATEDIF(B19,"2025-6-30","y") -> 7 | Z19: yzd@aso360.com
A20: =ROW()-1 -> 19 | B20: 42936 | C20: 46203 | D20: 张志成 | E20: 男 | F20: １ | G20: 杭州 | I20: 阿里巴巴达摩院 | J20: 高级技术专家 | K20: 标准会员 | L20: 5400 | M20: 388 | O20: - | P20: 1 | U20: =DATEDIF(B20,"2025-6-30","y") -> 7 | Z20: zczhang.hvac@gmail.com
A21: =ROW()-1 -> 20 | B21: 42941 | C21: 46203 | D21: 杨红光 | E21: 男 | F21: １ | G21: 北京 | I21: 1Box | J21: CTO | K21: 标准会员 | L21: 5400 | M21: 394 | N21: 北京13组 | O21: - | P21: 1 | U21: =DATEDIF(B21,"2025-6-30","y") -> 7 | W21: 已续费 | Z21: njyhg@163.com
A22: =ROW()-1 -> 21 | B22: 42954 | C22: 46203 | D22: 杨帅麒 | E22: 男 | F22: １ | G22: 上海 | I22: 上海盛大汽车服务集团 | J22: CTO | K22: 标准会员 | L22: 5400 | M22: 402 | O22: - | P22: 1 | R22: 无地址 | U22: =DATEDIF(B22,"2025-6-30","y") -> 7 | Z22: 408482214@qq.com
A23: =ROW()-1 -> 22 | B23: 42957 | C23: 46203 | D23: 胡继伟 | E23: 男 | F23: １ | G23: 北京 | I23: 合思 | J23: 架构师 | K23: 标准会员 | L23: 5400 | M23: 404 | N23: 北京13组 | O23: - | P23: 1 | S23: 1 | U23: =DATEDIF(B23,"2025-6-30","y") -> 7 | W23: 已续费 | Z23: hu_jiwei@foxmail.com
A24: =ROW()-1 -> 23 | B24: 42970 | C24: 46203 | D24: 沈旸 | E24: 男 | F24: 0 | G24: 北京 | I24: 联易融 | J24: 副总裁 | K24: 标准会员 | L24: 5400 | M24: 407 | N24: 北京12组 | O24: - | P24: 1 | U24: =DATEDIF(B24,"2025-6-30","y") -> 7 | W24: 已续费 | Z24: yang.shen.it@gmail.com
A25: =ROW()-1 -> 24 | B25: 42988 | C25: 46203 | D25: 杨威 | E25: 男 | F25: １ | G25: 北京 | I25: 明略科技 | J25: 技术副总裁 | K25: 标准会员 | L25: 5400 | M25: 81 | N25: 北京0组 | O25: - | P25: 1 | U25: =DATEDIF(B25,"2025-6-30","y") -> 7 | W25: 已续费 | Z25: yangwei@rongcloud.cn
A26: =ROW()-1 -> 25 | B26: 43000 | C26: 46203 | D26: 褚亮 | E26: 男 | F26: １ | G26: 杭州 | I26: 杭州咿啦科技有限公司 | J26: 联合创始人 & CTO | K26: 标准会员 | L26: 5400 | M26: 418 | O26: - | P26: 1 | S26: 1 | U26: =DATEDIF(B26,"2025-6-30","y") -> 7 | Z26: chuliang@ellabook.cn
A27: =ROW()-1 -> 26 | B27: 43004 | C27: 46203 | D27: 沈淦 | E27: 男 | F27: １ | G27: 杭州 | I27: 杭州正马软件科技有限公司 | J27: CTO | K27: 标准会员 | L27: 5400 | M27: 419 | O27: - | P27: 1 | U27: =DATEDIF(B27,"2025-6-30","y") -> 7 | Z27: floatin@sina.com
A28: =ROW()-1 -> 27 | B28: 43006 | C28: 46203 | D28: 蒋宏飞 | E28: 男 | F28: １ | G28: 北京 | I28: 作业帮 | J28: 研究员 | K28: 标准会员 | L28: 5400 | M28: 423 | N28: 北京16组 | O28: - | P28: 1 | S28: 1 | U28: =DATEDIF(B28,"2025-6-30","y") -> 7 | W28: 已续费 | Z28: hf.jiang@qq.com
A29: =ROW()-1 -> 28 | B29: 43017 | C29: 46203 | D29: 苏锐 | E29: 男 | F29: １ | G29: 北京 | I29: Juicedata, Inc | J29: 合伙人 | K29: 标准会员 | L29: 5400 | M29: 424 | N29: 北京0组 | O29: - | P29: 1 | U29: =DATEDIF(B29,"2025-6-30","y") -> 7 | W29: 已续费 | Z29: suave.su@gmail.com
A30: =ROW()-1 -> 29 | B30: 43051 | C30: 46203 | D30: 王志刚 | E30: 男 | F30: １ | G30: 深圳 | I30: 招商基金 | J30: 副总监 | K30: 标准会员 | L30: 5400 | M30: 433 | O30: - | P30: 1 | S30: 1 | U30: =DATEDIF(B30,"2025-6-30","y") -> 7 | Z30: zhigang78@163.com
A31: =ROW()-1 -> 30 | B31: 43069 | C31: 46203 | D31: 欧文盛 | E31: 男 | F31: １ | G31: 北京 | I31: 北京泰迪熊移动科技有限公司 | J31: CTO | K31: 高级会员 | L31: 9216 | M31: 439 | N31: 北京33组 | O31: - | P31: 1 | U31: =DATEDIF(B31,"2025-6-30","y") -> 7 | W31: 已续费 | Z31: ouwensheng@teddymobile.cn
A32: =ROW()-1 -> 31 | B32: 43080 | C32: 46203 | D32: 王浩 | E32: 男 | F32: 0 | G32: 上海 | I32: 贵州小爱机器人科技有限公司 | J32: CTO | K32: 标准会员 | L32: 5400 | M32: 443 | O32: - | P32: 1 | U32: =DATEDIF(B32,"2025-6-30","y") -> 7 | Z32: wanghao@metasigncloud.com
A33: =ROW()-1 -> 32 | B33: 43082 | C33: 46203 | D33: 樊伟伟 | E33: 男 | F33: １ | G33: 南京 | I33: 微鲤 | J33: 技术总监 | K33: 标准会员 | L33: 5400 | M33: 444 | O33: - | P33: 1 | U33: =DATEDIF(B33,"2025-6-30","y") -> 7 | Z33: fanweiwei@weli.cn
A34: =ROW()-1 -> 33 | B34: 43095 | C34: 46203 | D34: 肖剑涛 | E34: 男 | F34: １ | G34: 北京 | I34: 成绎半导体 | J34: 联合创始人 | K34: 标准会员 | L34: 5400 | M34: 449 | N34: 北京22组 | O34: - | P34: 1 | U34: =DATEDIF(B34,"2025-6-30","y") -> 7 | W34: 已续费 | Z34: xiaojiantao@vip.sina.com
A35: =ROW()-1 -> 34 | B35: 43095 | C35: 46203 | D35: 李少春 | E35: 男 | F35: １ | G35: 广州 | I35: 广州博泰数据有限公司 | J35: 总经理 | K35: 标准会员 | L35: 5400 | M35: 451 | O35: - | P35: 1 | U35: =DATEDIF(B35,"2025-6-30","y") -> 7 | Z35: cylsc@163.com
A36: =ROW()-1 -> 35 | B36: 43096 | C36: 46203 | D36: 于君泽 | E36: 男 | F36: １ | G36: 成都 | I36: 中生代技术 | J36: 创始人 | K36: 标准会员 | L36: 5400 | M36: 452 | O36: - | P36: 1 | U36: =DATEDIF(B36,"2025-6-30","y") -> 7 | Z36: 5581012@qq.com
A37: =ROW()-1 -> 36 | B37: 43098 | C37: 46203 | D37: 李列为 | E37: 男 | F37: １ | G37: 南京 | I37: 江苏华博实业集团有限公司 | J37: CTO | K37: 标准会员 | L37: 5400 | M37: 453 | O37: - | P37: 1 | U37: =DATEDIF(B37,"2025-6-30","y") -> 7 | Z37: 7538350@qq.com
A38: =ROW()-1 -> 37 | B38: 43117 | C38: 46203 | D38: 邹永强 | E38: 男 | F38: 0 | G38: 北京 | I38: 云账户 | J38: 联合创始人兼CTO | K38: 高级会员 | L38: 9216 | M38: 456 | N38: 北京24组 | O38: - | P38: 1 | S38: 1 | U38: =DATEDIF(B38,"2025-6-30","y") -> 7 | W38: 已续费 | Z38: yongqiangzou@gmail.com
A39: =ROW()-1 -> 38 | B39: 43128 | C39: 46203 | D39: 马力遥 | E39: 男 | F39: １ | G39: 成都 | I39: 互联极简网络科技成都有限公司 | J39: 联合创始人 CTO | K39: 标准会员 | L39: 5400 | M39: 460 | O39: - | P39: 1 | U39: =DATEDIF(B39,"2025-6-30","y") -> 7 | Z39: nelson.ma@gsafer.com
A40: =ROW()-1 -> 39 | B40: 43132 | C40: 46203 | D40: 吴传兵 | E40: 男 | F40: １ | G40: 广州 | I40: 广州味美优品食品科技有限公司 | J40: CTO | K40: 标准会员 | L40: 5400 | M40: 462 | O40: - | P40: 1 | U40: =DATEDIF(B40,"2025-6-30","y") -> 7 | Z40: whueric@gmail.com
A41: =ROW()-1 -> 40 | B41: 43159 | C41: 46203 | D41: 崔俊涛 | E41: 男 | F41: 0 | G41: 上海 | I41: 上海万位数字技术有限公司 | J41: CTO | K41: 高级会员 | L41: 9216 | M41: 468 | O41: - | P41: 1 | U41: =DATEDIF(B41,"2025-6-30","y") -> 7 | Z41: juntaocui@gmail.com
A42: =ROW()-1 -> 41 | B42: 43172 | C42: 46203 | D42: 黄振华 | E42: 男 | F42: １ | G42: 北京 | I42: 华策影视集团 | J42: 总助兼科技数字中心总经理 | K42: 标准会员 | L42: 5400 | M42: 479 | N42: 北京13组 | O42: - | P42: 1 | U42: =DATEDIF(B42,"2025-6-30","y") -> 7 | W42: 已续费 | Z42: zhenhua_edward@qq.com
A43: =ROW()-1 -> 42 | B43: 43178 | C43: 46203 | D43: 尹雯玉 | E43: 女 | F43: １ | G43: 北京 | I43: 北京搜狐新媒体信息技术有限公司 | J43: 高级技术经理 | K43: 标准会员 | L43: 5400 | M43: 484 | N43: 北京0组 | O43: - | P43: 1 | S43: 1 | U43: =DATEDIF(B43,"2025-6-30","y") -> 7 | W43: 无需续费 | Z43: amaaanda@163.com
A44: =ROW()-1 -> 43 | B44: 43178 | C44: 46203 | D44: 陈海 | E44: 男 | F44: １ | G44: 北京 | I44: 中信银行 | J44: 处长 | K44: 标准会员 | L44: 5400 | M44: 486 | N44: 北京13组 | O44: - | P44: 1 | S44: 1 | U44: =DATEDIF(B44,"2025-6-30","y") -> 7 | W44: 已续费 | Z44: chenhai@citicbank.com
A45: =ROW()-1 -> 44 | B45: 43179 | C45: 46203 | D45: 龚凌晖 | E45: 男 | F45: １ | G45: 上海 | I45: Strikingly | J45: 技术VP | K45: 标准会员 | L45: 5400 | M45: 489 | O45: - | P45: 1 | U45: =DATEDIF(B45,"2025-6-30","y") -> 7 | Z45: i@glh.co
A46: =ROW()-1 -> 45 | B46: 43185 | C46: 46203 | D46: 高琦 | E46: 男 | F46: １ | G46: 北京 | I46: 北京搜狐新媒体信息技术有限公司 | J46: 研发总监 | K46: 标准会员 | L46: 5400 | M46: 569 | N46: 北京0组 | O46: - | P46: 1 | U46: =DATEDIF(B46,"2025-6-30","y") -> 7 | W46: 无需续费 | Z46: 85285919@qq.com
A47: =ROW()-1 -> 46 | B47: 43187 | C47: 46203 | D47: 徐桢虎 | E47: 男 | F47: １ | G47: 成都 | I47: 封面传媒科技&川报集团 | J47: 封面传媒科技 副总经理兼川报集团 特聘首席工程师 | K47: 标准会员 | L47: 5400 | M47: 497 | O47: - | P47: 1 | S47: 1 | U47: =DATEDIF(B47,"2025-6-30","y") -> 7 | Z47: 290415881@qq.com
A48: =ROW()-1 -> 47 | B48: 43194 | C48: 46203 | D48: 曹犟 | E48: 男 | F48: １ | G48: 北京 | I48: 神策数据 | J48: 联合创始人&CTO | K48: 高级会员 | L48: 9216 | M48: 501 | N48: 北京0组 | O48: - | P48: 1 | U48: =DATEDIF(B48,"2025-6-30","y") -> 7 | W48: 已续费 | Z48: caojiang@sensorsdata.cn
A49: =ROW()-1 -> 48 | B49: 43200 | C49: 46203 | D49: 杨文 | E49: 男 | F49: １ | G49: 深圳 | I49: AfterShip | J49: 高级技术经理 | K49: 标准会员 | L49: 5400 | M49: 509 | O49: - | P49: 1 | U49: =DATEDIF(B49,"2025-6-30","y") -> 7 | Z49: yangwen.yw@gmail.com
A50: =ROW()-1 -> 49 | B50: 43202 | C50: 46203 | D50: 白德鑫 | E50: 男 | F50: １ | G50: 北京 | I50: 关税宝 | J50: CTO | K50: 标准会员 | L50: 5400 | M50: 513 | N50: 北京38组 | O50: - | P50: 1 | U50: =DATEDIF(B50,"2025-6-30","y") -> 7 | W50: 已续费 | Z50: ioke@qq.com
A51: =ROW()-1 -> 50 | B51: 43218 | C51: 46203 | D51: 梁杞平 | E51: 男 | F51: １ | G51: 深圳 | I51: 深圳市互盟科技股份有限公司 | J51: 副总经理&技术顾问 | K51: 标准会员 | L51: 5400 | M51: 524 | O51: - | P51: 1 | U51: =DATEDIF(B51,"2025-6-30","y") -> 7 | Z51: 87256052@qq.com
A52: =ROW()-1 -> 51 | B52: 43227 | C52: 46203 | D52: 周雨桐 | E52: 男 | F52: １ | G52: 南京 | I52: 南京功夫豆信息科技有限公司 | J52: CTO | K52: 标准会员 | L52: 5400 | M52: 545 | O52: - | P52: 1 | S52: 1 | U52: =DATEDIF(B52,"2025-6-30","y") -> 7 | Z52: zhouyt@outlook.com
A53: =ROW()-1 -> 52 | B53: 43228 | C53: 46203 | D53: 李涛 | E53: 男 | F53: １ | G53: 成都 | I53: 上海骐原智能科技有限公司 | J53: 联合创始人 | K53: 标准会员 | L53: 5400 | M53: 547 | O53: - | P53: 1 | U53: =DATEDIF(B53,"2025-6-30","y") -> 7 | Z53: lit_aaron@hotmail.com
A54: =ROW()-1 -> 53 | B54: 43228 | C54: 46203 | D54: 刘明 | E54: 男 | F54: １ | G54: 南京 | I54: 三星电子（中国） | J54: 研发中心＋智能电视应用软件部长 | K54: 标准会员 | L54: 5400 | M54: 546 | O54: - | P54: 1 | S54: 1 | U54: =DATEDIF(B54,"2025-6-30","y") -> 7 | Z54: minging.liu@samsung.com
A55: =ROW()-1 -> 54 | B55: 43230 | C55: 46203 | D55: 吴焕红 | E55: 男 | F55: １ | G55: 南京 | I55: 中国旅游集团旅行服务有限公司 | J55: 解决方案中心总经理 | K55: 标准会员 | L55: 5400 | M55: 552 | O55: - | P55: 1 | U55: =DATEDIF(B55,"2025-6-30","y") -> 7 | Z55: lispvv@163.com
A56: =ROW()-1 -> 55 | B56: 43273 | C56: 46203 | D56: 杨晶生 | E56: 男 | F56: １ | G56: 上海 | I56: 字节跳动 | J56: 技术Leader | K56: 高级会员 | L56: 9216 | M56: 589 | O56: - | P56: 1 | S56: 1 | U56: =DATEDIF(B56,"2025-6-30","y") -> 7 | Z56: zacyang@outlook.com
A57: =ROW()-1 -> 56 | B57: 43275 | C57: 46203 | D57: 曾義峰 | E57: 男 | F57: 0 | G57: 台北 | I57: 書亞集成股份有限公司 | J57: CTO | K57: 标准会员 | L57: 5400 | M57: 597 | O57: - | P57: 1 | U57: =DATEDIF(B57,"2025-6-30","y") -> 7 | Z57: yftzeng@gmail.com
A58: =ROW()-1 -> 57 | B58: 43275 | C58: 46203 | D58: 王銘駿 | E58: 男 | F58: 0 | G58: 台北 | I58: DFI 友通资讯 | J58: Manager | K58: 标准会员 | L58: 5400 | M58: 606 | O58: - | P58: 1 | U58: =DATEDIF(B58,"2025-6-30","y") -> 7 | Z58: hades.wang@hotmail.com
A59: =ROW()-1 -> 58 | B59: 43275 | C59: 46203 | D59: 林秉毅 | E59: 男 | F59: ０ | G59: 台北 | I59: 天鏡科技 | J59: CTO | K59: 标准会员 | L59: 5400 | M59: 615 | O59: - | P59: - | U59: =DATEDIF(B59,"2025-6-30","y") -> 7 | Z59: cookys@gmail.com
A60: =ROW()-1 -> 59 | B60: 43275 | C60: 46203 | D60: 游舒帆 | E60: 男 | F60: ０ | G60: 台北 | I60: 箴亞管理顧問有限公司 | J60: 負責人 | K60: 标准会员 | L60: 5400 | M60: 599 | O60: - | P60: 1 | U60: =DATEDIF(B60,"2025-6-30","y") -> 7 | Z60: james00668@gmail.com
A61: =ROW()-1 -> 60 | B61: 43275 | C61: 46203 | D61: 施政源 | E61: 男 | F61: ０ | G61: 台北 | I61: 寓意科技 | J61: CEO | K61: 标准会员 | L61: 5400 | M61: 600 | O61: - | P61: 1 | U61: =DATEDIF(B61,"2025-6-30","y") -> 7 | Z61: paul.shih@fable.com.tw
A62: =ROW()-1 -> 61 | B62: 43275 | C62: 46203 | D62: 莊靈 | E62: 女 | F62: ０ | G62: 台北 | I62: 慧邦科技股份有限公司 | J62: CTO | K62: 标准会员 | L62: 5400 | M62: 612 | O62: - | P62: 1 | U62: =DATEDIF(B62,"2025-6-30","y") -> 7 | Z62: in2@gamesofa.com
A63: =ROW()-1 -> 62 | B63: 43275 | C63: 46203 | D63: 蔣鐙緯 | E63: 男 | F63: ０ | G63: 台北 | I63: 派仕科技有限公司 | J63: 聯合創始人兼產品暨技術整合總監 | K63: 标准会员 | L63: 5400 | M63: 605 | O63: - | P63: 1 | U63: =DATEDIF(B63,"2025-6-30","y") -> 7 | Z63: ernest@pafers.com
A64: =ROW()-1 -> 63 | B64: 43275 | C64: 46203 | D64: 林瑞男 | E64: 男 | F64: 0 | G64: 台北 | I64: PIXNET | J64: 技術總監 | K64: 标准会员 | L64: 5400 | M64: 618 | O64: - | P64: 1 | U64: =DATEDIF(B64,"2025-6-30","y") -> 7 | Z64: jnlinn@gmail.com
A65: =ROW()-1 -> 64 | B65: 43275 | C65: 46203 | D65: 王志清 | E65: 男 | F65: ０ | G65: 台北 | I65: LEADBEST, 安世泰有限公司 | J65: 聯合創辦暨合夥人 | K65: 标准会员 | L65: 5400 | M65: 595 | O65: - | P65: 1 | U65: =DATEDIF(B65,"2025-6-30","y") -> 7 | Z65: rl@polydice.com
A66: =ROW()-1 -> 65 | B66: 43275 | C66: 46203 | D66: 李致緯 | E66: 男 | F66: ０ | G66: 台北 | I66: iCook 愛料理 | J66: CTO | K66: 标准会员 | L66: 5400 | M66: 598 | O66: - | P66: - | U66: =DATEDIF(B66,"2025-6-30","y") -> 7 | Z66: jerk.shih@gmail.com
A67: =ROW()-1 -> 66 | B67: 43277 | C67: 46203 | D67: 梁齐良 | E67: 男 | F67: １ | G67: 上海 | I67: 中智关爱通（上海）科技股份有限公司 | J67: 研发总监/架构师 | K67: 高级会员 | L67: 9216 | M67: 591 | O67: - | P67: 1 | S67: 1 | U67: =DATEDIF(B67,"2025-6-30","y") -> 7 | Z67: daniel.liang@guanaitong.com
A68: =ROW()-1 -> 67 | B68: 43277 | C68: 46203 | D68: 杨勇 | E68: 男 | F68: １ | G68: 上海 | I68: 中智关爱通（上海）科技股份有限公司 | J68: 技术总监 | K68: 高级会员 | L68: 9216 | M68: 592 | O68: - | P68: 1 | S68: 1 | U68: =DATEDIF(B68,"2025-6-30","y") -> 7 | Z68: young.yang@guanaitong.com
A69: =ROW()-1 -> 68 | B69: 43285 | C69: 46203 | D69: 程飞 | E69: 男 | F69: １ | G69: 成都 | I69: 四川乐为科技有限公司 | J69: 总经理 | K69: 标准会员 | L69: 5400 | M69: 626 | O69: - | P69: 1 | U69: =DATEDIF(B69,"2025-6-30","y") -> 6 | Z69: 332800462@qq.com
A70: =ROW()-1 -> 69 | B70: 43285 | C70: 46203 | D70: 庞向才 | E70: 男 | F70: １ | G70: 上海 | I70: 金数汇（上海）数据科技有限公司 | J70: CEO | K70: 标准会员 | L70: 5400 | M70: 624 | O70: - | P70: 1 | U70: =DATEDIF(B70,"2025-6-30","y") -> 6 | Z70: pangxiangcai@gmail.com
A71: =ROW()-1 -> 70 | B71: 43305 | C71: 46203 | D71: 林秉忠 | E71: 男 | F71: ０ | G71: 台北 | I71: 雄獅旅遊 | J71: 副總經理 | K71: 标准会员 | L71: 5400 | M71: 667 | O71: - | P71: - | R71: 无地址 | U71: =DATEDIF(B71,"2025-6-30","y") -> 6 | Z71: 111111@qq.com
A72: =ROW()-1 -> 71 | B72: 43305 | C72: 46203 | D72: 李境展 Tomas Li | E72: 男 | F72: ０ | G72: 台北 | I72: Titansoft Pte Ltd_新加坡商鈦坦科技股份有限公司台灣分公司 | J72: General Manager | K72: 标准会员 | L72: 5400 | M72: 774 | O72: - | P72: - | U72: =DATEDIF(B72,"2025-6-30","y") -> 6 | Z72: #N/A
A73: =ROW()-1 -> 72 | B73: 43305 | C73: 46203 | D73: 黃智彬 | E73: 男 | F73: ０ | G73: 台北 | I73: 舉手電商 | J73: COO | K73: 标准会员 | L73: 5400 | M73: 775 | O73: - | P73: - | U73: =DATEDIF(B73,"2025-6-30","y") -> 6 | Z73: #N/A
A74: =ROW()-1 -> 73 | B74: 43319 | C74: 46203 | D74: 梁强 | E74: 男 | F74: １ | G74: 成都 | I74: 东方金信 | J74: 解决方案西区总监 | K74: 标准会员 | L74: 5400 | M74: 646 | O74: - | P74: 1 | S74: 1 | U74: =DATEDIF(B74,"2025-6-30","y") -> 6 | Z74: billy5118@sina.com
A75: =ROW()-1 -> 74 | B75: 43320 | C75: 46203 | D75: 胡志明 | E75: 男 | F75: １ | G75: 上海 | I75: 携程租车 | J75: 租车&车船CTO | K75: 标准会员 | L75: 5400 | M75: 647 | O75: - | P75: 1 | S75: 1 | U75: =DATEDIF(B75,"2025-6-30","y") -> 6 | Z75: zmhu@qq.com
A76: =ROW()-1 -> 75 | B76: 43335 | C76: 46203 | D76: 王仁明 | E76: 男 | F76: １ | G76: 广州 | I76: 哈尔滨工业大学人工智能研究院 | J76: 架构师 | K76: 标准会员 | L76: 5400 | M76: 656 | O76: - | P76: 1 | U76: =DATEDIF(B76,"2025-6-30","y") -> 6 | Z76: 971762977@qq.com
A77: =ROW()-1 -> 76 | B77: 43336 | C77: 46203 | D77: 吴坚 | E77: 男 | F77: １ | G77: 上海 | I77: 保时捷 (上海)数字科技有限公司 | J77: 软件研发团队负责人 | K77: 标准会员 | L77: 5400 | M77: 657 | O77: - | P77: 1 | S77: 1 | U77: =DATEDIF(B77,"2025-6-30","y") -> 6 | Z77: genewoo@gmail.com
A78: =ROW()-1 -> 77 | B78: 43349 | C78: 46203 | D78: 李渭宁 | E78: 男 | F78: １ | G78: 广州 | I78: 汇丰科技 | J78: 企业架构师 | K78: 标准会员 | L78: 5400 | M78: 666 | O78: - | P78: 1 | U78: =DATEDIF(B78,"2025-6-30","y") -> 6 | Z78: lwiky@live.com
A79: =ROW()-1 -> 78 | B79: 43354 | C79: 46203 | D79: 于游 | E79: 男 | F79: １ | G79: 北京 | I79: 金山云大模型 | J79: 首席布道师 | K79: 高级会员 | L79: 9216 | M79: 668 | N79: 北京22组 | O79: - | P79: 1 | U79: =DATEDIF(B79,"2025-6-30","y") -> 6 | W79: 已续费 | Z79: yuyou_1983@163.com
A80: =ROW()-1 -> 79 | B80: 43356 | C80: 46203 | D80: 朱伟明 | E80: 男 | F80: １ | G80: 北京 | I80: 易企秀 | J80: CTO | K80: 标准会员 | L80: 5400 | M80: 672 | N80: 北京22组 | O80: - | P80: 1 | S80: 1 | U80: =DATEDIF(B80,"2025-6-30","y") -> 6 | W80: 已续费 | Z80: 260964587@qq.com
A81: =ROW()-1 -> 80 | B81: 43360 | C81: 46203 | D81: 裴华 | E81: 男 | F81: １ | G81: 上海 | I81: 银联智策顾问（上海）有限公司 | J81: 技术总监 | K81: 标准会员 | L81: 5400 | M81: 673 | O81: - | P81: 1 | U81: =DATEDIF(B81,"2025-6-30","y") -> 6 | Z81: pumayeah@163.com
A82: =ROW()-1 -> 81 | B82: 43361 | C82: 46203 | D82: 韩鑫 | E82: 男 | F82: １ | G82: 北京 | I82: 双极网络 | J82: 联合创始人 | K82: 标准会员 | L82: 5400 | M82: 675 | N82: 北京12组 | O82: - | P82: 1 | U82: =DATEDIF(B82,"2025-6-30","y") -> 6 | W82: 已续费 | Z82: hanxincade@gmail.com
A83: =ROW()-1 -> 82 | B83: 43367 | C83: 46203 | D83: 周敏 | E83: 男 | F83: １ | G83: 北京 | I83: 美团 | J83: 架构师 | K83: 标准会员 | L83: 5400 | M83: 690 | N83: 北京24组 | O83: - | P83: 1 | S83: 1 | U83: =DATEDIF(B83,"2025-6-30","y") -> 6 | W83: 已续费 | Z83: zhoumin422@163.com
A84: =ROW()-1 -> 83 | B84: 43385 | C84: 46203 | D84: 皮兴忠 | E84: 男 | F84: １ | G84: 上海 | I84: 中智关爱通（上海）科技股份有限公司 | J84: COO/CTO | K84: 高级会员 | L84: 9216 | M84: 686 | O84: - | P84: 1 | S84: 1 | U84: =DATEDIF(B84,"2025-6-30","y") -> 6 | Z84: 642603234@qq.com
A85: =ROW()-1 -> 84 | B85: 43402 | C85: 46203 | D85: 丁言龙 | E85: 男 | F85: １ | G85: 上海 | I85: 恒为科技智算 | J85: 总经理&恒科智算CEO | K85: 标准会员 | L85: 5400 | M85: 694 | O85: - | P85: 1 | U85: =DATEDIF(B85,"2025-6-30","y") -> 6 | Z85: 12935204@qq.com
A86: =ROW()-1 -> 85 | B86: 43402 | C86: 46203 | D86: 单致豪 | E86: 男 | F86: １ | G86: 深圳 | I86: 腾讯 | J86: 开源联盟主席&腾源会导师 | K86: 标准会员 | L86: 5400 | M86: 693 | O86: - | P86: 1 | S86: 1 | U86: =DATEDIF(B86,"2025-6-30","y") -> 6 | Z86: 14999610@qq.com
A87: =ROW()-1 -> 86 | B87: 43406 | C87: 46203 | D87: 邓蔚 | E87: 男 | F87: ０ | G87: 上海 | I87: 北京瑞达恒建筑咨询有限公司 | J87: 技术合伙人 | K87: 标准会员 | L87: 5400 | M87: 699 | O87: - | P87: 1 | U87: =DATEDIF(B87,"2025-6-30","y") -> 6 | Z87: wayne.deng.cn@gmail.com
A88: =ROW()-1 -> 87 | B88: 43406 | C88: 46203 | D88: 钟晓樑 | E88: 男 | F88: １ | G88: 苏州 | I88: 苏州盖雅信息技术有限公司 | J88: 产品总监 | K88: 标准会员 | L88: 5400 | M88: 700 | O88: - | P88: 1 | U88: =DATEDIF(B88,"2025-6-30","y") -> 6 | Z88: shinezhong77@163.com
A89: =ROW()-1 -> 88 | B89: 43413 | C89: 46203 | D89: 刘昊臻 | E89: 男 | F89: ０ | G89: 广州 | I89: eolinker | J89: CEO | K89: 标准会员 | L89: 5400 | M89: 703 | O89: - | P89: 1 | U89: =DATEDIF(B89,"2025-6-30","y") -> 6 | Z89: zhen@eolinker.com
A90: =ROW()-1 -> 89 | B90: 43426 | C90: 46203 | D90: 白新奋 | E90: 男 | F90: １ | G90: 上海 | I90: 随手 AI | J90: CEO | K90: 标准会员 | L90: 5400 | M90: 720 | O90: 45138 | P90: 1 | U90: =DATEDIF(B90,"2025-6-30","y") -> 6 | Z90: good_bai@qq.com
A91: =ROW()-1 -> 90 | B91: 43425 | C91: 46203 | D91: 吴清忠 | E91: 男 | F91: １ | G91: 武汉 | I91: 北京万界数据武汉分公司 | J91: 技术总监 | K91: 标准会员 | L91: 5400 | M91: 715 | O91: - | P91: 1 | U91: =DATEDIF(B91,"2025-6-30","y") -> 6 | V91: 是 | Z91: qingfly@foxmail.com | AA91: 24-25未续费，25-26续费
A92: =ROW()-1 -> 91 | B92: 43426 | C92: 46203 | D92: 谢文杰 | E92: 男 | F92: ０ | G92: 北京 | I92: 智链ChainNova | J92: CTO | K92: 标准会员 | L92: 5400 | M92: 717 | N92: 北京25组 | O92: - | P92: 1 | U92: =DATEDIF(B92,"2025-6-30","y") -> 6 | W92: 已续费 | Z92: jay@jayxie.com
A93: =ROW()-1 -> 92 | B93: 43426 | C93: 46203 | D93: 庞智 | E93: 男 | F93: １ | G93: 北京 | I93: 青岛绿波源新材料科技有限公司 | J93: 总经理 | K93: 标准会员 | L93: 5400 | M93: 719 | N93: 北京0组 | O93: - | P93: 1 | U93: =DATEDIF(B93,"2025-6-30","y") -> 6 | W93: 已续费 | Z93: 104986208@qq.com
A94: =ROW()-1 -> 93 | B94: 43432 | C94: 46203 | D94: 赵晓光 | E94: 男 | F94: １ | G94: 上海 | I94: 碧桂园生活服务集团 | J94: 副总裁&CTO | K94: 标准会员 | L94: 5400 | M94: 727 | O94: - | P94: 1 | S94: 1 | U94: =DATEDIF(B94,"2025-6-30","y") -> 6 | Z94: xgzhao@bgyfw.com
A95: =ROW()-1 -> 94 | B95: 43434 | C95: 46203 | D95: 张嵩 | E95: 男 | F95: １ | G95: 厦门 | I95: 七匹狼 | J95: CIO | K95: 标准会员 | L95: 5400 | M95: 738 | O95: - | P95: 1 | U95: =DATEDIF(B95,"2025-6-30","y") -> 6 | Z95: zs349596@gmail.com
A96: =ROW()-1 -> 95 | B96: 43434 | C96: 46203 | D96: 邱良军 | E96: 男 | F96: １ | G96: 苏州 | I96: 苏州正雄企业发展有限公司 | J96: CIO | K96: 标准会员 | L96: 5400 | M96: 735 | O96: - | P96: 1 | U96: =DATEDIF(B96,"2025-6-30","y") -> 6 | Z96: alex_qiu@unitedtex.com
A97: =ROW()-1 -> 96 | B97: 43442 | C97: 46203 | D97: 卢鹏 | E97: 男 | F97: １ | G97: 上海 | I97: 众安保险 | J97: 财富线cto | K97: 标准会员 | L97: 5400 | M97: 739 | O97: - | P97: 1 | S97: 1 | U97: =DATEDIF(B97,"2025-6-30","y") -> 6 | Z97: 304069453@qq.com
A98: =ROW()-1 -> 97 | B98: 43446 | C98: 46203 | D98: 蒲永波 | E98: 男 | F98: １ | G98: 成都 | I98: 重庆港澳大家软件产业有限公司 | J98: CTO | K98: 标准会员 | L98: 5400 | M98: 744 | O98: - | P98: 1 | U98: =DATEDIF(B98,"2025-6-30","y") -> 6 | Z98: cldrag@163.com
A99: =ROW()-1 -> 98 | B99: 43447 | C99: 46203 | D99: 丘秉宜 | E99: 男 | F99: ０ | G99: 上海 | I99: eubchain | J99: CEO | K99: 标准会员 | L99: 5400 | M99: 748 | O99: - | P99: 1 | U99: =DATEDIF(B99,"2025-6-30","y") -> 6 | Z99: keithyau.hk@gmail.com
A100: =ROW()-1 -> 99 | B100: 43447 | C100: 46203 | D100: 马进 | E100: 男 | F100: １ | G100: 南京 | I100: 数字小能人 | J100: CEO | K100: 标准会员 | L100: 5400 | M100: 747 | O100: - | P100: 1 | U100: =DATEDIF(B100,"2025-6-30","y") -> 6 | Z100: majin@depthsdata.com
...

Sheet 26年续费金额
A1: 地区 | B1: 求和:续费金额 | C1: 计数:姓名
A2: 北京 | B2: 1730160 | C2: 225
A3: 杭州 | B3: 418184 | C3: 65
A4: 广州 | B4: 637056 | C4: 89
A5: 成都 | B5: 290832 | C5: 46
A6: 硅谷 | B6: 45432 | C6: 14
A7: 深圳 | B7: 888120 | C7: 115
A8: 上海 | B8: 1492776 | C8: 198
A9: 苏州 | B9: 91512 | C9: 14
A10: 南京 | B10: 196248 | C10: 34
A11: 台北 | B11: 91800 | C11: 17
A12: 武汉 | B12: 26160 | C12: 5
A13: 厦门 | B13: 95520 | C13: 18
... A15: 总计 | B15: 6005848 | C15: 841

Sheet 硅谷名单
A1: 待续费会员
A2: 加入时间 | B2: 会籍时间 | C2: 姓名 | D2: 地区 | E2: 公司 | F2: 职位 | G2: 会员类型 | H2: 续费金额
A3: 43976 | B3: 45838 | C3: 张云浩 | D3: 硅谷 | E3: 力扣（LeetCode） | F3: CEO | G3: 高级会员 | H3: 1430
A4: 44228 | B4: 45473 | C4: 王雄 | D4: 硅谷 | E4: 腾讯 | F4: 技术专家 | G4: 高级会员 | H4: 2860
A5: 44316 | B5: 45838 | C5: 曹翔 | D5: 硅谷 | E5: Tik Tok | G5: 高级会员 | H5: 1430
A6: 44565 | B6: 45838 | C6: 王泳帅 | D6: 硅谷 | E6: 宝洁 | F6: CTO | G6: 高级会员 | H6: 1430
A7: 45133 | B7: 45657 | C7: 张俊伟 | D7: 硅谷 | E7: Doordash | F7: Marketplace Tech Lead | G7: 高级会员 | H7: 2145
A8: 45159 | B8: 45838 | C8: 刘正一 James | D8: 硅谷 | E8: 阿里云 | F8: Director of New Business & Innov | G8: 高级会员 | H8: 1430
A9: 43210 | B9: 45657 | C9: 孙超 | D9: 硅谷 | E9: 西部数据 | F9: 高级技术专家 | G9: 高级会员 | H9: 2145
A10: 43210 | B10: 45657 | C10: 潘洋洋 | D10: 硅谷 | E10: VMware | F10: 高级经理 | G10: 高级会员 | H10: 2145
A11: 45262 | B11: 45657 | C11: 叶谦 | D11: 硅谷 | E11: Celerdata Inc. | F11: 联合创始人和COO | G11: 高级会员 | H11: 2145
A12: 45276 | B12: 45657 | C12: 鲁颖 | D12: 硅谷 | E12: Zoom | F12: 研发总监 | G12: 高级会员 | H12: 2145
A13: 42676 | B13: 45657 | C13: 黄东旭 | D13: 硅谷 | E13: PingCAP | F13: CTO | G13: 高级会员 | H13: 2145
A14: 45281 | B14: 45657 | C14: 杨润德 | D14: 硅谷 | E14: Dream Voyage | F14: 联合创始人 | G14: 高级会员 | H14: 2145
A15: 45289 | B15: 45657 | C15: 谢超（星爵） | D15: 硅谷 | E15: Ziliz | F15: CEO | G15: 高级会员 | H15: 2145
A16: 45289 | B16: 45657 | C16: 沙振宇 | D16: 硅谷 | E16: plus.ai | F16: senior staff engineer | G16: 高级会员 | H16: 2145
A17: 45293 | B17: 45657 | C17: 魏长帅 | D17: 硅谷 | E17: LinkedIn | F17: Sr Staff ML Engineer | G17: 高级会员 | H17: 2145
... A31: 45575 | B31: 45940 | C31: Qingsong Wen | D31: 硅谷 | E31: 松鼠AI | F31: 首席科学兼AI研究院院长 | G31: 高级会员 | H31: 2383
A33: 在籍会员
A34: 加入时间 | B34: 会籍时间 | C34: 姓名 | D34: 地区 | E34: 公司 | F34: 职位 | G34: 会员类型
A35: 42838 | B35: 46203 | C35: 任腾 | D35: 硅谷 | E35: AI Rudder | F35: CEO | G35: 标准会员
A36: 43308 | B36: 46934 | C36: 夏澎 | D36: 硅谷 | E36: 博世 | F36: 架构总监 | G36: 标准会员
A37: 44325 | B37: 46203 | C37: 杨森 | D37: 硅谷 | E37: 点线面体 | F37: CEO | G37: 标准会员
A38: 44894 | B38: 46203 | C38: 肖伦文 | D38: 硅谷 | E38: 上海吉谛科技有限公司 | F38: CEO | G38: 标准会员
A39: 45162 | B39: 46203 | C39: 刘洋 | D39: 硅谷 | E39: ScaleFlux Inc. | F39: Chief Architect | G39: 标准会员
A40: 45231 | B40: 46203 | C40: 王文锋 | D40: 硅谷 | E40: Lifecycle AI | F40: CEO | G40: 标准会员
A41: 45295 | B41: 46203 | C41: Tracy Yu | D41: 硅谷 | E41: 大众集团 | F41: 工程经理 | G41: 高级会员
A42: 45490 | B42: 46203 | C42: 董昊 | D42: 硅谷 | E42: Meta | F42: 技术经理/主管 | G42: 高级会员
A43: 45670 | B43: 46203 | C43: Yanjia Guo | D43: 硅谷 | E43: Mathos AI | F43: 联合创始人 | G43: 高级会员
A44: 45679 | B44: 46203 | C44: 段威 | D44: 硅谷 | E44: Snapchat | F44: machine learning engineer, tech lead | G44: 高级会员
A45: 45742 | B45: 46203 | C45: 杨莹 | D45: 硅谷 | E45: Niantic | F45: Product Lead, Growth | G45: 高级会员
A46: 45769 | B46: 46203 | C46: 俞舟 | D46: 硅谷 | E46: Arklex.ai | F46: 联合创始人 | G46: 高级会员
... A50: 45885 | B50: 46203 | C50: 和昊原 | D50: 硅谷 | E50: Netflix | F50: Software Engineer | G50: 高级会员

Sheet 10.31日会籍人数透视
A1: 会籍时间 | B1: (多项)
A3: 地区 | B3: 计数:姓名
A4: 总计

Sheet 新增会员推荐
A1: 2025年新会员入会分布 | F1: 年(加入时间) | G1: 计数:姓名
A2: 序号 | B2: 推荐类别 | C2: 数量 | D2: 比例 | F2: 2015年 | G2: 27
A3: 1 | B3: 自然流量 | C3: 24 | D3: =C3/191 -> 0.12565445 | F3: 2016年 | G3: 45
A4: 2 | B4: 会员推荐 | C4: 132 | D4: =C4/191 -> 0.69109948 | E4: 25年新会员推荐入会人数：6 | F4: 2017年 | G4: 48
A5: 3 | B5: infoQ | C5: 8 | D5: =C5/191 -> 0.041884817 | F5: 2018年 | G5: 94
A6: 4 | B6: 潜在会员 | C6: 3 | D6: =C6/191 -> 0.015706806 | F6: 2019年 | G6: 97
A7: 5 | B7: Kevin | C7: 6 | D7: =C7/191 -> 0.031413613 | F7: 2020年 | G7: 79
A8: 6 | B8: GTLC | C8: 8 | D8: =C8/191 -> 0.041884817 | F8: 2021年 | G8: 99
A9: 7 | B9: 公司 | C9: 2 | D9: =C9/191 -> 0.010471204 | F9: 2022年 | G9: 106
A10: 8 | B10: 老会员回归 | C10: 5 | D10: =C10/191 -> 0.02617801 | F10: 2023年 | G10: 167
A11: 9 | B11: 分会活动 | C11: 2 | D11: =C11/191 -> 0.010471204 | F11: 2024年 | G11: 190
A12: 10 | B12: Selina | C12: 1 | D12: =C12/191 -> 0.0052356021 | F12: 2025年 | G12: 224
A13: 总计 | B13: 25年新增会员 | C13: =SUM(C3:C12) -> 191 | F13: 2026年 | G13: 36
F14: 总计 | G14: 1212
A17: 加入时间 - 年份 | B17: (全部)
A18: 加入时间 - 月份 | B18: (全部)
D19: 入会时间
A20: 推荐大类 | B20: 推荐人 | C20: 计数:姓名 | D20: {=_xlfn.XLOOKUP(B20,会员总表!D:D,会员总表!B:B)} -> #N/A
A21: 暂无 | B21: 暂无 | C21: 654 | D21: {=_xlfn.XLOOKUP(B21,会员总表!D:D,会员总表!B:B)} -> #N/A
A22: 暂无 汇总 | C22: 654 | D22: {=_xlfn.XLOOKUP(B22,会员总表!D:D,会员总表!B:B)} -> 0
A23: 自然流量 | B23: 自然流量-官网 | C23: 10 | D23: {=_xlfn.XLOOKUP(B23,会员总表!D:D,会员总表!B:B)} -> #N/A | E23: 1
B24: 自然流量-朋友 | C24: 4 | D24: {=_xlfn.XLOOKUP(B24,会员总表!D:D,会员总表!B:B)} -> #N/A
B25: 自然流量-公众号 | C25: 6 | D25: {=_xlfn.XLOOKUP(B25,会员总表!D:D,会员总表!B:B)} -> #N/A
B26: 自然流量-朋友圈 | C26: 4 | D26: {=_xlfn.XLOOKUP(B26,会员总表!D:D,会员总表!B:B)} -> #N/A
B27: 乔新亮 | C27: 1 | D27: {=_xlfn.XLOOKUP(B27,会员总表!D:D,会员总表!B:B)} -> #N/A
B28: 自然流量 | C28: 9 | D28: {=_xlfn.XLOOKUP(B28,会员总表!D:D,会员总表!B:B)} -> #N/A
B29: 自然流量-知乎 | C29: 1 | D29: {=_xlfn.XLOOKUP(B29,会员总表!D:D,会员总表!B:B)} -> #N/A
B30: 自然流量-deepseek | C30: 1 | D30: {=_xlfn.XLOOKUP(B30,会员总表!D:D,会员总表!B:B)} -> #N/A
B31: 非会员行业大佬推荐 | C31: 1 | D31: {=_xlfn.XLOOKUP(B31,会员总表!D:D,会员总表!B:B)} -> #N/A
B32: 朋友 | C32: 1 | D32: {=_xlfn.XLOOKUP(B32,会员总表!D:D,会员总表!B:B)} -> #N/A
A33: 自然流量 汇总 | C33: 38 | D33: {=_xlfn.XLOOKUP(B33,会员总表!D:D,会员总表!B:B)} -> 0
A34: 会员推荐 | B34: 郭子龙 | C34: 8 | D34: {=_xlfn.XLOOKUP(B34,会员总表!D:D,会员总表!B:B)} -> 44902
B35: 于功波 | C35: 5 | D35: {=_xlfn.XLOOKUP(B35,会员总表!D:D,会员总表!B:B)} -> 45098
B36: 杨攀 | C36: 30 | D36: {=_xlfn.XLOOKUP(B36,会员总表!D:D,会员总表!B:B)} -> 42773
B37: 赵新龙 | C37: 4 | D37: {=_xlfn.XLOOKUP(B37,会员总表!D:D,会员总表!B:B)} -> 45905
B38: 嵇伟 | C38: 6 | D38: {=_xlfn.XLOOKUP(B38,会员总表!D:D,会员总表!B:B)} -> 43462
B39: 吴炳锡 | C39: 1 | D39: {=_xlfn.XLOOKUP(B39,会员总表!D:D,会员总表!B:B)} -> #N/A
B40: 谢扬 | C40: 1 | D40: {=_xlfn.XLOOKUP(B40,会员总表!D:D,会员总表!B:B)} -> #N/A
B41: 程军 | C41: 1 | D41: {=_xlfn.XLOOKUP(B41,会员总表!D:D,会员总表!B:B)} -> #N/A
B42: 暨家愉 | C42: 2 | D42: {=_xlfn.XLOOKUP(B42,会员总表!D:D,会员总表!B:B)} -> 42874
B43: 郭云烽 | C43: 1 | D43: {=_xlfn.XLOOKUP(B43,会员总表!D:D,会员总表!B:B)} -> 43847
B44: 刘燕清 | C44: 1 | D44: {=_xlfn.XLOOKUP(B44,会员总表!D:D,会员总表!B:B)} -> 44547
B45: 刑佳良 | C45: 1 | D45: {=_xlfn.XLOOKUP(B45,会员总表!D:D,会员总表!B:B)} -> #N/A
B46: 吴亚昆 | C46: 9 | D46: {=_xlfn.XLOOKUP(B46,会员总表!D:D,会员总表!B:B)} -> 44503
B47: 黄哲铿 | C47: 7 | D47: 44403
B48: 胡溢洋 | C48: 2 | D48: {=_xlfn.XLOOKUP(B48,会员总表!D:D,会员总表!B:B)} -> 44431
B49: 王华锋 | C49: 1 | D49: {=_xlfn.XLOOKUP(B49,会员总表!D:D,会员总表!B:B)} -> #N/A
B50: 宜博 | C50: 4 | D50: {=_xlfn.XLOOKUP(B50,会员总表!D:D,会员总表!B:B)} -> 44371
B51: 卢忠阳 | C51: 1 | D51: {=_xlfn.XLOOKUP(B51,会员总表!D:D,会员总表!B:B)} -> #N/A
B52: 谭欣 | C52: 2 | D52: {=_xlfn.XLOOKUP(B52,会员总表!D:D,会员总表!B:B)} -> 44627
B53: 李钢 | C53: 1 | D53: {=_xlfn.XLOOKUP(B53,会员总表!D:D,会员总表!B:B)} -> #N/A
B54: 陈冲 | C54: 13 | D54: {=_xlfn.XLOOKUP(B54,会员总表!D:D,会员总表!B:B)} -> 43385
B55: 何耀文 | C55: 1 | D55: {=_xlfn.XLOOKUP(B55,会员总表!D:D,会员总表!B:B)} -> 44547
B56: 宋光进 | C56: 1 | D56: {=_xlfn.XLOOKUP(B56,会员总表!D:D,会员总表!B:B)} -> 43619
B57: 苏煦峰 | C57: 1 | D57: {=_xlfn.XLOOKUP(B57,会员总表!D:D,会员总表!B:B)} -> #N/A
B58: 陈世玉 | C58: 1 | D58: {=_xlfn.XLOOKUP(B58,会员总表!D:D,会员总表!B:B)} -> #N/A
B59: 张剑光 | C59: 1 | D59: {=_xlfn.XLOOKUP(B59,会员总表!D:D,会员总表!B:B)} -> 44641
... B61: 苗辉 | C61: 1 | D61: {=_xlfn.XLOOKUP(B61,会员总表!D:D,会员总表!B:B)} -> 43270
B62: 冼牛 | C62: 3 | D62: {=_xlfn.XLOOKUP(B62,会员总表!D:D,会员总表!B:B)} -> 46030 | E62: 2
B63: 华琨 | C63: 2 | D63: {=_xlfn.XLOOKUP(B63,会员总表!D:D,会员总表!B:B)} -> 43931
B64: 汤丁青 | C64: 2 | D64: {=_xlfn.XLOOKUP(B64,会员总表!D:D,会员总表!B:B)} -> 44497
B65: 白新奋 | C65: 2 | D65: {=_xlfn.XLOOKUP(B65,会员总表!D:D,会员总表!B:B)} -> 43426
B66: 刘连响 | C66: 1 | D66: {=_xlfn.XLOOKUP(B66,会员总表!D:D,会员总表!B:B)} -> #N/A
B67: 郭炜 | C67: 5 | D67: {=_xlfn.XLOOKUP(B67,会员总表!D:D,会员总表!B:B)} -> 42807
B68: 郑少麟 | C68: 2 | D68: {=_xlfn.XLOOKUP(B68,会员总表!D:D,会员总表!B:B)} -> 43801
B69: 陈驰远 | C69: 1 | D69: {=_xlfn.XLOOKUP(B69,会员总表!D:D,会员总表!B:B)} -> 45988
B70: 黄剑新 | C70: 2 | D70: 已过期
B71: 潘鑫磊 | C71: 1 | D71: {=_xlfn.XLOOKUP(B71,会员总表!D:D,会员总表!B:B)} -> #N/A
B72: 曹翔 | C72: 1 | D72: {=_xlfn.XLOOKUP(B72,会员总表!D:D,会员总表!B:B)} -> 44316
B73: 黄曙光 | C73: 1 | D73: {=_xlfn.XLOOKUP(B73,会员总表!D:D,会员总表!B:B)} -> 43636
B74: 王拓 | C74: 2 | D74: {=_xlfn.XLOOKUP(B74,会员总表!D:D,会员总表!B:B)} -> 42506
B75: 韩轶东 | C75: 2 | D75: {=_xlfn.XLOOKUP(B75,会员总表!D:D,会员总表!B:B)} -> 45078
B76: 陈于思 | C76: 1 | D76: {=_xlfn.XLOOKUP(B76,会员总表!D:D,会员总表!B:B)} -> 44714
B77: 熊昌伟 | C77: 1 | D77: {=_xlfn.XLOOKUP(B77,会员总表!D:D,会员总表!B:B)} -> 42202
B78: 李亚飞 | C78: 1 | D78: 已过期
B79: 龙凡 | C79: 1 | D79: {=_xlfn.XLOOKUP(B79,会员总表!D:D,会员总表!B:B)} -> 45016
B80: 邓先敏 | C80: 1 | D80: {=_xlfn.XLOOKUP(B80,会员总表!D:D,会员总表!B:B)} -> #N/A
B81: 史海峰 | C81: 1 | D81: {=_xlfn.XLOOKUP(B81,会员总表!D:D,会员总表!B:B)} -> 42171
B82: 郑浩杰 | C82: 3 | D82: {=_xlfn.XLOOKUP(B82,会员总表!D:D,会员总表!B:B)} -> 44285
B83: 岑裕 | C83: 1 | D83: 已过期 | E83: 3
B84: 邱良军 | C84: 5 | D84: {=_xlfn.XLOOKUP(B84,会员总表!D:D,会员总表!B:B)} -> 43434
B85: 陈浩 | C85: 1 | D85: {=_xlfn.XLOOKUP(B85,会员总表!D:D,会员总表!B:B)} -> 45030
B86: 路文杰 | C86: 5 | D86: {=_xlfn.XLOOKUP(B86,会员总表!D:D,会员总表!B:B)} -> 42451
B87: 潘飞 | C87: 1 | D87: {=_xlfn.XLOOKUP(B87,会员总表!D:D,会员总表!B:B)} -> 45170
B88: 杨攀，陈肃 | C88: 1 | D88: {=_xlfn.XLOOKUP(B88,会员总表!D:D,会员总表!B:B)} -> #N/A
B89: 檀德宾 | C89: 3 | D89: {=_xlfn.XLOOKUP(B89,会员总表!D:D,会员总表!B:B)} -> 44979
B90: 房晓乐 | C90: 5 | D90: {=_xlfn.XLOOKUP(B90,会员总表!D:D,会员总表!B:B)} -> 43572
B91: 陈靖华 | C91: 2 | D91: {=_xlfn.XLOOKUP(B91,会员总表!D:D,会员总表!B:B)} -> 42219 | E91: 4
B92: 李程 | C92: 1 | D92: {=_xlfn.XLOOKUP(B92,会员总表!D:D,会员总表!B:B)} -> #N/A
B93: 杨建戟 | C93: 1 | D93: 已过期
B94: 陈肃 | C94: 7 | D94: {=_xlfn.XLOOKUP(B94,会员总表!D:D,会员总表!B:B)} -> 43580
B95: 王电轻 | C95: 3 | D95: {=_xlfn.XLOOKUP(B95,会员总表!D:D,会员总表!B:B)} -> 44287
B96: 伍涛 | C96: 2 | D96: {=_xlfn.XLOOKUP(B96,会员总表!D:D,会员总表!B:B)} -> 42631
B97: 曾杰 | C97: 1 | D97: {=_xlfn.XLOOKUP(B97,会员总表!D:D,会员总表!B:B)} -> 43780
B98: 顾湘余 | C98: 1 | D98: {=_xlfn.XLOOKUP(B98,会员总表!D:D,会员总表!B:B)} -> 45216
B99: 金鑫 | C99: 1 | D99: {=_xlfn.XLOOKUP(B99,会员总表!D:D,会员总表!B:B)} -> 43713
B100: 杨瑞 | C100: 6 | D100: {=_xlfn.XLOOKUP(B100,会员总表!D:D,会员总表!B:B)} -> 43470 | E100: 5
B101: 马力遥 | C101: 7 | D101: {=_xlfn.XLOOKUP(B101,会员总表!D:D,会员总表!B:B)} -> 43128
B102: 张俊伟 | C102: 4 | D102: 已过期
B103: 薛理玮 | C103: 1 | D103: {=_xlfn.XLOOKUP(B103,会员总表!D:D,会员总表!B:B)} -> 44421
...

Sheet 各分会人数-1024
A1: 加入时间 - 年份 | B1: (全部)
A2: 加入时间 - 季度 | B2: (全部)
A3: 加入时间 - 月份 | B3: (全部)
A5: 地区 | B5: 计数:姓名
A6: 深圳 | B6: 143
A7: 杭州 | B7: 83
A8: 北京 | B8: 294
A9: 上海 | B9: 261
A10: 广州 | B10: 107
A11: 新加坡 | B11: 24
A12: 苏州 | B12: 22
A13: 南京 | B13: 44
A14: 成都 | B14: 47
A15: 硅谷 | B15: 46
A16: 武汉 | B16: 18
A17: 厦门 | B17: 25
... A19: 总计 | B19: 1131

Sheet 各分会人数-9月
A1: 加入时间 - 年份 | B1: (全部)
A2: 加入时间 - 季度 | B2: (全部)
A3: 加入时间 - 月份 | B3: (全部)
A5: 地区 | B5: 计数:姓名
A6: 深圳 | B6: 143
A7: 杭州 | B7: 83
A8: 北京 | B8: 294
A9: 上海 | B9: 261
A10: 广州 | B10: 107
A11: 新加坡 | B11: 24
A12: 苏州 | B12: 22
A13: 南京 | B13: 44
A14: 成都 | B14: 47
A15: 硅谷 | B15: 46
A16: 武汉 | B16: 18
A17: 厦门 | B17: 25
... A19: 总计 | B19: 1131

Sheet Sheet20
A1: member (4)
A2: 姓名 | B2: 手机 | C2: 公司 | D2: 职位 | E2: 邮箱 | F2: 分会 | G2: 会员类型 | H2: 加入时间 | I2: 到期时间
A3: 蔡铁 | B3: 广东九四智能科技有限公司 | C3: 13570953397 | D3: 高级技术总监 | E3: fragcai@qq.com | F3: 广州 | G3: 高级会员 | H3: 45842 | I3: 46203
A4: 张昕伟 | B4: VIPKid | C4: 15210231787 | D4: 技术总监 | E4: zhangxinwei@vipkid.com.cn | F4: 北京 | G4: 高级会员 | H4: 45846 | I4: 46203 | J4: 1
A5: 朱晓战 | B5: 全房通 | C5: 15652486096 | D5: 联合创始人 | E5: zhuxiaozhan@huizhaofang.com | F5: 北京 | G5: 高级会员 | H5: 45841 | I5: 46203 | J5: 2
A6: 朱威 | B6: 中邮消费金融有限公司 | C6: 18620668926 | D6: 其他 | E6: zhuwei@youcash.com | F6: 广州 | G6: 高级会员 | H6: 45842 | I6: 46203
A7: 邓思宇 | B7: 美高域集团HK1985 | C7: 18800356315 | D7: 技术VP/副总裁 | E7: siyudeng@microware.com.hk | F7: 深圳 | G7: 高级会员 | H7: 45826 | I7: 46203
A8: 吴永欢 | B8: 阿里云计算有限公司 | C8: 13632266659 | D8: 其他 | E8: 13632266659@qq.com | F8: 广州 | G8: 高级会员 | H8: 45846 | I8: 46203
A9: 孙翔舟 | B9: One Silver Sea | C9: 13501652230 | D9: CEO | E9: jonassun@mit.edu | F9: 深圳 | G9: 高级会员 | H9: 45833 | I9: 46203
A10: 李京林 | B10: DeerAPI | C10: 18601790523 | D10: CEO | E10: sonicli1983@163.com | F10: 上海 | G10: 高级会员 | H10: 45833 | I10: 46203
A11: 朱浩齐 | B11: 杭州网易智企科技有限公司 | C11: 13588735983 | D11: 总经理 | E11: zhuhaoqi@163.com | F11: 杭州 | G11: 高级会员 | H11: 45846 | I11: 46203
A12: 陈石 | B12: 峰瑞资本 | C12: 13801395480 | D12: 其他 | E12: bjchens@163.com | F12: 北京 | G12: 高级会员 | H12: 45826 | I12: 46203
A13: 吕琳 | B13: 英伟达 | C13: 13817054786 | D13: 其他 | E13: flowsands@qq.com | F13: 上海 | G13: 高级会员 | H13: 45832 | I13: 46203
A14: 刘泽辰 | B14: 医纪元 | C14: 13261754302 | D14: 联合创始人 | E14: liuzechen001@gmail.com | F14: 北京 | G14: 高级会员 | H14: 45840 | I14: 46203
A15: 陈志鉴 | B15: 和讯信息科技有限公司 | C15: 18518317941 | D15: 高级技术总监 | E15: chenzhijian@staff.hexun.com | F15: 北京 | G15: 高级会员 | H15: 45828 | I15: 46203
A16: 郑治东 | B16: 和讯网 | C16: 13718810082 | D16: 运维总监 | E16: zzd.ok@163.com | F16: 北京 | G16: 高级会员 | H16: 45828 | I16: 46203
A17: 周栋 | B17: 和讯信息科技有限公司 | C17: 18500388222 | D17: 技术总监 | E17: zhdong@staff.hexun.com | F17: 北京 | G17: 高级会员 | H17: 45828 | I17: 46203
... A208: 赵成业 | B208: 北京极智嘉机器人股份有限公司 | C208: 18616955651 | D208: 技术经理/主管 | E208: chengyezhao@gmail.com | F208: 上海 | G208: 高级会员 | H208: 45447 | I208: 46203
A209: 王志军 | B209: 中国联通 | C209: 18601105055 | D209: 技术VP/副总裁 | E209: wangzhijun1@chinaunicom.cn | G209: 高级会员 | H209: 45441 | I209: 45838
A210: 李红林 | B210: 东风汽车 | C210: 18602757512 | D210: 技术经理/主管 | E210: lihongl@dfmc.com.cn | G210: 高级会员 | H210: 45441 | I210: 45838
A211: 宋森 | B211: 清华大学 | C211: 18633333333 | D211: 其他 | E211: songsen@tsinghua.edu.cn | G211: 高级会员 | H211: 45441 | I211: 45838
A212: 袁粒 | B212: 北京大学深圳研究生院 | C212: 15656569683 | D212: 其他 | E212: yuanli-ece@pku.edu.cn | G212: 高级会员 | H212: 45441 | I212: 45838
A213: 吴甘沙 | B213: 驭势科技 | C213: 18610130118 | D213: CEO | E213: gansha.wu@uisee.com | G213: 高级会员 | H213: 45441 | I213: 45838
A214: 朱如江 | B214: 南通巨联数字科技有限公司 | C214: 13921628181 | D214: 技术VP/副总裁 | E214: zhurj@lianfa.cn | G214: 高级会员 | H214: 45441 | I214: 45838
A215: 刘昊 | B215: 北京泰迪未来科技 | C215: 18811180669 | D215: 技术VP/副总裁 | E215: guzi5618@qq.com | F215: 北京 | G215: 高级会员 | H215: 45457 | I215: 46203
A216: 鲍炎焱 | B216: 江苏版石软件股份有限公司 | C216: 18610527133 | D216: CTO | E216: 906425059@qq.com | F216: 北京 | G216: 高级会员 | H216: 45442 | I216: 46203
A217: 宋壬初 | B217: Epsilla | C217: 6073798668 | D217: CEO | E217: richard@epsilla.com | F217: 硅谷 | G217: 高级会员 | H217: 45447 | I217: 45812
A218: 张骏峰 | B218: 保时捷(上海)数字科技有限公司 | C218: 18601160302 | D218: CTO | E218: zhangjf@hotmail.com | F218: 北京 | G218: 高级会员 | H218: 45447 | I218: 45838
A219: 高驰涛 | B219: 云智慧（北京）科技有限公司 | C219: 13426211917 | D219: 其他 | E219: neeke.gao@hotmail.com | F219: 北京 | G219: 高级会员 | H219: 45454 | I219: 46203
A220: 高阳Sunny | B220: SegmentFault 思否 | C220: 18668162049 | D220: CEO | E220: sunny@sifou.com | F220: 杭州 | G220: 高级会员 | H220: 45446 | I220: 45838
A221: 张鹏 | B221: 知乎 | C221: 13752028021 | D221: 其他 | E221: 825817512@qq.com | F221: 北京 | G221: 高级会员 | H221: 45440 | I221: 45838
A222: 徐素文 | B222: 天度（厦门）科技股份有限公司 | C222: 18030158268 | D222: 联合创始人 | E222: wayne@tduvr.com | F222: 厦门 | G222: 高级会员 | H222: 45446 | I222: 46203
A223: 胡兵 | B223: 腾讯科技（深圳）有限公司 | C223: 18806653007 | D223: 其他 | E223: 421654305@qq.com | F223: 深圳 | G223: 高级会员 | H223: 45510 | I223: 46203
A224: 田冰 | B224: 南京百丝特网络科技有限公司 | C224: 18021519611 | D224: 其他 | E224: 501266561@qq.com | F224: 南京 | G224: 高级会员 | H224: 45450 | I224: 45838
A225: 杨金全 | B225: 北京基调网络股份有限公司 | C225: 15010968269 | D225: 技术VP/副总裁 | E225: yangjq@tingyun.com | F225: 北京 | G225: 高级会员 | H225: 45446 | I225: 46203
A226: 周卫林 | B226: 浙江大应科技有限公司 | C226: 15988160608 | D226: CEO | E226: jingzhi.zhou@aloudata.com | F226: 杭州 | G226: 高级会员 | H226: 45443 | I226: 45838
... A228: 李斌 | B228: 沐瞳科技 | C228: 13691562071 | D228: 技术VP/副总裁 | E228: 119579481@qq.com | F228: 上海 | G228: 高级会员 | H228: 45423 | I228: 45838
A229: 王曦 | B229: 杉数科技 | C229: 18610196656 | D229: 联合创始人 | E229: jack.xwang@gmail.com | G229: 高级会员 | H229: 45413 | I229: 45838
A230: 刘荣逵 | B230: 天弘基金 | C230: 18600397681 | D230: CIO | E230: rongkui.liu@gmail.com | G230: 高级会员 | H230: 45441 | I230: 45838
A231: 王浩宇 | B231: 宁波新物云科技有限公司 | C231: 13851821123 | D231: CEO | E231: damai@xinwuyun.com | G231: 高级会员 | H231: 45441 | I231: 45838
A232: 张旭 | B232: 用友网络科技股份有限公司 | C232: 13621078508 | D232: 其他 | E232: 249199027@qq.com | G232: 高级会员 | H232: 45441 | I232: 45838
A233: 蔡阳 | B233: 香港医院管理局 | C233: 17611090069 | D233: CIO | E233: kevincai@ha.org.hk | G233: 高级会员 | H233: 25569 | I233: 25569
A234: 万维钢 | B234: 得到 | C234: 7203527429 | D234: 其他 | E234: wanweigang@gmail.com | G234: 高级会员 | H234: 45441 | I234: 45838
A235: 邹德宏 | B235: 方元互联（北京）科技有限公司 | C235: 15891396443 | D235: CTO | E235: 136057505@qq.com | F235: 北京 | G235: 高级会员 | H235: 45432 | I235: 45838
A236: 冉敏 | B236: 树根互联股份有限公司 | C236: 13629738347 | D236: 其他 | E236: 810155977@qq.com | F236: 广州 | G236: 高级会员 | H236: 45758 | I236: 46203
A237: 王摩西 | B237: 优刻得（上海）数据科技有限公司 | C237: 18502115682 | D237: 技术总监 | E237: 401267756@qq.com | F237: 上海 | G237: 高级会员 | H237: 45439 | I237: 46203
A238: 王学武 | B238: 广州引力波信息科技有限公司 | C238: 13415112643 | D238: 研发总监 | E238: kite-x5@qq.com | F238: 广州 | G238: 高级会员 | H238: 45422 | I238: 45838
A239: 陈奕龙 | B239: 生数科技有限公司 | C239: 18502710958 | D239: 技术VP/副总裁 | E239: yilong.olaf@gmail.com | F239: 北京 | G239: 高级会员 | H239: 45421 | I239: 45838
A240: 房立明 | B240: 华为云计算技术有限公司 | C240: 18514431988 | D240: 其他 | E240: fangliming1@huawei.com | F240: 上海 | G240: 高级会员 | H240: 45532 | I240: 45838
A241: 黄永凯 | B241: 杭州点辰网络科技股份有限公司 | C241: 15958019620 | D241: 总经理 | E241: 76539062@qq.com | F241: 杭州 | G241: 高级会员 | H241: 45403 | I241: 46203
A242: 王克权 | B242: 数数信息科技 | C242: 18612258214 | D242: 总经理 | E242: bugking.wang@gmail.com | F242: 北京 | G242: 高级会员 | H242: 45464 | I242: 46203
A243: 张杰 | B243: 美团 | C243: 18019378559 | D243: 技术总监 | E243: zj7816@qq.com | F243: 上海 | G243: 高级会员 | H243: 45406 | I243: 46203
A244: 李男 | B244: 面试小助手人工智能科技有限公司 | C244: 13811387875 | D244: 联合创始人 | E244: linan@msxzs.wecom.work | F244: 杭州 | G244: 高级会员 | H244: 45747 | I244: 46203
A245: 唐军 | B245: 江苏开博科技有限公司 | C245: 18021501287 | D245: CTO | E245: 630894527@qq.com | F245: 南京 | G245: 高级会员 | H245: 45429 | I245: 46203
A246: 童熙 | B246: 广州宝洁科技创新有限公司 | C246: 13922208484 | D246: CTO | E246: tong.x@pg.com | F246: 广州 | G246: 高级会员 | H246: 45420 | I246: 46203
... A303: 彭诗懿 | B303: DeepCruit | C303: 4083480311 | D303: 联合创始人 | E303: c2shiyi@gmail.com | F303: 硅谷 | G303: 高级会员 | H303: 45313 | I303: 45657
A304: 田广礼 | B304: 天工开物开源基金会 | C304: 13908630408 | D304: 其他 | E304: 18908310128@189.cn | G304: 高级会员 | H304: 45261 | I304: 45838
A305: 苏格林 | B305: 蜻蜓FM | C305: 13699271341 | D305: 技术VP/副总裁 | E305: skeletoncs@gmail.com | F305: 北京 | G305: 高级会员 | H305: 45279 | I305: 45838
A306: 尹博学 | B306: 北京奥星贝斯科技有限公司 | C306: 13581863112 | D306: 技术VP/副总裁 | E306: guset007@163.com | F306: 北京 | G306: 高级会员 | H306: 45321 | I306: 45688
A307: 刘德鹏 | B307: 北京奥星贝斯科技有限公司 （蚂蚁集团子公司） | C307: 13350072829 | D307: 高级技术总监 | E307: 8380842@qq.com | F307: 成都 | G307: 高级会员 | H307: 45321 | I307: 45688
A308: 张磊 | B308: 北京智谱华章科技有限公司 | C308: 18611133358 | D308: 技术总监 | E308: bobzh@163.com | F308: 深圳 | G308: 高级会员 | H308: 45341 | I308: 46203
A309: 刘远 | B309: 阿里巴巴 | C309: 13928999525 | D309: 其他 | E309: 64604794@qq.com | F309: 深圳 | G309: 高级会员 | H309: 45485 | I309: 46203
A310: 刘宗瑒 | B310: 深圳市沐腾科技有限公司 | C310: 18566661337 | D310: CTO | E310: lzy@motern.com | F310: 深圳 | G310: 高级会员 | H310: 45399 | I310: 46203
A311: 曹伟 | B311: 杭州云猿生数据有限公司 | C311: 15869017778 | D311: CEO | E311: weston@apecloud.com | F311: 杭州 | G311: 高级会员 | H311: 45289 | I311: 45838
A312: 金新明 | B312: 平安科技（深圳）有限公司 | C312: 18924239964 | D312: 首席架构师 | E312: xmjin@hotmail.com | G312: 高级会员 | H312: 45261 | I312: 45838
A313: 王延松 | B313: 奇瑞徽银汽车金融股份有限公司 | C313: 19956595799 | D313: 其他 | E313: 27209176@qq.com | G313: 高级会员 | H313: 45261 | I313: 45838
A314: 杜旌 | B314: 武汉大学经济与管理学院 | C314: 18522222222 | D314: 其他 | E314: jdu@whu.edu.cn | G314: 高级会员 | H314: 45261 | I314: 45838
A315: 俞枫 | B315: 国泰君安证券 | C315: 13901604948 | D315: CIO | E315: yufeng@gtjas.com | G315: 高级会员 | H315: 45261 | I315: 45838
A316: 丛松 | B316: 新浪移动 | C316: 18911206123 | D316: 总经理 | E316: congsong@staff.sina.com | G316: 高级会员 | H316: 45261 | I316: 45838
A317: 杨润德 | B317: Dream Voyage | C317: 6073799526 | D317: 联合创始人 | E317: Ry82@cornell.edu | F317: 硅谷 | G317: 高级会员 | H317: 45282 | I317: 45657
A318: 王佳 | B318: 杭州杰峰科技有限公司 | C318: 18158119115 | D318: 技术VP/副总裁 | E318: jiaxin987@126.com | F318: 杭州 | G318: 高级会员 | H318: 45279 | I318: 45838
A319: 刘恒一 | B319: 商汤 | C319: 18601090970 | D319: 高级技术总监 | E319: liuhengyi@sensetime.com | F319: 北京 | G319: 高级会员 | H319: 45559 | I319: 46203
A320: 鲁颖 | B320: Zoom | C320: 6502509914 | D320: 研发总监 | E320: yinglu1985.shanghai@gmail.com | F320: 硅谷 | G320: 高级会员 | H320: 45279 | I320: 45657
A321: 金明剑 | B321: 北京致大尽微科技有限公司 | C321: 18611693367 | D321: CEO | E321: jin.phd@gmail.com | F321: 北京 | G321: 高级会员 | H321: 45267 | I321: 45838
A322: 陈霈霖 | B322: 深圳维格云科技有限公司 | C322: 18688180270 | D322: CEO | E322: kelly@aitable.ai | F322: 深圳 | G322: 标准会员 | H322: 45314 | I322: 46053
A323: 潘乱 | B323: 乱翻书 | C323: 15300333060 | D323: CEO | E323: luanbooks@qq.com | G323: 高级会员 | H323: 45260 | I323: 45838
A324: 快刀青衣 | B324: 得到 | C324: 18611822278 | D324: 联合创始人 | E324: kuaidaoqingyi@luojilab.com | G324: 高级会员 | H324: 45260 | I324: 45838
A325: Tina Jiang 姜瑞 | B325: TalentX Consulting | C325: 18601287954 | D325: CEO | E325: tinajiang@talentxchina.com | G325: 高级会员 | H325: 45260 | I325: 45838
A326: 安秋明 | B326: 北京赋能加科技有限公司 | C326: 13661156604 | D326: CEO | E326: 9404755@qq.com | G326: 高级会员 | H326: 45260 | I326: 45838
A327: 马占凯 | B327: 美团 | C327: 18611423700 | D327: 其他 | E327: 42112503@qq.com | G327: 高级会员 | H327: 45260 | I327: 45838
A328: 刘江 | B328: 智谱AI | C328: 13910386820 | D328: CEO | E328: liuj.turing@gmail.com | G328: 高级会员 | H328: 45260 | I328: 45838
A329: 刘富军 | B329: 元位科技（上海）有限公司 | C329: 18121471860 | D329: 其他 | E329: allen_lfj@163.com | F329: 上海 | G329: 高级会员 | H329: 45271 | I329: 46203
A330: 吕睿韬 | B330: 喜马拉雅 | C330: 18992846772 | D330: 研发总监 | E330: lvruitao@yeah.net | F330: 上海 | G330: 高级会员 | H330: 45264 | I330: 45838
A331: 王筱磊 | B331: Cider | C331: 18518720372 | D331: 其他 | E331: wangxiaoleiim@163.com | F331: 北京 | G331: 高级会员 | H331: 45267 | I331: 45838
A332: 周会朗 | B332: 华为云计算技术有限公司 | C332: 18115885523 | D332: 其他 | E332: huilang1992@126.com | F332: 厦门 | G332: 高级会员 | H332: 45281 | I332: 46203
A333: 张泉 | B333: 拓维海云天 | C333: 18682126499 | D333: 技术VP/副总裁 | E333: zhangquan.hust@icloud.com | F333: 广州 | G333: 高级会员 | H333: 45260 | I333: 45473
A334: 苏丹 | B334: 武汉叁一互娱科技发展有限公司 | C334: 18903616985 | D334: CEO | E334: sudan@31gamestudio.com | F334: 武汉 | G334: 高级会员 | H334: 45272 | I334: 45838
A335: 孙双琛 | B335: 阿里云计算有限公司 | C335: 18098900375 | D335: 首席架构师 | E335: 287831540@qq.com | F335: 深圳 | G335: 高级会员 | H335: 45299 | I335: 46022
A336: 吴楠 | B336: 北京衔远科技有限公司 | C336: 15618818067 | D336: 其他 | E336: wunan7@hotmail.com | F336: 北京 | G336: 高级会员 | H336: 45285 | I336: 45838
A337: 何涛 | B337: 网联清算有限公司 | C337: 15210835658 | D337: 技术经理/主管 | E337: 76849109@qq.com | F337: 北京 | G337: 高级会员 | H337: 45273 | I337: 45473
A338: 付聪 | B338: 腾讯 | C338: 15910600959 | D338: 其他 | E338: fc4976@qq.com | F338: 北京 | G338: 高级会员 | H338: 45266 | I338: 46203
A339: 王凯 | B339: UCloud | C339: 18917852576 | D339: CTO | E339: hwwkkk@aliyun.com | F339: 上海 | G339: 高级会员 | H339: 45286 | I339: 46203
A340: 王超 | B340: 字节跳动 | C340: 17600818817 | D340: 其他 | E340: charleswangme@gmail.com | F340: 北京 | G340: 高级会员 | H340: 45260 | I340: 45473
... A656: 孟珊 | B656: 好未来 | C656: 13520154077 | D656: 其他 | E656: 437366919@qq.com | F656: 北京 | G656: 高级会员 | H656: 44784 | I656: 46203
A657: 廖珈 | B657: 1 | C657: 18610330579 | D657: CTO | E657: 1742193196@qq.com | F657: 杭州 | G657: 高级会员 | H657: 44748 | I657: 44742
A658: 周泉 | B658: 浙江大应科技 | C658: 18905818760 | D658: CTO | E658: ldzhouquan@163.com | F658: 杭州 | G658: 高级会员 | H658: 44770 | I658: 45473
A659: 何坤 | B659: 1 | C659: 19131128311 | D659: CTO | E659: 1822902750@qq.com | F659: 杭州 | G659: 高级会员 | H659: 44748 | I659: 45107
A660: 肖贝贝 | B660: Tapdata | C660: 18311098769 | D660: CTO | E660: berry@tapdata.io | F660: 深圳 | G660: 高级会员 | H660: 44781 | I660: 45473
A661: 徐丹青 | B661: Bytebase | C661: 15988127923 | D661: CTO | E661: d@bytebase.com | F661: 杭州 | G661: 高级会员 | H661: 44757 | I661: 45107
A662: 柳忠阳 | B662: 金蝶软件（中国）有限公司 | C662: 15323750150 | D662: 其他 | E662: edwardlzylqf@outlook.com | F662: 深圳 | G662: 高级会员 | H662: 44739 | I662: 45838
...

Sheet 各分会人数
A1: 加入时间 - 年份 | B1: (全部)
A2: 加入时间 - 季度 | B2: (全部)
A3: 加入时间 - 月份 | B3: (全部)
A5: 地区 | B5: 计数:姓名
A6: 深圳 | B6: 143
A7: 杭州 | B7: 83
A8: 北京 | B8: 294
A9: 上海 | B9: 261
A10: 广州 | B10: 107
A11: 新加坡 | B11: 24
A12: 苏州 | B12: 22
A13: 南京 | B13: 44
A14: 成都 | B14: 47
A15: 硅谷 | B15: 46
A16: 武汉 | B16: 18
A17: 厦门 | B17: 25
... A19: 总计 | B19: 1131

Sheet 数据透视表
A1: 地区 | B1: 计数:序号
A2: 上海 | B2: 246
A3: 总计 | B3: 246 | O3: 深圳3年以上 | P3: =I8 -> 0 | R3: 选这个+8个会长（不含新加坡、台北）
O4: 广州5年以上 | P4: =G9 -> 0
O5: 厦门5年以上 | P5: =G10 -> 0
O6: 合计 | P6: =SUM(P3:P5) -> 0 | Q6: =P6*400 -> 0
S7: =103+8 -> 111
A8: 深圳年份合计 | B8: =SUM(B5) -> 0 | C8: =SUM($B$5:C5) -> 0 | D8: =SUM($B$5:D5) -> 0 | E8: =SUM($B$5:E5) -> 0 | F8: =SUM($B$5:F5) -> 0 | G8: =SUM($B$5:G5) -> 0 | H8: =SUM($B$5:H5) -> 0 | I8: =SUM($B$5:I5) -> 0 | J8: =SUM($B$5:J5) -> 0 | ... L8: =SUM($B$5:L5) -> 0 | O8: 深圳2年以上 | P8: =J8 -> 0
A9: 广州年份合计 | B9: =SUM(B6) -> 0 | C9: =SUM($B$6:C6) -> 0 | D9: =SUM($B$6:D6) -> 0 | E9: =SUM($B$6:E6) -> 0 | F9: =SUM($B$6:F6) -> 0 | G9: =SUM($B$6:G6) -> 0 | H9: =SUM($B$6:H6) -> 0 | I9: =SUM($B$6:I6) -> 0 | J9: =SUM($B$6:J6) -> 0 | ... L9: =SUM($B$6:L6) -> 0 | O9: 广州5年以上 | P9: 32
A10: 厦门年份合计 | B10: =SUM(B7) -> 0 | C10: =SUM($B$7:C7) -> 0 | D10: =SUM($B$7:D7) -> 0 | E10: =SUM($B$7:E7) -> 0 | F10: =SUM($B$7:F7) -> 0 | G10: =SUM($B$7:G7) -> 0 | H10: =SUM($B$7:H7) -> 0 | I10: =SUM($B$7:I7) -> 0 | J10: =SUM($B$7:J7) -> 0 | ... L10: =SUM($B$7:L7) -> 0 | O10: 厦门5年以上 | P10: 8
O11: 合计 | P11: =SUM(P8:P10) -> 40 | Q11: =P11*400 -> 16000
O13: 深圳1年以上 | P13: =K8 -> 0
O14: 广州8年以上 | P14: =D9 -> 0
O15: 厦门8年以上 | P15: =C10 -> 0
O16: 合计 | P16: =SUM(P13:P15) -> 0 | Q16: =P16*400 -> 0
P19: =119*400 -> 47600
P20: =110*400 -> 44000
O21: =104+8 -> 112 | P21: =O21*400 -> 44800
B27: 姓名 | C27: 所在分会
B28: 洪小军 | C28: 深圳 | D28: =VLOOKUP(B28,会员总表!D:M,6,0) -> 暂无 | E28: =VLOOKUP(B28,会员总表!D:M,7,0) -> １
B29: 肖伦文 | C29: 硅谷分会 | D29: =VLOOKUP(B29,会员总表!D:M,6,0) -> 暂无 | E29: =VLOOKUP(B29,会员总表!D:M,7,0) -> 1
B30: 鲍博 | C30: 北京 | D30: =VLOOKUP(B30,会员总表!D:M,6,0) -> 会员推荐 | E30: =VLOOKUP(B30,会员总表!D:M,7,0) -> 0
B31: 夏澎 | C31: 硅谷 | D31: =VLOOKUP(B31,会员总表!D:M,6,0) -> 暂无 | E31: =VLOOKUP(B31,会员总表!D:M,7,0) -> ０
B32: 林群书 | C32: 硅谷 | D32: =VLOOKUP(B32,会员总表!D:M,6,0) -> 会员推荐 | E32: =VLOOKUP(B32,会员总表!D:M,7,0) -> 1
B33: 林旅强 | C33: 北京 | D33: =VLOOKUP(B33,会员总表!D:M,6,0) -> 会员推荐 | E33: =VLOOKUP(B33,会员总表!D:M,7,0) -> 1
B34: 姜景康 | C34: TGO杭州分会 | D34: =VLOOKUP(B34,会员总表!D:M,6,0) -> 会员推荐 | E34: =VLOOKUP(B34,会员总表!D:M,7,0) -> 0
B35: 凌馨霞 | D35: Cloudpilot AI | E35: 海外增长负责人
B36: 许小川 | C36: 深圳 | D36: =VLOOKUP(B36,会员总表!D:M,6,0) -> 会员推荐 | E36: =VLOOKUP(B36,会员总表!D:M,7,0) -> 1
B37: 张小龙 | C37: 广州 | D37: =VLOOKUP(B37,会员总表!D:M,6,0) -> 暂无 | E37: =VLOOKUP(B37,会员总表!D:M,7,0) -> 1
B38: 冯颖 | C38: 深圳 | D38: =VLOOKUP(B38,会员总表!D:M,6,0) -> 会员推荐 | E38: =VLOOKUP(B38,会员总表!D:M,7,0) -> 1
B39: 刘建国 | C39: 广州 | D39: =VLOOKUP(B39,会员总表!D:M,6,0) -> 暂无 | E39: =VLOOKUP(B39,会员总表!D:M,7,0) -> 1
B40: 王战勇 | C40: 苏州分会 | D40: =VLOOKUP(B40,会员总表!D:M,6,0) -> 会员推荐 | E40: =VLOOKUP(B40,会员总表!D:M,7,0) -> 1
B41: 逄永涛 | C41: 北京26组 | D41: =VLOOKUP(B41,会员总表!D:M,6,0) -> 暂无 | E41: =VLOOKUP(B41,会员总表!D:M,7,0) -> 1
B42: 李亚飞 | C42: 深圳 | D42: =VLOOKUP(B42,会员总表!D:M,6,0) -> 暂无 | E42: =VLOOKUP(B42,会员总表!D:M,7,0) -> 1
B43: 郭欢乐 | C43: 深圳分会 | D43: =VLOOKUP(B43,会员总表!D:M,6,0) -> 暂无 | E43: =VLOOKUP(B43,会员总表!D:M,7,0) -> 1
B44: 杜达林 | C44: 深圳分会 | D44: =VLOOKUP(B44,会员总表!D:M,6,0) -> infoQ | E44: =VLOOKUP(B44,会员总表!D:M,7,0) -> 0
B45: 王仁明 | C45: 广州会分 | D45: =VLOOKUP(B45,会员总表!D:M,6,0) -> 暂无 | E45: =VLOOKUP(B45,会员总表!D:M,7,0) -> １
B46: 杨韶伟 | C46: 广州 | D46: =VLOOKUP(B46,会员总表!D:M,6,0) -> 暂无 | E46: =VLOOKUP(B46,会员总表!D:M,7,0) -> 1
B47: 秦圆圆 | C47: 广州 | D47: =VLOOKUP(B47,会员总表!D:M,6,0) -> 会员推荐 | E47: =VLOOKUP(B47,会员总表!D:M,7,0) -> 0
... B49: 崔俊涛 | C49: 上海 | D49: =VLOOKUP(B49,会员总表!D:M,6,0) -> 暂无 | E49: =VLOOKUP(B49,会员总表!D:M,7,0) -> 0

Sheet Sheet21
A1: 姓名 | B1: 公司 | C1: 职位
A2: 郭理靖 | B2: 奈雪的茶 | C2: CTO
A3: 林华根 | B3: 安徽超远信息技术有限公司 | C3: 副总工程师
A4: 魏吉贺 | B4: 深圳市残友软件股份有限公司 | C4: 技术总监
A5: 龚银 | B5: 安克创新 | C5: CIO
A6: 高楚涛 | B6: 深圳市嘉立创科技发展有限公司 | C6: CIO
A7: 何德照 | B7: AfterShip | C7: 技术VP
A8: 张呈刚 | B8: AWS | C8: 架构师经理
A9: 冯斌 | B9: ONES | C9: CTO
A10: 宋书俊 | B10: 广州爆米科技有限公司 | C10: CTO
A11: 李晨丰 | B11: 深圳米筐科技有限公司 | C11: COO
A12: 王志刚 | B12: 招商基金 | C12: 副总监
... A111: 谢锐 | B111: 维克时光 | C111: CTO

Sheet 深圳
A1: 地区 | B1: 深圳
A3: 序号 | B3: 加入时间 | C3: 会籍时间 | D3: 姓名 | E3: 公司 | H3: 点击地区 > 点击刷新数据源 > 点击（部分）输入对应的城市
A4: 1 | B4: 42129 | C4: 46203 | D4: 艾芙（徐雁斐） | E4: 暂无
D5: 艾芙（徐雁斐） 汇总
C6: 2026/6/30 汇总
B7: 2015/5/5 汇总
A8: 1 汇总
A9: 7 | B9: 42160 | C9: 46203 | D9: 黄良懿 | E9: 高仙机器人
D10: 黄良懿 汇总
C11: 2026/6/30 汇总
B12: 2015/6/5 汇总
A13: 7 汇总
A14: 21 | B14: 42318 | C14: 46203 | D14: 林华根 | E14: 安徽超远信息技术有限公司
D15: 林华根 汇总
C16: 2026/6/30 汇总
B17: 2015/11/10 汇总
A18: 21 汇总
A19: 22 | B19: 42334 | C19: 46203 | D19: 魏吉贺 | E19: 深圳市残友软件股份有限公司
D20: 魏吉贺 汇总
C21: 2026/6/30 汇总
B22: 2015/11/26 汇总
A23: 22 汇总
A24: 23 | B24: 42339 | C24: 46203 | D24: 龚银 | E24: 安克创新
D25: 龚银 汇总
C26: 2026/6/30 汇总
B27: 2015/12/1 汇总
A28: 23 汇总
A29: 29 | B29: 42473 | C29: 46203 | D29: 高楚涛 | E29: 深圳市嘉立创科技发展有限公司
D30: 高楚涛 汇总
C31: 2026/6/30 汇总
B32: 2016/4/13 汇总
A33: 29 汇总
A34: 52 | B34: 42698 | C34: 46203 | D34: 何德照 | E34: AfterShip
D35: 何德照 汇总
C36: 2026/6/30 汇总
B37: 2016/11/24 汇总
A38: 52 汇总
A39: 53 | B39: 42706 | C39: 46203 | D39: 张呈刚 | E39: AWS
D40: 张呈刚 汇总
C41: 2026/6/30 汇总
B42: 2016/12/2 汇总
A43: 53 汇总
A44: 55 | B44: 42730 | C44: 46203 | D44: 冯斌 | E44: ONES
D45: 冯斌 汇总
C46: 2026/6/30 汇总
B47: 2016/12/26 汇总
A48: 55 汇总
A49: 60 | B49: 42734 | C49: 46203 | D49: 宋书俊 | E49: 广州爆米科技有限公司
D50: 宋书俊 汇总
C51: 2026/6/30 汇总
B52: 2016/12/30 汇总
A53: 60 汇总
A54: 75 | B54: 42839 | C54: 46203 | D54: 李晨丰 | E54: 深圳米筐科技有限公司
D55: 李晨丰 汇总
C56: 2026/6/30 汇总
B57: 2017/4/14 汇总
A58: 75 汇总
A59: 96 | B59: 43051 | C59: 46203 | D59: 王志刚 | E59: 招商基金
D60: 王志刚 汇总
C61: 2026/6/30 汇总
B62: 2017/11/12 汇总
A63: 96 汇总
A64: 118 | B64: 43200 | C64: 46203 | D64: 杨文 | E64: AfterShip
D65: 杨文 汇总
C66: 2026/6/30 汇总
B67: 2018/4/10 汇总
A68: 118 汇总
A69: 121 | B69: 43218 | C69: 46203 | D69: 梁杞平 | E69: 深圳市互盟科技股份有限公司
D70: 梁杞平 汇总
C71: 2026/6/30 汇总
B72: 2018/4/28 汇总
A73: 121 汇总
A74: 165 | B74: 43402 | C74: 46203 | D74: 单致豪 | E74: 腾讯
D75: 单致豪 汇总
C76: 2026/6/30 汇总
B77: 2018/10/29 汇总
A78: 165 汇总
A79: 184 | B79: 43452 | C79: 46203 | D79: 洪小军 | E79: AfterShip
D80: 洪小军 汇总
C81: 2026/6/30 汇总
B82: 2018/12/18 汇总
A83: 184 汇总
A84: 197 | B84: 43485 | C84: 46203 | D84: 邓欣 | E84: 深圳永安在线科技有限公司
D85: 邓欣 汇总
C86: 2026/6/30 汇总
B87: 2019/1/20 汇总
A88: 197 汇总
A89: 201 | B89: 43496 | C89: 46203 | D89: 刘华 | E89: UCloud
D90: 刘华 汇总
C91: 2026/6/30 汇总
B92: 2019/1/31 汇总
A93: 201 汇总
A94: 223 | B94: 43619 | C94: 46203 | D94: 宋光进 | E94: 百度国际科技(深圳)有限公司
D95: 宋光进 汇总
C96: 2026/6/30 汇总
B97: 2019/6/3 汇总
A98: 223 汇总
A99: 224 | B99: 43636 | C99: 46203 | D99: 黄曙光 | E99: 华盛证券
D100: 黄曙光 汇总
C101: 2026/6/30 汇总
...

Sheet 上海
A1: 地区 | B1: 上海
A3: 序号 | B3: 加入时间 | C3: 姓名 | D3: 公司 | G3: 点击地区 > 点击刷新数据源 > 点击（部分）输入对应的城市
A4: 5 | B4: 42147 | C4: 唐小浙 | D4: 墨誉科技
C5: 唐小浙 汇总
B6: 2015/5/23 汇总
A7: 5 汇总
A8: 14 | B8: 42246 | C8: 黄彬彬 | D8: 多云转晴
C9: 黄彬彬 汇总
B10: 2015/8/30 汇总
A11: 14 汇总
A12: 15 | B12: 42248 | C12: 王立博 | D12: 未来保贝
C13: 王立博 汇总
B14: 2015/9/1 汇总
A15: 15 汇总
A16: 16 | B16: 42256 | C16: 胡震 | D16: 某公链基金会
C17: 胡震 汇总
B18: 2015/9/9 汇总
A19: 16 汇总
A20: 31 | B20: 42482 | C20: 万林涛 | D20: 上海蔚星数据
C21: 万林涛 汇总
B22: 2016/4/22 汇总
A23: 31 汇总
A24: 32 | B24: 42482 | C24: 徐翎 | D24: 上海数达物流科技有限公司
C25: 徐翎 汇总
B26: 2016/4/22 汇总
A27: 32 汇总
A28: 33 | B28: 42495 | C28: 肖颖 | D28: 上海澄廓信息科技有限公司
C29: 肖颖 汇总
B30: 2016/5/5 汇总
A31: 33 汇总
A32: 34 | B32: 42524 | C32: 张剑伟 | D32: 百安居
C33: 张剑伟 汇总
B34: 2016/6/3 汇总
A35: 34 汇总
A36: 38 | B36: 42556 | C36: 陈杰 | D36: 上海领健信息技术有限公司
C37: 陈杰 汇总
B38: 2016/7/5 汇总
A39: 38 汇总
A40: 40 | B40: 42559 | C40: 黄勇 | D40: 阅流
C41: 黄勇 汇总
B42: 2016/7/8 汇总
A43: 40 汇总
A44: 41 | B44: 42562 | C44: 奚铭皋 | D44: 比图科技
C45: 奚铭皋 汇总
B46: 2016/7/11 汇总
A47: 41 汇总
A48: 42 | B48: 42562 | C48: 陆云昆 | D48: 上海钢蜂信息科技有限公司
C49: 陆云昆 汇总
B50: 2016/7/11 汇总
A51: 42 汇总
A52: 47 | B52: 42631 | C52: 伍涛 | D52: Funplus
C53: 伍涛 汇总
B54: 2016/9/18 汇总
A55: 47 汇总
A56: 48 | B56: 42657 | C56: 张飞 | D56: vivo
C57: 张飞 汇总
B58: 2016/10/14 汇总
A59: 48 汇总
A60: 50 | B60: 42667 | C60: 洪倍 | D60: ValueZ智库
C61: 洪倍 汇总
B62: 2016/10/24 汇总
A63: 50 汇总
A64: 56 | B64: 42730 | C64: 朱攀 | D64: 阿旅科技
C65: 朱攀 汇总
B66: 2016/12/26 汇总
A67: 56 汇总
A68: 64 | B68: 42782 | C68: 陈晨 | D68: 上海慧度至明信息科技有限公司
C69: 陈晨 汇总
B70: 2017/2/16 汇总
A71: 64 汇总
A72: 73 | B72: 42838 | C72: 黄玉飞 | D72: 浙江太美医疗科技有限公司
C73: 黄玉飞 汇总
B74: 2017/4/13 汇总
A75: 73 汇总
A76: 76 | B76: 42849 | C76: 钱小军 | D76: 安永中国咨询
C77: 钱小军 汇总
B78: 2017/4/24 汇总
A79: 76 汇总
A80: 82 | B80: 42935 | C80: 杨振东 | D80: 上海方亿信息科技有限公司
C81: 杨振东 汇总
B82: 2017/7/19 汇总
A83: 82 汇总
A84: 84 | B84: 42940 | C84: 任剑钢 | D84: 哔哩哔哩
C85: 任剑钢 汇总
B86: 2017/7/24 汇总
A87: 84 汇总
A88: 86 | B88: 42954 | C88: 杨帅麒 | D88: 上海盛大汽车服务集团
C89: 杨帅麒 汇总
B90: 2017/8/7 汇总
A91: 86 汇总
A92: 88 | B92: 42964 | C92: 黄杲 | D92: 上海卓盟信息科技有限公司
C93: 黄杲 汇总
B94: 2017/8/17 汇总
A95: 88 汇总
A96: 91 | B96: 42991 | C96: 解安亮 | D96: 谱域科技
C97: 解安亮 汇总
B98: 2017/9/13 汇总
A99: 91 汇总
A100: 98 | B100: 43080 | C100: 王浩 | D100: 贵州小爱机器人科技有限公司
C101: 王浩 汇总
...

Sheet 杭州
A1: 地区 | B1: 杭州
A3: 序号 | B3: 加入时间 | C3: 会籍时间 | D3: 姓名 | E3: 公司 | H3: 点击地区 > 点击刷新数据源 > 点击（部分）输入对应的城市
A4: 2 | B4: 42132 | C4: 46203 | D4: 郭理靖 | E4: 奈雪的茶
D5: 郭理靖 汇总
C6: 2026/6/30 汇总
B7: 2015/5/8 汇总
A8: 2 汇总
A9: 36 | B9: 42537 | C9: 46203 | D9: 孙其瑞 | E9: 苏州优频科技有限公司
D10: 孙其瑞 汇总
C11: 2026/6/30 汇总
B12: 2016/6/16 汇总
A13: 36 汇总
A14: 37 | B14: 42552 | C14: 46203 | D14: 芦宇峰 | E14: 上海擎路科技
D15: 芦宇峰 汇总
C16: 2026/6/30 汇总
B17: 2016/7/1 汇总
A18: 37 汇总
A19: 58 | B19: 42731 | C19: 46203 | D19: 李卓 | E19: 道富信息科技
D20: 李卓 汇总
C21: 2026/6/30 汇总
B22: 2016/12/27 汇总
A23: 58 汇总
A24: 65 | B24: 42783 | C24: 46203 | D24: 林佳齐 | E24: 西阿爱木
D25: 林佳齐 汇总
C26: 2026/6/30 汇总
B27: 2017/2/17 汇总
A28: 65 汇总
A29: 77 | B29: 42866 | C29: 46203 | D29: 王翱宇 | E29: 杭州谐云科技有限公司
D30: 王翱宇 汇总
C31: 2026/6/30 汇总
B32: 2017/5/11 汇总
A33: 77 汇总
A34: 83 | B34: 42936 | C34: 46203 | D34: 张志成 | E34: 阿里巴巴达摩院
D35: 张志成 汇总
C36: 2026/6/30 汇总
B37: 2017/7/20 汇总
A38: 83 汇总
A39: 92 | B39: 43000 | C39: 46203 | D39: 褚亮 | E39: 杭州咿啦科技有限公司
D40: 褚亮 汇总
C41: 2026/6/30 汇总
B42: 2017/9/22 汇总
A43: 92 汇总
A44: 93 | B44: 43004 | C44: 46203 | D44: 沈淦 | E44: 杭州正马软件科技有限公司
D45: 沈淦 汇总
C46: 2026/6/30 汇总
B47: 2017/9/26 汇总
A48: 93 汇总
A49: 127 | B49: 43251 | C49: 45838 | D49: 胡海 | E49: 嗨逛
D50: 胡海 汇总
C51: 2025/6/30 汇总
B52: 2018/5/31 汇总
A53: 127 汇总
A54: 247 | B54: 43718 | C54: 46203 | D54: 姜博 | E54: 有赞
D55: 姜博 汇总
C56: 2026/6/30 汇总
B57: 2019/9/10 汇总
A58: 247 汇总
A59: 260 | B59: 43780 | C59: 46203 | D59: 李良敏 | E59: 浙江卫视
D60: 李良敏 汇总
C61: 2026/6/30 汇总
B62: 2019/11/11 汇总
A63: 260 汇总
A64: 282 | B64: 43837 | C64: 46203 | D64: 杨德华 | E64: 杭州数列网络科技有限公司
D65: 杨德华 汇总
C66: 2026/6/30 汇总
B67: 2020/1/7 汇总
A68: 282 汇总
A69: 287 | B69: 43854 | C69: 46203 | D69: 张进 | E69: 杭州观远数据有限公司
D70: 张进 汇总
C71: 2026/6/30 汇总
B72: 2020/1/24 汇总
A73: 287 汇总
A74: 316 | B74: 44025 | C74: 46203 | D74: 吴小宁 | E74: 杭州文思千问智能科技有限公司
D75: 吴小宁 汇总
C76: 2026/6/30 汇总
B77: 2020/7/13 汇总
A78: 316 汇总
A79: 319 | B79: 44047 | C79: 45838 | D79: 杨永清 | E79: 青岛国创智能家电研究院有限公司
D80: 杨永清 汇总
C81: 2025/6/30 汇总
B82: 2020/8/4 汇总
A83: 319 汇总
A84: 329 | B84: 44099 | C84: 46203 | D84: 刘增俊 | E84: 上海曦智科技
D85: 刘增俊 汇总
C86: 2026/6/30 汇总
B87: 2020/9/25 汇总
A88: 329 汇总
A89: 356 | B89: 44234 | C89: 46203 | D89: 黄魏 | E89: 杭州天戟
D90: 黄魏 汇总
C91: 2026/6/30 汇总
B92: 2021/2/7 汇总
A93: 356 汇总
A94: 381 | B94: 44334 | C94: 46203 | D94: 邹燕建 | E94: 要务科技
D95: 邹燕建 汇总
C96: 2026/6/30 汇总
B97: 2021/5/18 汇总
A98: 381 汇总
A99: 382 | B99: 44334 | C99: 46203 | D99: 李喜财 | E99: 北京商越网络科技有限公司
D100: 李喜财 汇总
C101: 2026/6/30 汇总
...

Sheet 北京
A1: 地区 | B1: 北京 | H1: 点击地区 > 点击刷新数据源 > 点击（部分）输入对应的城市
A3: 序号 | B3: 加入时间 - 年份 | C3: 姓名 | D3: 公司 | H3: 点击地区 > 点击刷新数据源 > 点击（部分）输入对应的城市
A4: 3 | B4: 2015年 | C4: 陈锡言 | D4: 一览科技
C5: 陈锡言 汇总
B6: 2015年 汇总
A7: 3 汇总
A8: 4 | B8: 2015年 | C8: 汪威 | D8: 心语未来
C9: 汪威 汇总
B10: 2015年 汇总
A11: 4 汇总
A12: 8 | B12: 2015年 | C12: 史海峰 | D12: 方正证券
C13: 史海峰 汇总
B14: 2015年 汇总
A15: 8 汇总
A16: 9 | B16: 2015年 | C16: 梁宇鹏 | D16: 蓝莺IM
C17: 梁宇鹏 汇总
B18: 2015年 汇总
A19: 9 汇总
A20: 10 | B20: 2015年 | C20: 熊昌伟 | D20: 畅捷通信息技术有限公司
C21: 熊昌伟 汇总
B22: 2015年 汇总
A23: 10 汇总
A24: 12 | B24: 2015年 | C24: 陈靖华 | D24: 北京基调网络股份有限公司
C25: 陈靖华 汇总
B26: 2015年 汇总
A27: 12 汇总
A28: 13 | B28: 2015年 | C28: 侯冬雯 | D28: 北京微梦传媒
C29: 侯冬雯 汇总
B30: 2015年 汇总
A31: 13 汇总
A32: 17 | B32: 2015年 | C32: 洪强宁 | D32: 雅识科技
C33: 洪强宁 汇总
B34: 2015年 汇总
A35: 17 汇总
A36: 18 | B36: 2015年 | C36: 李道兵 | D36: Fortinet Principal Embedded Software Developer
C37: 李道兵 汇总
B38: 2015年 汇总
A39: 18 汇总
A40: 24 | B40: 2015年 | C40: 华健 | D40: 北京梦诚科技
C41: 华健 汇总
B42: 2015年 汇总
A43: 24 汇总
A44: 26 | B44: 2016年 | C44: 李玉福 | D44: 农信互联
C45: 李玉福 汇总
B46: 2016年 汇总
A47: 26 汇总
A48: 43 | B48: 2016年 | C48: 陈峰 | D48: Red Hat
C49: 陈峰 汇总
B50: 2016年 汇总
A51: 43 汇总
A52: 46 | B52: 2016年 | C52: 廖雄杰 | D52: 基调听云
C53: 廖雄杰 汇总
B54: 2016年 汇总
A55: 46 汇总
A56: 49 | B56: 2016年 | C56: 卢亿雷 | D56: 白海科技
C57: 卢亿雷 汇总
B58: 2016年 汇总
A59: 49 汇总
A60: 59 | B60: 2016年 | C60: 吴永强 | D60: 便利蜂
C61: 吴永强 汇总
B62: 2016年 汇总
A63: 59 汇总
A64: 61 | B64: 2017年 | C64: 孙斌 | D64: 去哪儿网
C65: 孙斌 汇总
B66: 2017年 汇总
A67: 61 汇总
A68: 62 | B68: 2017年 | C68: 杨冀龙 | D68: 北京知道创宇信息技术有限公司
C69: 杨冀龙 汇总
B70: 2017年 汇总
A71: 62 汇总
A72: 63 | B72: 2017年 | C72: 余峰 | D72: 汉迪移动互联网科技股份有限公司
C73: 余峰 汇总
B74: 2017年 汇总
A75: 63 汇总
A76: 66 | B76: 2017年 | C76: 焦洋 | D76: 盖亚互娱
C77: 焦洋 汇总
B78: 2017年 汇总
A79: 66 汇总
A80: 67 | B80: 2017年 | C80: 张觅 | D80: 况客科技（北京）有限公司
C81: 张觅 汇总
B82: 2017年 汇总
A83: 67 汇总
A84: 70 | B84: 2017年 | C84: 李伟辰 | D84: 知道创宇
C85: 李伟辰 汇总
B86: 2017年 汇总
A87: 70 汇总
A88: 71 | B88: 2017年 | C88: 郭炜 | D88: 白鲸开源
C89: 郭炜 汇总
B90: 2017年 汇总
A91: 71 汇总
A92: 72 | B92: 2017年 | C92: 崔浩波 | D92: 嗨学
C93: 崔浩波 汇总
B94: 2017年 汇总
A95: 72 汇总
A96: 85 | B96: 2017年 | C96: 杨红光 | D96: 玲珑卓越科技
C97: 杨红光 汇总
B98: 2017年 汇总
A99: 85 汇总
A100: 87 | B100: 2017年 | C100: 胡继伟 | D100: 合思
C101: 胡继伟 汇总
...

Sheet 广州
A1: 地区 | B1: 广州
H2: 点击地区 > 点击刷新数据源 > 点击（部分）输入对应的城市
A3: 序号 | B3: 加入时间 - 年份 | C3: 姓名 | D3: 公司
A4: 6 | B4: 2015年 | C4: 邹光先 | D4: 其他
C5: 邹光先 汇总
B6: 2015年 汇总
A7: 6 汇总
A8: 25 | B8: 2016年 | C8: 何世友 | D8: 腾讯云
C9: 何世友 汇总
B10: 2016年 汇总
A11: 25 汇总
A12: 27 | B12: 2016年 | C12: 曾冠东 | D12: 酷狗音乐
C13: 曾冠东 汇总
B14: 2016年 汇总
A15: 27 汇总
A16: 28 | B16: 2016年 | C16: 路文杰 | D16: 甘果科技
C17: 路文杰 汇总
B18: 2016年 汇总
A19: 28 汇总
A20: 30 | B20: 2016年 | C20: 刘建国 | D20: 伊智信息科技
C21: 刘建国 汇总
B22: 2016年 汇总
A23: 30 汇总
A24: 35 | B24: 2016年 | C24: 苏煦烽 | D24: 亲邻科技
C25: 苏煦烽 汇总
B26: 2016年 汇总
A27: 35 汇总
A28: 39 | B28: 2016年 | C28: 黄伟坚 | D28: mobvista汇量科技
C29: 黄伟坚 汇总
B30: 2016年 汇总
A31: 39 汇总
A32: 44 | B32: 2016年 | C32: 张志合 | D32: 广州卓越教育
C33: 张志合 汇总
B34: 2016年 汇总
A35: 44 汇总
A36: 45 | B36: 2016年 | C36: 谢金牛 | D36: 深圳风信计算机服务有限公司
C37: 谢金牛 汇总
B38: 2016年 汇总
A39: 45 汇总
A40: 57 | B40: 2016年 | C40: 贾锦杰 | D40: KEEP
C41: 贾锦杰 汇总
B42: 2016年 汇总
A43: 57 汇总
A44: 68 | B44: 2017年 | C44: 陈颖棠 | D44: 论客科技（广州）有限公司
C45: 陈颖棠 汇总
B46: 2017年 汇总
A47: 68 汇总
A48: 79 | B48: 2017年 | C48: 暨家愉 | D48: 腾讯
C49: 暨家愉 汇总
B50: 2017年 汇总
A51: 79 汇总
A52: 101 | B52: 2017年 | C52: 李少春 | D52: 广州博泰数据有限公司
C53: 李少春 汇总
B54: 2017年 汇总
A55: 101 汇总
A56: 106 | B56: 2018年 | C56: 吴传兵 | D56: 广州味美优品食品科技有限公司
C57: 吴传兵 汇总
B58: 2018年 汇总
A59: 106 汇总
A60: 120 | B60: 2018年 | C60: 肖玉军 | D60: 广州安信云信息科技有限公司
C61: 肖玉军 汇总
B62: 2018年 汇总
A63: 120 汇总
A64: 152 | B64: 2018年 | C64: 王仁明 | D64: 哈尔滨工业大学人工智能研究院
C65: 王仁明 汇总
B66: 2018年 汇总
A67: 152 汇总
A68: 155 | B68: 2018年 | C68: 李渭宁 | D68: 汇丰科技
C69: 李渭宁 汇总
B70: 2018年 汇总
A71: 155 汇总
A72: 170 | B72: 2018年 | C72: 刘昊臻 | D72: eolinker
C73: 刘昊臻 汇总
B74: 2018年 汇总
A75: 170 汇总
A76: 199 | B76: 2019年 | C76: 邹春刚 | D76: 广州快批信息科技有限公司
C77: 邹春刚 汇总
B78: 2019年 汇总
A79: 199 汇总
A80: 206 | B80: 2019年 | C80: 赵欣 | D80: 广州国邦网络科技有限公司
C81: 赵欣 汇总
B82: 2019年 汇总
A83: 206 汇总
A84: 213 | B84: 2019年 | C84: 冯大双 | D84: 很久文化
C85: 冯大双 汇总
B86: 2019年 汇总
A87: 213 汇总
A88: 219 | B88: 2019年 | C88: 袁泉 | D88: 浪潮电子信息产业股份有限公司
C89: 袁泉 汇总
B90: 2019年 汇总
A91: 219 汇总
A92: 220 | B92: 2019年 | C92: 姚维 | D92: PingCAP
C93: 姚维 汇总
B94: 2019年 汇总
A95: 220 汇总
A96: 230 | B96: 2019年 | C96: 杨韶伟 | D96: 广州威而比科技有限公司
C97: 杨韶伟 汇总
B98: 2019年 汇总
A99: 230 汇总
A100: 241 | B100: 2019年 | C100: 何丹 | D100: 网易游戏
...

Sheet 成都
A1: 地区 | B1: 成都
A3: 序号 | B3: 加入时间 | C3: 会籍时间 | D3: 姓名 | E3: 公司 | H3: 点击地区 > 点击刷新数据源 > 点击（部分）输入对应的城市
A4: 69 | B4: 42801 | C4: 46203 | D4: 黎宏伟 | E4: 中科院山地所
D5: 黎宏伟 汇总
C6: 2026/6/30 汇总
B7: 2017/3/7 汇总
A8: 69 汇总
A9: 80 | B9: 42886 | C9: 46203 | D9: 肖毅 | E9: 成都智客科技有限公司
D10: 肖毅 汇总
C11: 2026/6/30 汇总
B12: 2017/5/31 汇总
A13: 80 汇总
A14: 102 | B14: 43096 | C14: 46203 | D14: 于君泽 | E14: 智绘未来
D15: 于君泽 汇总
C16: 2026/6/30 汇总
B17: 2017/12/27 汇总
A18: 102 汇总
A19: 105 | B19: 43128 | C19: 46203 | D19: 马力遥 | E19: 互联极简网络科技成都有限公司
D20: 马力遥 汇总
C21: 2026/6/30 汇总
B22: 2018/1/28 汇总
A23: 105 汇总
A24: 114 | B24: 43187 | C24: 46203 | D24: 徐桢虎 | E24: 封面传媒科技
D25: 徐桢虎 汇总
C26: 2026/6/30 汇总
B27: 2018/3/28 汇总
A28: 114 汇总
A29: 123 | B29: 43228 | C29: 46203 | D29: 李涛 | E29: 上海骐原智能科技有限公司
D30: 李涛 汇总
C31: 2026/6/30 汇总
B32: 2018/5/8 汇总
A33: 123 汇总
A34: 143 | B34: 43285 | C34: 46203 | D34: 程飞 | E34: 四川乐为科技有限公司
D35: 程飞 汇总
C36: 2026/6/30 汇总
B37: 2018/7/4 汇总
A38: 143 汇总
A39: 150 | B39: 43319 | C39: 46203 | D39: 梁强 | E39: 四川蜀宁科技有限公司
D40: 梁强 汇总
C41: 2026/6/30 汇总
B42: 2018/8/7 汇总
A43: 150 汇总
A44: 154 | B44: 43340 | C44: 45838 | D44: 朱涛 | E44: 华为微波产品部
D45: 朱涛 汇总
C46: 2025/6/30 汇总
B47: 2018/8/28 汇总
A48: 154 汇总
A49: 181 | B49: 43446 | C49: 46203 | D49: 蒲永波 | E49: 重庆港澳大家软件产业有限公司
D50: 蒲永波 汇总
C51: 2026/6/30 汇总
B52: 2018/12/12 汇总
A53: 181 汇总
A54: 185 | B54: 43452 | C54: 46203 | D54: 罗仕杰 | E54: 马上消费
D55: 罗仕杰 汇总
C56: 2026/6/30 汇总
B57: 2018/12/18 汇总
A58: 185 汇总
A59: 200 | B59: 43496 | C59: 46203 | D59: 冯智超 | E59: 金数据
D60: 冯智超 汇总
C61: 2026/6/30 汇总
B62: 2019/1/31 汇总
A63: 200 汇总
A64: 208 | B64: 43550 | C64: 46203 | D64: 王聪 | E64: 成都橙意保
D65: 王聪 汇总
C66: 2026/6/30 汇总
B67: 2019/3/26 汇总
A68: 208 汇总
A69: 222 | B69: 43619 | C69: 45838 | D69: 杨博 | E69: 成都博智云创科技有限公司
D70: 杨博 汇总
C71: 2025/6/30 汇总
B72: 2019/6/3 汇总
A73: 222 汇总
A74: 242 | B74: 43703 | C74: 46203 | D74: 卿明 | E74: 成都滨桦智能科技
D75: 卿明 汇总
C76: 2026/6/30 汇总
B77: 2019/8/26 汇总
A78: 242 汇总
A79: 263 | B79: 43809 | C79: 46203 | D79: 唐雷 | E79: 成都医联科技有限公司
D80: 唐雷 汇总
C81: 2026/6/30 汇总
B82: 2019/12/10 汇总
A83: 263 汇总
A84: 301 | B84: 43986 | C84: 45838 | D84: 邓金城 | E84: 北京知道创宇信息技术股份有限公司
D85: 邓金城 汇总
C86: 2025/6/30 汇总
B87: 2020/6/4 汇总
A88: 301 汇总
A89: 308 | B89: 44011 | C89: 46203 | D89: 李睿 | E89: 龙湖
D90: 李睿 汇总
C91: 2026/6/30 汇总
B92: 2020/6/29 汇总
A93: 308 汇总
A94: 397 | B94: 44403 | C94: 46203 | D94: 王磊 | E94: AI产品空气小猪
D95: 王磊 汇总
C96: 2026/6/30 汇总
B97: 2021/7/26 汇总
A98: 397 汇总
A99: 441 | B99: 44529 | C99: 46203 | D99: 周华君 | E99: 成都恩淳思信息技术有限责任公司
D100: 周华君 汇总
C101: 2026/6/30 汇总
...

Sheet 南京
A1: 地区 | B1: 南京
A3: 序号 | B3: 加入时间 | C3: 会籍时间 | D3: 姓名 | E3: 公司 | H3: 点击地区 > 点击刷新数据源 > 点击（部分）输入对应的城市
A4: 51 | B4: 42695 | C4: 46203 | D4: 王河生 | E4: 南京四维向量科技有限公司
D5: 王河生 汇总
C6: 2026/6/30 汇总
B7: 2016/11/21 汇总
A8: 51 汇总
A9: 81 | B9: 42927 | C9: 46203 | D9: 曹祖鹏 | E9: 南京知亦行信息技术有限公司
D10: 曹祖鹏 汇总
C11: 2026/6/30 汇总
B12: 2017/7/11 汇总
A13: 81 汇总
A14: 99 | B14: 43082 | C14: 46203 | D14: 樊伟伟 | E14: 微鲤
D15: 樊伟伟 汇总
C16: 2026/6/30 汇总
B17: 2017/12/13 汇总
A18: 99 汇总
A19: 103 | B19: 43098 | C19: 46203 | D19: 李列为 | E19: 江苏华博实业集团有限公司
D20: 李列为 汇总
C21: 2026/6/30 汇总
B22: 2017/12/29 汇总
A23: 103 汇总
A24: 122 | B24: 43227 | C24: 46203 | D24: 周雨桐 | E24: 南京功夫豆信息科技有限公司
D25: 周雨桐 汇总
C26: 2026/6/30 汇总
B27: 2018/5/7 汇总
A28: 122 汇总
A29: 124 | B29: 43228 | C29: 46203 | D29: 刘明 | E29: 三星电子（中国）
D30: 刘明 汇总
C31: 2026/6/30 汇总
B32: 2018/5/8 汇总
A33: 124 汇总
A34: 125 | B34: 43230 | C34: 46203 | D34: 吴焕红 | E34: 中国旅游集团旅行服务有限公司
D35: 吴焕红 汇总
C36: 2026/6/30 汇总
B37: 2018/5/10 汇总
A38: 125 汇总
A39: 183 | B39: 43447 | C39: 46203 | D39: 马进 | E39: 数字小能人
D40: 马进 汇总
C41: 2026/6/30 汇总
B42: 2018/12/13 汇总
A43: 183 汇总
A44: 187 | B44: 43462 | C44: 46203 | D44: 陈桂峰 | E44: 南京宽乐健康
D45: 陈桂峰 汇总
C46: 2026/6/30 汇总
B47: 2018/12/28 汇总
A48: 187 汇总
A49: 188 | B49: 43462 | C49: 46203 | D49: 嵇伟 | E49: 神笔软件有限责任公司
D50: 嵇伟 汇总
C51: 2026/6/30 汇总
B52: 2018/12/28 汇总
A53: 188 汇总
A54: 205 | B54: 43532 | C54: 46203 | D54: 王雷 | E54: 福建新大陆软件工程有限公司
D55: 王雷 汇总
C56: 2026/6/30 汇总
B57: 2019/3/8 汇总
A58: 205 汇总
A59: 253 | B59: 43753 | C59: 46203 | D59: 程云 | E59: 江苏群杰物联科技有限公司
D60: 程云 汇总
C61: 2026/6/30 汇总
B62: 2019/10/15 汇总
A63: 253 汇总
A64: 274 | B64: 43829 | C64: 46203 | D64: 冀烨 | E64: 江苏省未来网络创新研究院
D65: 冀烨 汇总
C66: 2026/6/30 汇总
B67: 2019/12/30 汇总
A68: 274 汇总
A69: 283 | B69: 43855 | C69: 46203 | D69: 陈儒 | E69: 北京小诚文化传媒南京研发中心
D70: 陈儒 汇总
C71: 2026/6/30 汇总
B72: 2020/1/25 汇总
A73: 283 汇总
A74: 322 | B74: 44079 | C74: 46203 | D74: 郭有春 | E74: 腾讯云
D75: 郭有春 汇总
C76: 2026/6/30 汇总
B77: 2020/9/5 汇总
A78: 322 汇总
A79: 332 | B79: 44134 | C79: 46203 | D79: 马锋 | E79: 江苏泰治科技股份有限公司
D80: 马锋 汇总
C81: 2026/6/30 汇总
B82: 2020/10/30 汇总
A83: 332 汇总
A84: 355 | B84: 44232 | C84: 45838 | D84: 王东 | E84: 满帮集团
D85: 王东 汇总
C86: 2025/6/30 汇总
B87: 2021/2/5 汇总
A88: 355 汇总
A89: 360 | B89: 44253 | C89: 45838 | D89: 叶飞 | E89: 迪原创新
D90: 叶飞 汇总
C91: 2025/6/30 汇总
B92: 2021/2/26 汇总
A93: 360 汇总
A94: 365 | B94: 44267 | C94: 45838 | D94: 谢钢 | E94: 南京云恩通讯科技有限公司
D95: 谢钢 汇总
C96: 2025/6/30 汇总
B97: 2021/3/12 汇总
A98: 365 汇总
A99: 451 | B99: 44559 | C99: 45838 | D99: 任翔 | E99: WEBEYE
D100: 任翔 汇总
C101: 2025/6/30 汇总
...

Sheet 厦门
A1: 地区 | B1: 厦门
A3: 序号 | B3: 加入时间 | C3: 会籍时间 | D3: 姓名 | E3: 公司 | H3: 点击地区 > 点击刷新数据源 > 点击（部分）输入对应的城市
A4: 总计

Sheet 苏州
A1: 地区 | B1: 苏州
A3: 序号 | B3: 加入时间 | C3: 会籍时间 | D3: 姓名 | E3: 公司 | H3: 点击地区 > 点击刷新数据源 > 点击（部分）输入对应的城市
A4: 19 | B4: 42300 | C4: 46203 | D4: 张海龙 | E4: 同程旅行
D5: 张海龙 汇总
C6: 2026/6/30 汇总
B7: 2015/10/23 汇总
A8: 19 汇总
A9: 20 | B9: 42300 | C9: 46203 | D9: 王晓波 | E9: 同程旅行
D10: 王晓波 汇总
C11: 2026/6/30 汇总
B12: 2015/10/23 汇总
A13: 20 汇总
A14: 54 | B14: 42723 | C14: 46203 | D14: 练海荣 | E14: 龙石数据
D15: 练海荣 汇总
C16: 2026/6/30 汇总
B17: 2016/12/19 汇总
A18: 54 汇总
A19: 78 | B19: 42912 | C19: 46203 | D19: 徐庆新 | E19: 苏州乐佰图信息技术有限公司
D20: 徐庆新 汇总
C21: 2026/6/30 汇总
B22: 2017/6/26 汇总
A23: 78 汇总
A24: 168 | B24: 43406 | C24: 46203 | D24: 钟晓樑 | E24: 苏州盖雅信息技术有限公司
D25: 钟晓樑 汇总
C26: 2026/6/30 汇总
B27: 2018/11/2 汇总
A28: 168 汇总
A29: 172 | B29: 43424 | C29: 46934 | D29: 马金昌 | E29: 洛基英语
D30: 马金昌 汇总
C31: 2028/6/30 汇总
B32: 2018/11/20 汇总
A33: 172 汇总
A34: 179 | B34: 43434 | C34: 46203 | D34: 邱良军 | E34: 苏州正雄企业发展有限公司
D35: 邱良军 汇总
C36: 2026/6/30 汇总
B37: 2018/11/30 汇总
A38: 179 汇总
A39: 267 | B39: 43816 | C39: 46203 | D39: 蒋良东 | E39: 京东工业品
D40: 蒋良东 汇总
C41: 2026/6/30 汇总
B42: 2019/12/17 汇总
A43: 267 汇总
A44: 348 | B44: 44183 | C44: 46203 | D44: 熊伟 | E44: 苏州盖雅信息技术有限公司
D45: 熊伟 汇总
C46: 2026/6/30 汇总
B47: 2020/12/18 汇总
A48: 348 汇总
A49: 413 | B49: 44438 | C49: 46203 | D49: 宋少鸿 | E49: 苏州盈天地资讯科技有限公司
D50: 宋少鸿 汇总
C51: 2026/6/30 汇总
B52: 2021/8/30 汇总
A53: 413 汇总
A54: 512 | B54: 44774 | C54: 46203 | D54: 顾浩 | E54: 苏州盖雅信息技术有限公司
D55: 顾浩 汇总
C56: 2026/6/30 汇总
B57: 2022/8/1 汇总
A58: 512 汇总
A59: 525 | B59: 44800 | C59: 46568 | D59: 陈晗琪 | E59: 苏州英格玛服务外包股份有限公司
D60: 陈晗琪 汇总
C61: 2027/6/30 汇总
B62: 2022/8/27 汇总
A63: 525 汇总
A64: 533 | B64: 44848 | C64: 45473 | D64: 师江帆 | E64: 苏州市龙测智能科技有限公司
D65: 师江帆 汇总
C66: 2024/6/30 汇总
B67: 2022/10/14 汇总
A68: 533 汇总
A69: 545 | B69: 44893 | C69: 46203 | D69: 宋军超 | E69: 苏州瑞云智服信息科技有限公司
D70: 宋军超 汇总
C71: 2026/6/30 汇总
B72: 2022/11/28 汇总
A73: 545 汇总
A74: 657 | B74: 45183 | C74: 46203 | D74: 王战勇 | E74: 苏州恒琪信息科技有限公司
D75: 王战勇 汇总
C76: 2026/6/30 汇总
B77: 2023/9/14 汇总
A78: 657 汇总
A79: 669 | B79: 45216 | C79: 46203 | D79: 江文东 | E79: 苏州正雄企业发展有限公司
D80: 江文东 汇总
C81: 2026/6/30 汇总
B82: 2023/10/17 汇总
A83: 669 汇总
A84: 677 | B84: 45227 | C84: 45596 | D84: 曹海峰 | E84: 苏州盈合工具有限公司
D85: 曹海峰 汇总
C86: 2024/10/31 汇总
B87: 2023/10/28 汇总
A88: 677 汇总
A89: 708 | B89: 45260 | C89: 46568 | D89: 孙磊 | E89: 苏州课得乐教育科技有限公司
D90: 孙磊 汇总
C91: 2027/6/30 汇总
B92: 2023/11/30 汇总
A93: 708 汇总
A94: 749 | B94: 45301 | C94: 46203 | D94: 金路 | E94: 智慧芽信息科技
D95: 金路 汇总
C96: 2026/6/30 汇总
B97: 2024/1/10 汇总
A98: 749 汇总
A99: 835 | B99: 45459 | C99: 46203 | D99: 刘培彬 | E99: 苏州新歌科技有限责任公司
D100: 刘培彬 汇总
C101: 2026/6/30 汇总
...

Sheet 武汉
A1: 地区 | B1: 武汉
A3: 序号 | B3: 加入时间 | C3: 会籍时间 | D3: 姓名 | E3: 公司 | H3: 点击地区 > 点击刷新数据源 > 点击（部分）输入对应的城市
A4: 126 | B4: 43248 | C4: 46568 | D4: 吕兆星 | E4: 北京万界数据
D5: 吕兆星 汇总
C6: 2027/6/30 汇总
B7: 2018/5/28 汇总
A8: 126 汇总
A9: 128 | B9: 43264 | C9: 46934 | D9: 谢锐 | E9: 维克时光
D10: 谢锐 汇总
C11: 2028/6/30 汇总
B12: 2018/6/13 汇总
A13: 128 汇总
A14: 166 | B14: 43403 | C14: 45473 | D14: 万学凡 | E14: 凯捷咨询（中国）有限公司
D15: 万学凡 汇总
C16: 2024/6/30 汇总
B17: 2018/10/30 汇总
A18: 166 汇总
A19: 169 | B19: 43413 | C19: 45473 | D19: 姚化鹏 | E19: 金山办公
D20: 姚化鹏 汇总
C21: 2024/6/30 汇总
B22: 2018/11/9 汇总
A23: 169 汇总
A24: 173 | B24: 43425 | C24: 46203 | D24: 吴清忠 | E24: 北京万界数据武汉分公司
D25: 吴清忠 汇总
C26: 2026/6/30 汇总
B27: 2018/11/21 汇总
A28: 173 汇总
A29: 225 | B29: 43661 | C29: 45473 | D29: 詹威 | E29: 深圳优诚
D30: 詹威 汇总
C31: 2024/6/30 汇总
B32: 2019/7/15 汇总
A33: 225 汇总
A34: 227 | B34: 43662 | C34: 46568 | D34: 谢强 | E34: 武汉极意网络科技有限公司
D35: 谢强 汇总
C36: 2027/6/30 汇总
B37: 2019/7/16 汇总
A38: 227 汇总
A39: 238 | B39: 43703 | C39: 46203 | D39: 丁鹏 | E39: 北京万界智算
D40: 丁鹏 汇总
C41: 2026/6/30 汇总
B42: 2019/8/26 汇总
A43: 238 汇总
A44: 344 | B44: 45988 | C44: 46568 | D44: 陈驰远 | E44: 北京青橙信息技术有限公司
D45: 陈驰远 汇总
C46: 2027/6/30 汇总
B47: 2025/11/27 汇总
A48: 344 汇总
A49: 376 | B49: 44323 | C49: 45838 | D49: 曾丽星 | E49: 武汉噢易云计算股份有限公司
D50: 曾丽星 汇总
C51: 2025/6/30 汇总
B52: 2021/5/7 汇总
A53: 376 汇总
A54: 438 | B54: 46020 | C54: 46568 | D54: 罗小虎 | E54: 一号车市
D55: 罗小虎 汇总
C56: 2027/6/30 汇总
B57: 2025/12/29 汇总
A58: 438 汇总
A59: 518 | B59: 45994 | C59: 46568 | D59: 贾腾飞 | E59: 阿里云
D60: 贾腾飞 汇总
C61: 2027/6/30 汇总
B62: 2025/12/3 汇总
A63: 518 汇总
A64: 687 | B64: 44378 | C64: 45606 | D64: 张扬 | E64: 极狐(GitLab)
D65: 张扬 汇总
C66: 2024/11/10 汇总
B67: 2021/7/1 汇总
A68: 687 汇总
A69: 702 | B69: 45260 | C69: 45838 | D69: 栾义来 | E69: 湖北九州医药供应链有限公司
D70: 栾义来 汇总
C71: 2025/6/30 汇总
B72: 2023/11/30 汇总
A73: 702 汇总
A74: 719 | B74: 45272 | C74: 45838 | D74: 苏丹 | E74: 31Games
D75: 苏丹 汇总
C76: 2025/6/30 汇总
B77: 2023/12/12 汇总
A78: 719 汇总
A79: 845 | B79: 45470 | C79: 46203 | D79: 万仁亮 | E79: 开心灿烂
D80: 万仁亮 汇总
C81: 2026/6/30 汇总
B82: 2024/6/27 汇总
A83: 845 汇总
A84: 1092 | B84: 45869 | C84: 46203 | D84: 涂亮 | E84: 武汉凯比思电力设备有限公司
D85: 涂亮 汇总
C86: 2026/6/30 汇总
B87: 2025/7/31 汇总
A88: 1092 汇总
A89: 总计

Sheet 新加坡
A1: 地区 | B1: 新加坡
A3: 序号 | B3: 加入时间 | C3: 会籍时间 | D3: 姓名 | E3: 公司 | H3: 点击地区 > 点击刷新数据源 > 点击（部分）输入对应的城市
A4: 11 | B4: 42209 | C4: 46203 | D4: 丁宁 | E4: 荔枝集团
D5: 丁宁 汇总
C6: 2026/6/30 汇总
B7: 2015/7/24 汇总
A8: 11 汇总
A9: 177 | B9: 43437 | C9: 45838 | D9: 唐铕泽 | E9: 1Token
D10: 唐铕泽 汇总
C11: 2025/6/30 汇总
B12: 2018/12/3 汇总
A13: 177 汇总
A14: 278 | B14: 43843 | C14: 45838 | D14: 张兴华 | E14: King Coder Pte Ltd
D15: 张兴华 汇总
C16: 2025/6/30 汇总
B17: 2020/1/13 汇总
A18: 278 汇总
A19: 572 | B19: 45012 | C19: 45838 | D19: 杨锦涛 | E19: The Place Holdings
D20: 杨锦涛 汇总
C21: 2025/6/30 汇总
B22: 2023/3/27 汇总
A23: 572 汇总
A24: 597 | B24: 45078 | C24: 45473 | D24: 韩轶东 | E24: Reddio
D25: 韩轶东 汇总
C26: 2024/6/30 汇总
B27: 2023/6/1 汇总
A28: 597 汇总
A29: 609 | B29: 45097 | C29: 45838 | D29: 曾东方 | E29: EdgeNext
D30: 曾东方 汇总
C31: 2025/6/30 汇总
B32: 2023/6/20 汇总
A33: 609 汇总
A34: 618 | B34: 45114 | C34: 45838 | D34: 熊培淞 | E34: ReAPI
D35: 熊培淞 汇总
C36: 2025/6/30 汇总
B37: 2023/7/7 汇总
A38: 618 汇总
A39: 619 | B39: 45119 | C39: 45473 | D39: 李凌 | E39: Heyvva
D40: 李凌 汇总
C41: 2024/6/30 汇总
B42: 2023/7/12 汇总
A43: 619 汇总
A44: 625 | B44: 45131 | C44: 45473 | D44: 李江玕 | E44: Momentum Works Pte Ltd
D45: 李江玕 汇总
C46: 2024/6/30 汇总
B47: 2023/7/24 汇总
A48: 625 汇总
A49: 630 | B49: 45141 | C49: 45838 | D49: 蔡荔 | E49: DataOwl
D50: 蔡荔 汇总
C51: 2025/6/30 汇总
B52: 2023/8/3 汇总
A53: 630 汇总
A54: 632 | B54: 45142 | C54: 45473 | D54: 钟庚发 | E54: ChainUp Pte Ltd
D55: 钟庚发 汇总
C56: 2024/6/30 汇总
B57: 2023/8/4 汇总
A58: 632 汇总
A59: 633 | B59: 45142 | C59: 45473 | D59: 弓子介 | E59: OceanBase
D60: 弓子介 汇总
C61: 2024/6/30 汇总
B62: 2023/8/4 汇总
A63: 633 汇总
A64: 634 | B64: 45147 | C64: 45473 | D64: 颜世兴 | E64: Lazada
D65: 颜世兴 汇总
C66: 2024/6/30 汇总
B67: 2023/8/9 汇总
A68: 634 汇总
A69: 645 | B69: 45169 | C69: 45473 | D69: 郑炜翔 | E69: 华为云
D70: 郑炜翔 汇总
C71: 2024/6/30 汇总
B72: 2023/8/31 汇总
A73: 645 汇总
A74: 650 | B74: 45173 | C74: 45473 | D74: 冯继强 | E74: 极光无限信息技术有限公司
D75: 冯继强 汇总
C76: 2024/6/30 汇总
B77: 2023/9/4 汇总
A78: 650 汇总
A79: 655 | B79: 45183 | C79: 45473 | D79: 李毅 | E79: 华为技术有限公司新加坡分公司
D80: 李毅 汇总
C81: 2024/6/30 汇总
B82: 2023/9/14 汇总
A83: 655 汇总
A84: 666 | B84: 44391 | C84: 45473 | D84: 冯越 | E84: 声网
D85: 冯越 汇总
C86: 2024/6/30 汇总
B87: 2021/7/14 汇总
A88: 666 汇总
A89: 697 | B89: 45251 | C89: 45473 | D89: 尤洋 | E89: 潞晨科技
D90: 尤洋 汇总
C91: 2024/6/30 汇总
B92: 2023/11/21 汇总
A93: 697 汇总
A94: 701 | B94: 43942 | C94: 45618 | D94: 荚济民 | E94: Envision Digital
D95: 荚济民 汇总
C96: 2024/11/22 汇总
B97: 2020/4/21 汇总
A98: 701 汇总
A99: 758 | B99: 45317 | C99: 45838 | D99: 邓爵 | E99: ChainStar.Cloud
D100: 邓爵 汇总
C101: 2025/6/30 汇总
...

Sheet 硅谷
A1: 地区 | B1: 硅谷
A3: 序号 | B3: 加入时间 | C3: 会籍时间 | D3: 姓名 | E3: 公司 | H3: 点击地区 > 点击刷新数据源 > 点击（部分）输入对应的城市
A4: 74 | B4: 42838 | C4: 46203 | D4: 任腾 | E4: AI Rudder
D5: 任腾 汇总
C6: 2026/6/30 汇总
B7: 2017/4/13 汇总
A8: 74 汇总
A9: 149 | B9: 43308 | C9: 46934 | D9: 夏澎 | E9: 博世
D10: 夏澎 汇总
C11: 2028/6/30 汇总
B12: 2018/7/27 汇总
A13: 149 汇总
A14: 295 | B14: 43976 | C14: 45838 | D14: 张云浩 | E14: 力扣（LeetCode）
D15: 张云浩 汇总
C16: 2025/6/30 汇总
B17: 2020/5/25 汇总
A18: 295 汇总
A19: 357 | B19: 44228 | C19: 45473 | D19: 王雄 | E19: 腾讯
D20: 王雄 汇总
C21: 2024/6/30 汇总
B22: 2021/2/1 汇总
A23: 357 汇总
A24: 377 | B24: 44325 | C24: 46203 | D24: 杨森 | E24: 点线面体
D25: 杨森 汇总
C26: 2026/6/30 汇总
B27: 2021/5/9 汇总
A28: 377 汇总
A29: 379 | B29: 44316 | C29: 45838 | D29: 曹翔 | E29: Tik Tok
D30: 曹翔 汇总
C31: 2025/6/30 汇总
B32: 2021/4/30 汇总
A33: 379 汇总
A34: 384 | B34: 44336 | C34: 46203 | D34: 周然 | E34: LigaAI
D35: 周然 汇总
C36: 2026/6/30 汇总
B37: 2021/5/20 汇总
A38: 384 汇总
A39: 454 | B39: 44565 | C39: 45838 | D39: 王泳帅 | E39: 宝洁
D40: 王泳帅 汇总
C41: 2025/6/30 汇总
B42: 2022/1/4 汇总
A43: 454 汇总
A44: 547 | B44: 44894 | C44: 46203 | D44: 肖伦文 | E44: 上海吉谛科技有限公司
D45: 肖伦文 汇总
C46: 2026/6/30 汇总
B47: 2022/11/29 汇总
A48: 547 汇总
A49: 626 | B49: 45133 | C49: 45657 | D49: 张俊伟 | E49: Doordash
D50: 张俊伟 汇总
C51: 2024/12/31 汇总
B52: 2023/7/26 汇总
A53: 626 汇总
A54: 637 | B54: 45159 | C54: 45838 | D54: 刘正一 James | E54: 阿里云
D55: 刘正一 James 汇总
C56: 2025/6/30 汇总
B57: 2023/8/21 汇总
A58: 637 汇总
A59: 640 | B59: 45162 | C59: 46203 | D59: 刘洋 | E59: ScaleFlux Inc.
D60: 刘洋 汇总
C61: 2026/6/30 汇总
B62: 2023/8/24 汇总
A63: 640 汇总
A64: 680 | B64: 45231 | C64: 46203 | D64: 王文锋 | E64: Lifecycle AI
D65: 王文锋 汇总
C66: 2026/6/30 汇总
B67: 2023/11/1 汇总
A68: 680 汇总
A69: 695 | B69: 43210 | C69: 45657 | D69: 孙超 | E69: 西部数据
D70: 孙超 汇总
C71: 2024/12/31 汇总
B72: 2018/4/20 汇总
A73: 695 汇总
A74: 696 | B74: 43210 | C74: 45657 | D74: 潘洋洋 | E74: VMware
D75: 潘洋洋 汇总
C76: 2024/12/31 汇总
B77: 2018/4/20 汇总
A78: 696 汇总
A79: 712 | B79: 45262 | C79: 45657 | D79: 叶谦 | E79: Celerdata Inc.
D80: 叶谦 汇总
C81: 2024/12/31 汇总
B82: 2023/12/2 汇总
A83: 712 汇总
A84: 724 | B84: 45276 | C84: 45657 | D84: 鲁颖 | E84: Zoom
D85: 鲁颖 汇总
C86: 2024/12/31 汇总
B87: 2023/12/16 汇总
A88: 724 汇总
A89: 727 | B89: 42676 | C89: 45657 | D89: 黄东旭 | E89: PingCAP
D90: 黄东旭 汇总
C91: 2024/12/31 汇总
B92: 2016/11/2 汇总
A93: 727 汇总
A94: 730 | B94: 45281 | C94: 45657 | D94: 杨润德 | E94: Dream Voyage
D95: 杨润德 汇总
C96: 2024/12/31 汇总
B97: 2023/12/21 汇总
A98: 730 汇总
A99: 733 | B99: 45289 | C99: 45657 | D99: 谢超（星爵） | E99: Ziliz
D100: 谢超（星爵） 汇总
C101: 2024/12/31 汇总
...

Sheet 台北
A1: 地区 | B1: 台北
A3: 序号 | B3: 加入时间 | C3: 会籍时间 | D3: 姓名 | E3: 公司 | H3: 点击地区 > 点击刷新数据源 > 点击（部分）输入对应的城市
A4: 131 | B4: 43275 | C4: 46203 | D4: 曾義峰 | E4: 書亞集成股份有限公司
D5: 曾義峰 汇总
C6: 2026/6/30 汇总
B7: 2018/6/24 汇总
A8: 131 汇总
A9: 132 | B9: 43275 | C9: 46203 | D9: 王銘駿 | E9: DFI 友通资讯
D10: 王銘駿 汇总
C11: 2026/6/30 汇总
B12: 2018/6/24 汇总
A13: 132 汇总
A14: 133 | B14: 43275 | C14: 46203 | D14: 林秉毅 | E14: 天鏡科技
D15: 林秉毅 汇总
C16: 2026/6/30 汇总
B17: 2018/6/24 汇总
A18: 133 汇总
A19: 134 | B19: 43275 | C19: 46203 | D19: 游舒帆 | E19: 箴亞管理顧問有限公司
D20: 游舒帆 汇总
C21: 2026/6/30 汇总
B22: 2018/6/24 汇总
A23: 134 汇总
A24: 135 | B24: 43275 | C24: 46203 | D24: 施政源 | E24: 寓意科技
D25: 施政源 汇总
C26: 2026/6/30 汇总
B27: 2018/6/24 汇总
A28: 135 汇总
A29: 136 | B29: 43275 | C29: 46203 | D29: 莊靈 | E29: 慧邦科技股份有限公司
D30: 莊靈 汇总
C31: 2026/6/30 汇总
B32: 2018/6/24 汇总
A33: 136 汇总
A34: 137 | B34: 43275 | C34: 46203 | D34: 蔣鐙緯 | E34: 派仕科技有限公司
D35: 蔣鐙緯 汇总
C36: 2026/6/30 汇总
B37: 2018/6/24 汇总
A38: 137 汇总
A39: 138 | B39: 43275 | C39: 46203 | D39: 林瑞男 | E39: PIXNET
D40: 林瑞男 汇总
C41: 2026/6/30 汇总
B42: 2018/6/24 汇总
A43: 138 汇总
A44: 139 | B44: 43275 | C44: 46203 | D44: 王志清 | E44: LEADBEST, 安世泰有限公司
D45: 王志清 汇总
C46: 2026/6/30 汇总
B47: 2018/6/24 汇总
A48: 139 汇总
A49: 140 | B49: 43275 | C49: 46203 | D49: 李致緯 | E49: iCook 愛料理
D50: 李致緯 汇总
C51: 2026/6/30 汇总
B52: 2018/6/24 汇总
A53: 140 汇总
A54: 146 | B54: 43305 | C54: 46203 | D54: 林秉忠 | E54: 雄獅旅遊
D55: 林秉忠 汇总
C56: 2026/6/30 汇总
B57: 2018/7/24 汇总
A58: 146 汇总
A59: 147 | B59: 43305 | C59: 46203 | D59: 李境展 Tomas Li | E59: Titansoft Pte Ltd_新加坡商鈦坦科技股份有限公司台灣分公司
D60: 李境展 Tomas Li 汇总
C61: 2026/6/30 汇总
B62: 2018/7/24 汇总
A63: 147 汇总
A64: 148 | B64: 43305 | C64: 46203 | D64: 黃智彬 | E64: 舉手電商
D65: 黃智彬 汇总
C66: 2026/6/30 汇总
B67: 2018/7/24 汇总
A68: 148 汇总
A69: 217 | B69: 43586 | C69: 46203 | D69: 林裕欽 | E69: Dcard_狄卡科技股份有限公司
D70: 林裕欽 汇总
C71: 2026/6/30 汇总
B72: 2019/5/1 汇总
A73: 217 汇总
A74: 234 | B74: 43678 | C74: 46203 | D74: 黃泳瑜 | E74: 巴可股份有限公司
D75: 黃泳瑜 汇总
C76: 2026/6/30 汇总
B77: 2019/8/1 汇总
A78: 234 汇总
A79: 254 | B79: 43753 | C79: 46203 | D79: 江致平 | E79: 新加坡商鈦坦科技台灣分公司
D80: 江致平 汇总
C81: 2026/6/30 汇总
B82: 2019/10/15 汇总
A83: 254 汇总
A84: 294 | B84: 43864 | C84: 46203 | D84: 黃元亨 | E84: 印尼商艾希英
D85: 黃元亨 汇总
C86: 2026/6/30 汇总
B87: 2020/2/3 汇总
A88: 294 汇总
A89: 总计

Sheet 各城市人数
A1: 计数:姓名
A2: 999 | C2: 郭炜
C3: 陈冲
C4: 龚银
C5: 路文杰
C6: 李卓
C7: 嵇伟
C8: 马力遥
C9: 杨瑞
C10: 练海荣
C14: 谢锐

Sheet Sheet16
A1: 地区 | B1: 杭州
A3: 序号 | B3: 加入时间 | C3: 会籍时间 | D3: 姓名 | E3: 公司 | H3: 点击地区 > 点击刷新数据源 > 点击（部分）输入对应的城市
A4: 2 | B4: 42132 | C4: 46203 | D4: 郭理靖 | E4: 奈雪的茶
D5: 郭理靖 汇总
C6: 2026/6/30 汇总
B7: 2015/5/8 汇总
A8: 2 汇总
A9: 36 | B9: 42537 | C9: 46203 | D9: 孙其瑞 | E9: 苏州优频科技有限公司
D10: 孙其瑞 汇总
C11: 2026/6/30 汇总
B12: 2016/6/16 汇总
A13: 36 汇总
A14: 37 | B14: 42552 | C14: 46203 | D14: 芦宇峰 | E14: 上海擎路科技
D15: 芦宇峰 汇总
C16: 2026/6/30 汇总
B17: 2016/7/1 汇总
A18: 37 汇总
A19: 58 | B19: 42731 | C19: 46203 | D19: 李卓 | E19: 道富信息科技
D20: 李卓 汇总
C21: 2026/6/30 汇总
B22: 2016/12/27 汇总
A23: 58 汇总
A24: 65 | B24: 42783 | C24: 46203 | D24: 林佳齐 | E24: 西阿爱木
D25: 林佳齐 汇总
C26: 2026/6/30 汇总
B27: 2017/2/17 汇总
A28: 65 汇总
A29: 77 | B29: 42866 | C29: 46203 | D29: 王翱宇 | E29: 杭州谐云科技有限公司
D30: 王翱宇 汇总
C31: 2026/6/30 汇总
B32: 2017/5/11 汇总
A33: 77 汇总
A34: 83 | B34: 42936 | C34: 46203 | D34: 张志成 | E34: 阿里巴巴达摩院
D35: 张志成 汇总
C36: 2026/6/30 汇总
B37: 2017/7/20 汇总
A38: 83 汇总
A39: 92 | B39: 43000 | C39: 46203 | D39: 褚亮 | E39: 杭州咿啦科技有限公司
D40: 褚亮 汇总
C41: 2026/6/30 汇总
B42: 2017/9/22 汇总
A43: 92 汇总
A44: 93 | B44: 43004 | C44: 46203 | D44: 沈淦 | E44: 杭州正马软件科技有限公司
D45: 沈淦 汇总
C46: 2026/6/30 汇总
B47: 2017/9/26 汇总
A48: 93 汇总
A49: 127 | B49: 43251 | C49: 45838 | D49: 胡海 | E49: 嗨逛
D50: 胡海 汇总
C51: 2025/6/30 汇总
B52: 2018/5/31 汇总
A53: 127 汇总
A54: 247 | B54: 43718 | C54: 46203 | D54: 姜博 | E54: 有赞
D55: 姜博 汇总
C56: 2026/6/30 汇总
B57: 2019/9/10 汇总
A58: 247 汇总
A59: 260 | B59: 43780 | C59: 46203 | D59: 李良敏 | E59: 浙江卫视
D60: 李良敏 汇总
C61: 2026/6/30 汇总
B62: 2019/11/11 汇总
A63: 260 汇总
A64: 282 | B64: 43837 | C64: 46203 | D64: 杨德华 | E64: 杭州数列网络科技有限公司
D65: 杨德华 汇总
C66: 2026/6/30 汇总
B67: 2020/1/7 汇总
A68: 282 汇总
A69: 287 | B69: 43854 | C69: 46203 | D69: 张进 | E69: 杭州观远数据有限公司
D70: 张进 汇总
C71: 2026/6/30 汇总
B72: 2020/1/24 汇总
A73: 287 汇总
A74: 316 | B74: 44025 | C74: 46203 | D74: 吴小宁 | E74: 杭州文思千问智能科技有限公司
D75: 吴小宁 汇总
C76: 2026/6/30 汇总
B77: 2020/7/13 汇总
A78: 316 汇总
A79: 319 | B79: 44047 | C79: 45838 | D79: 杨永清 | E79: 青岛国创智能家电研究院有限公司
D80: 杨永清 汇总
C81: 2025/6/30 汇总
B82: 2020/8/4 汇总
A83: 319 汇总
A84: 329 | B84: 44099 | C84: 46203 | D84: 刘增俊 | E84: 上海曦智科技
D85: 刘增俊 汇总
C86: 2026/6/30 汇总
B87: 2020/9/25 汇总
A88: 329 汇总
A89: 356 | B89: 44234 | C89: 46203 | D89: 黄魏 | E89: 杭州天戟
D90: 黄魏 汇总
C91: 2026/6/30 汇总
B92: 2021/2/7 汇总
A93: 356 汇总
A94: 381 | B94: 44334 | C94: 46203 | D94: 邹燕建 | E94: 要务科技
D95: 邹燕建 汇总
C96: 2026/6/30 汇总
B97: 2021/5/18 汇总
A98: 381 汇总
A99: 382 | B99: 44334 | C99: 46203 | D99: 李喜财 | E99: 北京商越网络科技有限公司
D100: 李喜财 汇总
C101: 2026/6/30 汇总
...

Sheet 不续费
A1: 序号 | B1: 加入时间 | C1: 会籍时间 | D1: 姓名 | E1: 地区 | F1: 公司 | G1: 职位 | H1: 会员类型 | I1: 会员编号 | J1: 新会员培训时间 | K1: 上线官网 | L1: 所属行业 | M1: 备注
B2: 44651 | C2: 45016 | D2: 胡闽 | E2: 杭州 | F2: 亿格云 | G2: CTO | H2: 企业会员 | I2: 1577 | K2: 1
B3: =B2+1 -> 44652 | C3: 42552 | D3: 石戬 | E3: 北京 | F3: 小鱼山房企服影棚 | G3: CEO | H3: 标准会员 | I3: 177 | K3: 1
B5: =会员总表!B492+1 -> 42608 | C5: 43369 | D5: 陈实如 | E5: 北京 | F5: 前 方正宽带 | G5: CTO | H5: 标准会员 | I5: 681 | K5: 1
B6: =B5+1 -> 42609 | C6: 43532 | D6: 刘广民 | E6: 北京 | F6: 龙湖集团 | G6: 龙湖商业CTO | H6: 标准会员 | I6: 819 | K6: 1
B7: =B6+1 -> 42610 | C7: 44001 | D7: 王怡 | E7: 北京 | F7: 随行付支付有限公司 | G7: 研发中心助理总经理 | H7: 企业会员 | I7: 1113 | K7: 1
B8: =B7+1 -> 42611 | C8: 44201 | D8: 姚延栋 | E8: 北京 | F8: 北京四维纵横数据技术有限公司 | G8: CEO | H8: 标准会员 | I8: 1236 | J8: 44945 | K8: 1
B9: =B8+1 -> 42612 | C9: 44218 | D9: 翟佳 | E9: 北京 | F9: StreamNative | G9: 联合创始人 | H9: 企业会员 | I9: 1245 | J9: 44958 | K9: 1
B10: =B9+1 -> 42613 | C10: 44235 | D10: 吴金龙 | E10: 北京 | F10: 海南贝叶智能科技有限公司 | G10: 技术负责人 | H10: 企业会员 | I10: 1255 | J10: 44996 | K10: 1
B11: =B10+1 -> 42614 | C11: 44270 | D11: 赵浩多 | E11: 北京 | F11: 北京知斗科技有限公司 | G11: 合伙人兼CTO | H11: 标准会员 | I11: 1274 | J11: 45016 | K11: 1
B12: =B11+1 -> 42615 | C12: 44278 | D12: 蒋光桃 | E12: 北京 | F12: 彩讯科技股份有限公司 | G12: 技术VP | H12: 标准会员 | I12: 1280 | J12: 45015 | K12: 1
B13: =B12+1 -> 42616 | C13: 44378 | D13: 杜晓祥 | E13: 北京 | F13: 北京云上曲率科技有限公司 | G13: CEO | H13: 标准会员 | I13: 1341 | K13: 1
B14: =B13+1 -> 42617 | C14: 44379 | D14: 鹿靳坤 | E14: 北京 | F14: 北京花房科技有限公司 | G14: 高级技术总监 | H14: 标准会员 | I14: 1356 | J14: 45121 | K14: 1
B15: =B14+1 -> 42618 | C15: 44397 | D15: 杨路 | E15: 北京 | F15: 狮桥 | G15: 高级技术总监 | H15: 标准会员 | I15: 1363 | J15: 45143 | K15: 1
B16: =B15+1 -> 42619 | C16: 44406 | D16: 尚清刚 | E16: 北京 | F16: 澳优 | G16: 大数据总监 | H16: 标准会员 | I16: 1367 | J16: 45144 | K16: 1
B17: =B16+1 -> 42620 | C17: 44425 | D17: 王新涵 | E17: 北京 | F17: 北京快牛智营科技有限公司 | G17: CTO | H17: 标准会员 | I17: 1389 | J17: 45169 | K17: 1
B18: =B17+1 -> 42621 | C18: 44432 | D18: 郝闯 | E18: 北京 | F18: 脉时云（北京云联万维技术有限公司） | G18: 创始人&CEO | H18: 企业会员 | I18: 1393 | J18: 45169 | K18: 1
B19: =B18+1 -> 42622 | C19: 44490 | D19: 林统传 | E19: 北京 | F19: 雪球(北京)信息科技技术有限公司 | G19: 技术经理 | H19: 标准会员 | I19: 1411 | J19: 45227 | K19: 1
B20: =B19+1 -> 42623 | C20: 44510 | D20: 李光 | E20: 北京 | F20: 北京一润一达科技有限公司 | G20: CEO | H20: 标准会员 | I20: 1428 | J20: 45253 | K20: 1
B21: =B20+1 -> 42624 | C21: 44511 | D21: 杨振华 | E21: 北京 | F21: 阿里云计算有限公司 | G21: 中国区游戏行业技术负责人 | H21: 标准会员 | I21: 1431 | J21: 44544 | K21: 1
B22: =B21+1 -> 42625 | C22: 44525 | D22: 杨毓丞 | E22: 北京 | F22: 知藏 | G22: 技术总监 | H22: 标准会员 | I22: 99 | J22: 老会员回归 | K22: 1
B23: =B22+1 -> 42626 | C23: 44530 | D23: 赵振东 | E23: 北京 | F23: 北京焱融科技有限公司 | G23: 高级技术总监 | H23: 企业会员 | I23: 1443 | J23: 44546 | K23: 1
B24: =B23+1 -> 42627 | C24: 44536 | D24: 冯森 | E24: 北京 | F24: 北京方云 | G24: 联合创始人兼CTO | H24: 企业会员 | I24: 1446 | J24: 44546 | K24: 1
B25: =B24+1 -> 42628 | C25: 44539 | D25: 高峰 | E25: 北京 | F25: 京东 | G25: 架构师 | H25: 标准会员 | I25: 1456 | J25: 44614 | K25: 1
B26: =B25+1 -> 42629 | C26: 44573 | D26: 何小锋 | E26: 北京 | F26: 京东科技 | G26: 高级技术总监 | H26: 企业会员 | I26: 1484 | J26: 44581 | K26: 1
B27: =B26+1 -> 42630 | C27: 44610 | D27: 白景滨 | E27: 北京 | F27: 内蒙古物链易通科技股份有限公司 | G27: 研发总监 | H27: 标准会员 | I27: 1509 | J27: 44652 | K27: 1
B28: =B27+1 -> 42631 | C28: 44669 | D28: 谢扬 | E28: 北京 | F28: Authing 身份云 | G28: CEO | H28: / | I28: 1554 | J28: 44719 | K28: 1
B29: =B28+1 -> 42632 | C29: 44671 | D29: 舒超 | E29: 北京 | F29: 星汉未来网络科技有限公司 | G29: CTO | H29: / | I29: 1555 | J29: 44791 | K29: 1
B30: =B29+1 -> 42633 | C30: 44680 | D30: 谭敏锋 | E30: 北京 | F30: 北京致远互联软件股份有限公司 | G30: 副总裁 | H30: 企业会员 | I30: 1562 | K30: 1
B31: =B30+1 -> 42634 | C31: 44742 | D31: 李松林 | E31: 北京 | F31: 珩宇科技 | G31: 合伙人 | H31: 标准会员 | I31: 459 | J31: 老会员回归 | K31: 1
B32: 44809 | C32: 45107 | D32: 蔺瑞军 | E32: 北京 | F32: 阿里云 | G32: 技术负责人 | H32: / | I32: 1628 | J32: 44819 | K32: 1
B33: 44811 | C33: 45107 | D33: 王明华 | E33: 北京 | F33: 北京市多来点信息技术有限公司 | G33: CTO | H33: / | I33: 1631 | J33: 44819 | K33: 1
C34: 45107 | D34: 高铁柱 | E34: 北京 | F34: 百度时代网络技术（北京）有限公司 | G34: 技术经理 | H34: / | I34: 1632 | J34: 44817 | K34: 1
B35: 44858 | C35: 45107 | D35: 李坤 | E35: 北京 | F35: PingCAP | G35: 中国出海事业部技术总监 | H35: / | I35: 1647 | J35: 44867 | K35: 1
B36: 44900 | C36: 45107 | D36: 董江 | E36: 北京 | F36: 中国移动云能力中心 | G36: 高级系统架构师专家 | H36: / | I36: 1666 | J36: 44908 | K36: 1
B38: 44904 | C38: 45107 | D38: 李佳峰 | E38: 北京 | F38: 北京中安网星科技有限责任公司 | G38: CTO | H38: 企业会员 | I38: 1671 | J38: 44965 | K38: 1
B39: 42417 | C39: 45107 | D39: 王平 | E39: 成都 | F39: 猿人学 | G39: CEO | H39: 标准会员 | I39: 106 | K39: 1
B40: 42552 | C40: 45107 | D40: 黄云 | E40: 成都 | F40: 川报观察 | G40: CTO | H40: 标准会员 | I40: 179 | K40: 1
B41: 42657 | C41: 45107 | D41: 贾乐 | E41: 成都 | F41: 京东 | G41: 技术总监 | H41: 标准会员 | I41: 252 | K41: 1
B42: 42724 | C42: 45107 | D42: 张印 | E42: 成都 | F42: 成都翌擎科技 | G42: 联合创始人兼CTO | H42: 标准会员 | I42: 285 | K42: 1
B43: 42997 | C43: 45107 | D43: 廖茜 | E43: 成都 | F43: 美团 | G43: 架构师 | H43: 标准会员 | I43: 413 | K43: 1
B44: 43087 | C44: 45107 | D44: 张永波 | E44: 成都 | F44: 北京知道创宇信息技术有限公司 | G44: 产品线总经理 | H44: 标准会员 | I44: 445 | K44: 1
B45: 43472 | C45: 45107 | D45: 程名 | E45: 成都 | F45: 重庆交运集团 | G45: 科技信息部部长 | H45: 标准会员 | I45: 776 | K45: 1
B46: 43472 | C46: 45107 | D46: 龙武 | E46: 成都 | F46: 成都医联科技有限公司 | G46: CTO | H46: 标准会员 | I46: 777 | K46: 1
B47: 43580 | C47: 45107 | D47: 柳飞 | E47: 成都 | F47: 成都博智云创科技有限公司 | G47: 业务线负责人 | H47: 标准会员 | I47: 858 | K47: 1
B48: 43782 | C48: 45107 | D48: 杜伟 | E48: 成都 | F48: 西安梵响数据 | G48: 总经理 | H48: 标准会员 | I48: 996 | J48: 44993 | K48: 1
B49: 44315 | C49: 45107 | D49: 蔡灿 | E49: 成都 | F49: 招商新智 | G49: 重庆创新办公室负责人 | H49: 标准会员 | I49: 13007 | J49: 45087 | K49: 1
B50: 44335 | C50: 45107 | D50: 黄鹏 | E50: 成都 | F50: 成都晓多科技有限公司 | G50: CTO | H50: 企业会员 | I50: 1323 | J50: 45094 | K50: 1
B52: 44610 | C52: 45107 | D52: 刘世林 | E52: 成都 | F52: 北京深度搜索科技有限公司 | G52: CTO | H52: 标准会员 | I52: 1510 | J52: 44630 | K52: 1
B53: 44615 | C53: 45107 | D53: 颜海涛 | E53: 成都 | F53: 四川创力科技有限责任公司 | G53: 研发总监 | H53: 标准会员 | I53: 1513 | J53: 44630 | K53: 1
B54: 44754 | C54: 45107 | D54: 周旭 | E54: 成都 | F54: FITURE | G54: 软件研发负责人 | H54: 标准会员 | I54: 830 | J54: 老会员回归 | K54: 1
B55: 43244 | C55: 45107 | D55: 刘嗣平 | E55: 广州 | F55: 九四智能 | G55: 创始人&CEO | H55: 企业会员 | I55: 562 | K55: 1
B56: 43861 | C56: 45107 | D56: 张保峰 | E56: 广州 | F56: 创酷互动 | G56: CTO | H56: 标准会员 | I56: 1060 | K56: 1
B57: 44146 | C57: 45107 | D57: 汤杰 | E57: 广州 | F57: 西山居 | G57: 技术总监 | H57: 标准会员 | I57: 1198 | J57: 45254 | K57: 1
B58: 44174 | C58: 45107 | D58: 刘跃 | E58: 广州 | F58: 特斯联 | G58: 技术总监 | H58: 标准会员 | I58: 1212 | J58: 45280 | K58: 1
B59: 44333 | C59: 45107 | D59: 马玉文 | E59: 广州 | F59: 富米科技 | G59: 技术负责人 | H59: 标准会员 | I59: 1320 | J59: 45143 | K59: 1
B60: 44511 | C60: 45107 | D60: 赵明芳 | E60: 广州 | F60: 华为技术有限公司 | G60: 广州华为云业务总经理 | H60: 标准会员 | I60: 1429 | K60: 1
B61: 44519 | C61: 45107 | D61: 许坤丰 | E61: 广州 | F61: 广州视睿电子 | G61: 技术经理 | H61: 标准会员 | I61: 1439 | J61: 44546 | K61: 1
B62: 44536 | C62: 45107 | D62: 黄仁 | E62: 广州 | F62: 优维科技（深圳）有限公司 | G62: 研发总监 | H62: 标准会员 | I62: 1447 | J62: 44579 | K62: 1
B63: 44539 | C63: 45107 | D63: 黄八斤 | E63: 广州 | F63: 北京基调网络 | G63: 技术总监 | H63: 标准会员 | I63: 1457 | J63: 44579 | K63: 1
B64: 44585 | C64: 45107 | D64: 阚嘉彬 | E64: 广州 | F64: 保利投资顾问有限公司 | G64: 技术总监 | H64: 标准会员 | I64: 1489 | J64: 44614 | K64: 1
B65: 44586 | C65: 45107 | D65: 李翔 | E65: 广州 | F65: WakeData | G65: 算法负责人 | H65: 标准会员 | I65: 1490 | J65: 44651 | K65: 1
B66: 44588 | C66: 45107 | D66: 彭翔 | E66: 广州 | F66: 广东上佳照明科技有限公司 | G66: 总经理 | H66: 标准会员 | I66: 1492 | J66: 44616 | K66: 1
B67: 44645 | C67: 45107 | D67: 龚宏绩 | E67: 广州 | F67: 首都在线 | G67: CTO&海外事业部副总经理 | H67: 企业会员 | I67: 1537 | J67: 44672 | K67: 1
B68: 44797 | C68: 45107 | D68: 江纬 | E68: 广州 | F68: 软通动力 | G68: 高级人工智能专家 | H68: / | I68: 1618 | J68: 44868 | K68: 1
B69: 44810 | C69: 45107 | D69: 宋振蔚 | E69: 广州 | F69: 广州亦云信息科技有限公司 | G69: 研发总经理 | H69: 标准会员 | I69: 366 | J69: 老会员 | K69: 1
B70: 42333 | C70: 45107 | D70: 陈超 | E70: 杭州 | F70: 七牛云 | G70: 首席产品官/董事 | H70: 企业会员 | I70: 87 | K70: 1
B71: 43795 | C71: 45107 | D71: 马京超 | E71: 杭州 | F71: 南通云尚找家纺电子商务有限公司杭州分公司 | G71: 技术总监 | H71: 标准会员 | I71: 1004 | J71: 44983 | K71: 1
B72: 44104 | C72: 45107 | D72: 林河山 | E72: 杭州 | F72: 杭州几何唯优诊所有限公司 | G72: 联合创始人 | H72: 标准会员 | I72: 1172 | J72: 45228 | K72: 1
B73: 44183 | C73: 45107 | D73: 张国平 | E73: 杭州 | F73: 杭州光年数据科技有限公司 | G73: CEO | H73: 标准会员 | I73: 1222 | J73: 44932 | K73: 1
B74: 44234 | C74: 45107 | D74: 杨云兵 | E74: 杭州 | F74: 浙江乐檬 | G74: 技术总监 | H74: 标准会员 | I74: 1252 | J74: 44996 | K74: 1
B75: 44272 | C75: 45107 | D75: 周森 | E75: 杭州 | F75: 网易 | G75: 安全部、易盾产品部总经理 | H75: 企业会员 | I75: 1276 | J75: 45016 | K75: 1
B76: 44294 | C76: 45107 | D76: 刘涛 | E76: 杭州 | F76: 杭州老爸评测科技有限公司 | G76: 研发总监 | H76: 标准会员 | I76: 1292 | J76: 45058 | K76: 1
B77: 44480 | C77: 45107 | D77: 朴兴国 | E77: 杭州 | F77: 杭州视洞科技有限公司 | G77: 产品&研发高级副总裁 | H77: 标准会员 | I77: 1409 | J77: 45253 | K77: 1
B78: 44649 | C78: 45107 | D78: 胡晓阳 | E78: 杭州 | F78: 杭州健信科技有限公司 | G78: 技术总监 | H78: 标准会员 | I78: 1542 | J78: 44673 | K78: 1
B79: 44757 | C79: 45107 | D79: 徐丹青 | E79: 杭州 | F79: Bytebase | G79: CTO | H79: / | I79: 1589 | J79: 44775 | K79: 1
B80: 44767 | C80: 45107 | D80: 孙勤 | E80: 杭州 | F80: 杭州每刻科技有限公司 | G80: CTO | H80: / | I80: 1595 | J80: 44782 | K80: 1
B81: =B80+1 -> 44768 | C81: 44424 | D81: 李潜飞 | E81: 深圳 | F81: 腾讯 | G81: 广告-商业数据产品负责人 | H81: 标准会员 | I81: 1384 | J81: 45156 | K81: 1
A82: =#REF!+1 -> #REF! | B82: 43734 | C82: 45107 | D82: 薛军军 | E82: 北京 | F82: 中国船舶集团物资有限公司 | G82: 信息管理部 技术架构师 | H82: 标准会员 | I82: 968 | J82: 老会员回归 | K82: 1
B83: 43227 | C83: 45107 | D83: 李家强 | E83: 南京 | F83: 亚信安全 | G83: 架构师 | H83: 标准会员 | I83: 543 | K83: 1
B84: 43228 | C84: 45107 | D84: 苏金刚 | E84: 南京 | F84: 南京帮帮达信息科技有限公司 | G84: CEO | H84: 标准会员 | I84: 551 | K84: 1
B85: 43234 | C85: 45107 | D85: 缪鹏 | E85: 南京 | F85: 江苏立维互联科技有限公司 | G85: CEO | H85: 标准会员 | I85: 555 | K85: 1
B86: 43230 | C86: 45107 | D86: 张超 | E86: 南京 | F86: 国环碳中和 | G86: CEO | H86: 标准会员 | I86: 553 | K86: 1
B87: 43584 | C87: 45107 | D87: 刘涛 | E87: 南京 | F87: 江苏多飞网络科技有限公司 | G87: CTO | H87: 标准会员 | I87: 859 | K87: 1
B88: 43663 | C88: 45107 | D88: 李恒 | E88: 南京 | F88: 微鲤科技 | G88: 技术总监 | H88: 标准会员 | I88: 913 | K88: 1
B89: 43964 | C89: 45107 | D89: 叶成洲 | E89: 南京 | F89: 中科软科技股份有限公司 | G89: 总经理 | H89: 标准会员 | I89: 1090 | K89: 1
B90: 44104 | C90: 45107 | D90: 李文俊 | E90: 南京 | F90: 南京万米信息技术有限公司 | G90: CTO | H90: 标准会员 | I90: 1173 | J90: 45228 | K90: 1
B91: 44327 | C91: 45107 | D91: 曾祥斌 | E91: 南京 | F91: 南京箭竹网络科技有限公司 | G91: 总经理 | H91: 标准会员 | I91: 1314 | J91: 45087 | K91: 1
B92: 44378 | C92: 45107 | D92: 孟强 | E92: 南京 | F92: 南京树安信息技术有限公司 | G92: 联合创始人 | H92: 标准会员 | I92: 1342 | J92: 45120 | K92: 1
B93: 44378 | C93: 45107 | D93: 周红磊 | E93: 南京 | F93: 赛诺数据科技 | G93: 技术总监 | H93: 标准会员 | I93: 783 | J93: 45143 | K93: 1
B94: 44461 | C94: 45107 | D94: 徐俊杰 | E94: 南京 | F94: 赛诺贝斯 | G94: 交付部负责人 | H94: 标准会员 | I94: 1402 | K94: 1
B95: 44645 | C95: 45107 | D95: 陶林 | E95: 南京 | F95: 江苏星诺信息技术有限公司 | G95: CEO | H95: 企业会员 | I95: 1536 | J95: 44651 | K95: 1
B96: 44750 | C96: 45107 | D96: 朱彬 | E96: 南京 | F96: 江苏洺芯医疗康复管理有限公司 | G96: 副总经理 | H96: 标准会员 | I96: 1585 | J96: 老会员回归 | K96: 1
B97: 43462 | C97: 45107 | D97: 李仁杰 | E97: 厦门 | F97: 罗普特（厦门）科技集团有限公司 | G97: 第一研究院院长 | H97: 标准会员 | I97: 762 | K97: 1
B98: 43550 | C98: 45107 | D98: 陈建伟 | E98: 厦门 | F98: 厦门铃盛软件有限公司 | G98: 研发经理 | H98: 企业会员 | I98: 831 | K98: 1
B99: 43677 | C99: 45107 | D99: 黄及峰 | E99: 厦门 | F99: 美图公司 | G99: 技术总监 | H99: 标准会员 | I99: 926 | K99: 1
B100: 43781 | C100: 45107 | D100: 谢桂勇 | E100: 厦门 | F100: 福建番茄科技有限公司 | G100: 技术总监 | H100: 标准会员 | I100: 995 | K100: 1
B101: 42537 | C101: 45107 | D101: 谭伟 | E101: 上海 | F101: 上海敏识网络科技有限公司 | G101: CTO | H101: 标准会员 | I101: 169 | K101: 1
B102: 42662 | C102: 45107 | D102: 胡哲人 | E102: 上海 | F102: 上海流利说信息技术有限公司 | G102: CTO 联合创始人 | H102: 企业会员 | I102: 256 | K102: 1
B103: 42860 | C103: 45107 | D103: 李炫熠 | E103: 上海 | F103: 上海秦苍信息科技有限公司 | G103: 联合创始人&CTO | H103: 标准会员 | I103: 353 | K103: 1
...

Sheet Sheet33
A1: 订单号 | B1: 表单名称 | C1: 提交时间 | D1: 表单开始时间 | E1: 表单截止时间 | F1: 渠道 | G1: UTM | H1: 姓名 | I1: 所属分会 | J1: 请选择衣服尺码（男女同款） | K1: 区号 | L1: 联系电话 | M1: 邮寄地址 | N1: 目前所在公司名称+职务
A2: G25290443163987968 | B2: TGO鲲鹏会2025年度会员年度礼包信息收集 | C2: 45860.711 | D2: 45301 | F2: id=2735 | H2: 张念念 | I2: 北京 | J2: S（身高：160-165cm） | K2: =86 -> 86 | L2: 13673615407 | M2: 北京, 北京市, 东城区, 叶青大厦A座7层 | N2: 张念念
A3: G25290904798912512 | B3: TGO鲲鹏会2025年度会员年度礼包信息收集 | C3: 45860.752 | D3: 45301 | E3: 46063.999 | F3: id=2735 | H3: 陈肃 | I3: 北京 | J3: XL（身高：175-180cm） | K3: =86 -> 86 | L3: 13701065207 | M3: 北京, 北京市, 西城区, 参政胡同19号楼1208 | N3: 北京涛思数据科技有限公司 高级副总裁
A4: G25290906905505792 | B4: TGO鲲鹏会2025年度会员年度礼包信息收集 | C4: 45860.752 | D4: 45301 | E4: 46063.999 | F4: id=2735 | H4: 朱俊 | I4: 上海 | J4: L（身高：170-175cm） | K4: =86 -> 86 | L4: 13817564323 | M4: 上海, 上海市, 浦东新区, 惠南镇南园路327弄29号302室 | N4: 千瓦科技 创始人&CTO
A5: G25290907536613376 | B5: TGO鲲鹏会2025年度会员年度礼包信息收集 | C5: 45860.752 | D5: 45301 | E5: 46063.999 | F5: id=2735 | H5: 王立博 | I5: 上海 | J5: L（身高：170-175cm） | K5: =86 -> 86 | L5: 13817219818 | M5: 上海, 上海市, 浦东新区, 张江镇荣科路177号19号301室 | N5: 未来保贝 合伙人&CTO
A6: G25290908953632768 | B6: TGO鲲鹏会2025年度会员年度礼包信息收集 | C6: 45860.752 | D6: 45301 | E6: 46063.999 | F6: id=2735 | H6: 黄哲铿 | I6: 上海 | J6: M（身高：165-170cm） | K6: =86 -> 86 | L6: 13524102003 | M6: 上海, 上海市, 浦东新区, 唐镇齐爱路168号180-1003 | N6: 顿悟山丘科技，CEO
A7: G25290909551583232 | B7: TGO鲲鹏会2025年度会员年度礼包信息收集 | C7: 45860.752 | D7: 45301 | E7: 46063.999 | F7: id=2735 | H7: 张进 | I7: 杭州 | J7: L（身高：170-175cm） | K7: =86 -> 86 | L7: 15258849158 | M7: 浙江省, 杭州市, 余杭区, 海创园18幢708 | N7: 观远数据CTO
A8: G25290911393669120 | B8: TGO鲲鹏会2025年度会员年度礼包信息收集 | C8: 45860.752 | D8: 45301 | E8: 46063.999 | F8: id=2735 | H8: 张文涛 | I8: 上海 | J8: XL（身高：175-180cm） | K8: =86 -> 86 | L8: 18511480656 | M8: 上海, 上海市, 浦东新区, 广兰路50弄139号101 | N8: 北京焱融科技有限公司 CTO
A9: G25290912421408768 | B9: TGO鲲鹏会2025年度会员年度礼包信息收集 | C9: 45860.753 | D9: 45301 | E9: 46063.999 | F9: id=2735 | H9: 王金平 | I9: 深圳 | J9: XL（身高：175-180cm） | K9: =86 -> 86 | L9: 13910720924 | M9: 广东省, 深圳市, 福田区, 红荔西路鲁班大厦一区27WN | N9: 立创商城CIO
A10: G25290912440676352 | B10: TGO鲲鹏会2025年度会员年度礼包信息收集 | C10: 45860.753 | D10: 45301 | E10: 46063.999 | F10: id=2735 | H10: 范泽平 | I10: 广州 | J10: XL（身高：175-180cm） | K10: =86 -> 86 | L10: 18666942822 | M10: 广东省, 广州市, 海珠区, 石岗路中海观澔府 3 栋 3302 房 | N10: 北京博睿宏远数据科技股份有限公司+副总裁
A11: G25290913039933440 | B11: TGO鲲鹏会2025年度会员年度礼包信息收集 | C11: 45860.753 | D11: 45301 | E11: 46063.999 | F11: id=2735 | H11: 王海华 | I11: 深圳 | J11: 3XL（身高：185-190cm） | K11: =86 -> 86 | L11: 13426355910 | M11: 北京, 北京市, 西城区, 广安门外京铁和园6号楼1单元302 | N11: 货拉拉+高级AI&大数据架构师
A12: G25290913934106624 | B12: TGO鲲鹏会2025年度会员年度礼包信息收集 | C12: 45860.753 | D12: 45301 | E12: 46063.999 | F12: id=2735 | H12: 陈文 | I12: 北京 | J12: XL（身高：175-180cm） | K12: =86 -> 86 | L12: 18614055510 | M12: 北京, 北京市, 东城区, 南新仓商务大厦A座607 | N12: 乐可互动 CEO
A13: G25290914265849856 | B13: TGO鲲鹏会2025年度会员年度礼包信息收集 | C13: 45860.753 | D13: 45301 | E13: 46063.999 | F13: id=2735 | H13: 姚化鹏 | I13: 武汉 | J13: 2XL（身高：180-185cm） | K13: =86 -> 86 | L13: 13928059886 | M13: 湖北省, 武汉市, 洪山区, 关山大道保利时代北区14栋 | N13: 金山办公+总监
A14: G25290915070767104 | B14: TGO鲲鹏会2025年度会员年度礼包信息收集 | C14: 45860.753 | D14: 45301 | E14: 46063.999 | F14: id=2735 | H14: 宜博 | I14: 北京 | J14: L（身高：170-175cm） | K14: =86 -> 86 | L14: 13911181917 | M14: 北京, 北京市, 朝阳区, 孙河西路禧瑞春秋3-2-902 | N14: 宜创科技 CEO
... A176: G25291069591941120 | B176: TGO鲲鹏会2025年度会员年度礼包信息收集 | C176: 45860.766 | D176: 45301 | E176: 46063.999 | F176: id=2735 | H176: 王全根 | I176: 上海 | J176: L（身高：170-175cm） | K176: =86 -> 86 | L176: 16621269660 | M176: 上海, 上海市, 闵行区, 七莘路2299弄42号201 | N176: 外企德科，高级技术经理
A177: G25291070166687744 | B177: TGO鲲鹏会2025年度会员年度礼包信息收集 | C177: 45860.767 | D177: 45301 | E177: 46063.999 | F177: id=2735 | H177: 郭镭 | I177: 新加坡 | J177: M（身高：165-170cm） | K177: =65 -> 65 | L177: 93894155 | M177: 海外, 海外, 其他, 82 Frankel Avenue, 458210, Singapore | N177: Singdata, General Manager
A178: G25291074741497856 | B178: TGO鲲鹏会2025年度会员年度礼包信息收集 | C178: 45860.767 | D178: 45301 | E178: 46063.999 | F178: id=2735 | H178: 杨光 | I178: 北京 | J178: 2XL（身高：180-185cm） | K178: =86 -> 86 | L178: 13501186880 | M178: 北京, 北京市, 朝阳区, 朝阳区CBD国际大厦20层 矩量无限 | N178: 北京矩量无限科技有限公司 工程副总裁
A179: G25291076034523136 | B179: TGO鲲鹏会2025年度会员年度礼包信息收集 | C179: 45860.767 | D179: 45301 | E179: 46063.999 | F179: id=2735 | H179: 张永成 | I179: 苏州 | J179: L（身高：170-175cm） | K179: =86 -> 86 | L179: 13260118281 | M179: 江苏省, 苏州市, 苏州工业园区, 苏惠路88号环球财富广场1栋2106室 | N179: 诚成融合智科技公司 + CEO
A180: G25291080208248832 | B180: TGO鲲鹏会2025年度会员年度礼包信息收集 | C180: 45860.767 | D180: 45301 | E180: 46063.999 | F180: id=2735 | H180: 尚宇亮 | I180: 上海 | J180: L（身高：170-175cm） | K180: =86 -> 86 | L180: 13918077918 | M180: 上海, 上海市, 宝山区, 塘祁路517号48单元604室 | N180: 上海恒驰信息系统有限公司，副总裁
A181: G25291084564164608 | B181: TGO鲲鹏会2025年度会员年度礼包信息收集 | C181: 45860.768 | D181: 45301 | E181: 46063.999 | F181: id=2735 | H181: 练海荣 | I181: 苏州 | J181: 2XL（身高：180-185cm） | K181: =86 -> 86 | L181: 13771801998 | M181: 江苏省, 苏州市, 苏州工业园区, 星湖街创意产业园6-602室 | N181: 龙石数据 总经理
A182: G25291088403918848 | B182: TGO鲲鹏会2025年度会员年度礼包信息收集 | C182: 45860.768 | D182: 45301 | E182: 46063.999 | F182: id=2735 | H182: 张晨 | I182: 杭州 | J182: 3XL（身高：185-190cm） | K182: =86 -> 86 | L182: 15658007737 | M182: 浙江省, 杭州市, 西湖区, 三墩镇耀江文鼎苑34-201 | N182: 浙江创邻科技有限公司 CEO
A183: G25291098178351104 | B183: TGO鲲鹏会2025年度会员年度礼包信息收集 | C183: 45860.769 | D183: 45301 | E183: 46063.999 | F183: id=2735 | H183: 左瑞文 | I183: 上海 | J183: L（身高：170-175cm） | K183: =86 -> 86 | L183: 13524919174 | M183: 上海, 上海市, 闵行区, 江桦路400弄3号 | N183: Unity中国+CTO
A184: G25291105871097856 | B184: TGO鲲鹏会2025年度会员年度礼包信息收集 | C184: 45860.77 | D184: 45301 | E184: 46063.999 | F184: id=2735 | H184: 李剑洪 | I184: 厦门 | J184: XL（身高：175-180cm） | K184: =86 -> 86 | L184: 13585784554 | M184: 福建省, 厦门市, 集美区, 宁海三里禹洲中央海岸二期1号楼1901 | N184: 厦门编界科技 创始人
A185: G25291107180503040 | B185: TGO鲲鹏会2025年度会员年度礼包信息收集 | C185: 45860.77 | D185: 45301 | E185: 46063.999 | F185: id=2735 | H185: 李婷婷 | I185: 上海 | J185: L（身高：170-175cm） | K185: =86 -> 86 | L185: 13402171010 | M185: 上海, 上海市, 闵行区, 灯辉路601弄93号301室 | N185: 上海木宇信息科技有限公司 创始人 ceo
A186: G25291113759010816 | B186: TGO鲲鹏会2025年度会员年度礼包信息收集 | C186: 45860.77 | D186: 45301 | E186: 46063.999 | F186: id=2735 | H186: 邱良军 | I186: 苏州 | J186: L（身高：170-175cm） | K186: =86 -> 86 | L186: 13625280127 | M186: 江苏省, 苏州市, 苏州工业园区, 绿洲别墅144号 | N186: 苏州正雄企业发展有限公司 CIO
A187: G25291118573023232 | B187: TGO鲲鹏会2025年度会员年度礼包信息收集 | C187: 45860.771 | D187: 45301 | E187: 46063.999 | F187: id=2735 | H187: 郭有春 | I187: 南京 | J187: XL（身高：175-180cm） | K187: =86 -> 86 | L187: 13851463305 | M187: 江苏省, 南京市, 江宁区, 文心街28号 康博花园7-903 | N187: 腾讯云 架构师
A188: G25291128881442816 | B188: TGO鲲鹏会2025年度会员年度礼包信息收集 | C188: 45860.772 | D188: 45301 | E188: 46063.999 | F188: id=2735 | H188: 杨欣楠 | I188: 上海 | J188: 4XL（身高：190-195cm） | K188: =86 -> 86 | L188: 13585896465 | M188: 上海, 上海市, 浦东新区, 东方路738号裕安大厦3层 | N188: 上海馨橙网络科技有限公司. CEO
A189: G25291133158973440 | B189: TGO鲲鹏会2025年度会员年度礼包信息收集 | C189: 45860.772 | D189: 45301 | E189: 46063.999 | F189: id=2735 | H189: 张扬 | I189: 武汉 | J189: L（身高：170-175cm） | K189: =86 -> 86 | L189: 18062623260 | M189: 湖北省, 武汉市, 蔡甸区, 恒大绿洲11-1-1201 | N189: 极狐GitLab 解决方案总监
... A550: G25368809803898880 | B550: TGO鲲鹏会2025年度会员年度礼包信息收集 | C550: 45867.631 | D550: 45301 | E550: 46063.999 | F550: id=2735 | H550: 邹春刚 | I550: 广州 | J550: L（身高：170-175cm） | K550: =86 -> 86 | L550: 13560350832 | M550: 广东省, 广州市, 黄埔区, 黄埔东路680号13栋2702房 | N550: 广州阿尔戈信息科技有限公司 + CEO
A551: G25368883120205824 | B551: TGO鲲鹏会2025年度会员年度礼包信息收集 | C551: 45867.638 | D551: 45301 | E551: 46063.999 | F551: id=2735 | H551: 李道兵 | I551: 北京 | J551: XL（身高：175-180cm） | K551: =1 -> 1 | L551: 2369654848 | M551: 海外, 海外, 其他, 2206-4808 Hazel St., Burnaby, BC, Canada V5H 0A2 | N551: Fortinet Principal Embedded Software Developer
A552: G25368884239687680 | B552: TGO鲲鹏会2025年度会员年度礼包信息收集 | C552: 45867.638 | D552: 45301 | E552: 46063.999 | F552: id=2735 | H552: 张剑光 | I552: 广州 | J552: L（身高：170-175cm） | K552: =86 -> 86 | L552: 18666628706 | M552: 广东省, 广州市, 越秀区, 永胜街38号503 | N552: Apifox CEO
A553: G25368892304023552 | B553: TGO鲲鹏会2025年度会员年度礼包信息收集 | C553: 45867.638 | D553: 45301 | E553: 46063.999 | F553: id=2735 | H553: 洪强宁 | I553: 北京 | J553: L（身高：170-175cm） | K553: =86 -> 86 | L553: 18611604177 | M553: 北京, 北京市, 西城区, 西四北大街160号304室 | N553: 雅识科技联合创始人兼CTO
A554: G25368893472796672 | B554: TGO鲲鹏会2025年度会员年度礼包信息收集 | C554: 45867.639 | D554: 45301 | E554: 46063.999 | F554: id=2735 | H554: 孙斌 | I554: 北京 | J554: 4XL（身高：190-195cm） | K554: =86 -> 86 | L554: 18601178661 | M554: 北京, 北京市, 海淀区, 苏州街维亚大厦3层 | N554: 去哪儿网副总裁
A555: G25368902255669248 | B555: TGO鲲鹏会2025年度会员年度礼包信息收集 | C555: 45867.639 | D555: 45301 | E555: 46063.999 | F555: id=2735 | H555: 孙晓晖 | I555: 广州 | J555: 2XL（身高：180-185cm） | K555: =86 -> 86 | L555: 15302290071 | M555: 广东省, 广州市, 越秀区, 中山一路金羊三街12号东堤湾C4座1307房 | N555: 广东瑞普科技股份有限公司 副总经理
A556: G25368902781919232 | B556: TGO鲲鹏会2025年度会员年度礼包信息收集 | C556: 45867.639 | D556: 45301 | E556: 46063.999 | F556: id=2735 | H556: 焦洋 | I556: 北京 | J556: 3XL（身高：185-190cm） | K556: =86 -> 86 | L556: 13810184127 | M556: 北京, 北京市, 朝阳区, 阳光上东5号楼1单元601 | N556: 待定
A557: G25368918940475392 | B557: TGO鲲鹏会2025年度会员年度礼包信息收集 | C557: 45867.641 | D557: 45301 | E557: 46063.999 | F557: id=2735 | H557: 王浩华 | I557: 广州 | J557: S（身高：160-165cm） | K557: =86 -> 86 | L557: 13560004606 | M557: 广东省, 广州市, 天河区, 龙蟠花园 3 栋 2902 | N557: 广东很久文化传播有限公司+技术主管
A558: G25368937484017664 | B558: TGO鲲鹏会2025年度会员年度礼包信息收集 | C558: 45867.642 | D558: 45301 | E558: 46063.999 | F558: id=2735 | H558: 李闯 | I558: 北京 | J558: L（身高：170-175cm） | K558: =86 -> 86 | L558: 15600648213 | M558: 北京, 北京市, 海淀区, 上地街道上地东里三区6号楼1单元201 | N558: 北京飞码流星科技有限公司,CTO
A559: G25368940735393792 | B559: TGO鲲鹏会2025年度会员年度礼包信息收集 | C559: 45867.643 | D559: 45301 | E559: 46063.999 | F559: id=2735 | H559: 尹雯玉 | I559: 北京 | J559: S（身高：160-165cm） | K559: =86 -> 86 | L559: 13810170792 | M559: 北京, 北京市, 海淀区, 科学院南路搜狐媒体大厦 | N559: 搜狐+高级技术经理
A560: G25368949084811264 | B560: TGO鲲鹏会2025年度会员年度礼包信息收集 | C560: 45867.643 | D560: 45301 | E560: 46063.999 | F560: id=2735 | H560: 庞智 | I560: 北京 | J560: M（身高：165-170cm） | K560: =86 -> 86 | L560: 18610590053 | M560: 山东省, 青岛市, 胶州市, 三里河街道空港澜庭美地B区26号楼一单元202 | N560: 青岛绿波源新材料科技有限公司+总经理
A561: G25368964194004992 | B561: TGO鲲鹏会2025年度会员年度礼包信息收集 | C561: 45867.645 | D561: 45301 | E561: 46063.999 | F561: id=2735 | H561: 叶青 | I561: 广州 | J561: M（身高：165-170cm） | K561: =86 -> 86 | L561: 18680297021 | M561: 广东省, 广州市, 番禺区, 信悦都会A1栋1703室 | N561: 海鹚科技副总裁CTO
A562: G25368964482625536 | B562: TGO鲲鹏会2025年度会员年度礼包信息收集 | C562: 45867.645 | D562: 45301 | E562: 46063.999 | F562: id=2735 | H562: 王电轻 | I562: 北京 | J562: XL（身高：175-180cm） | K562: =86 -> 86 | L562: 18610254500 | M562: 五道口东升大厦ab座国家火炬科创学院3层314, 北京, 北京市, 海淀区 | N562: 不变
A563: G25368970748911616 | B563: TGO鲲鹏会2025年度会员年度礼包信息收集 | C563: 45867.645 | D563: 45301 | E563: 46063.999 | F563: id=2735 | H563: 房晓乐 | I563: 北京 | J563: L（身高：170-175cm） | K563: =86 -> 86 | L563: 13811380171 | M563: 北京, 北京市, 海淀区, 万柳中路光大西园2号楼0238 | N563: PingCAP 高级技术总监
... A719: G25381875075805184 | B719: TGO鲲鹏会2025年度会员年度礼包信息收集 | C719: 45868.785 | D719: 45301 | E719: 46063.999 | F719: id=2735 | H719: 蓝兹宏 | I719: 广州 | J719: L（身高：170-175cm） | K719: =86 -> 86 | L719: 13928707568 | M719: 广东省, 广州市, 黄埔区, 联和街道龙光香悦山二街26号1楼 | N719: 浪潮电子信息产业股份有限公司
A720: G25382388404744192 | B720: TGO鲲鹏会2025年度会员年度礼包信息收集 | C720: 45868.83 | D720: 45301 | E720: 46063.999 | F720: id=2735 | H720: 梁杰超 | I720: 广州 | J720: L（身高：170-175cm） | K720: =852 -> 852 | L720: 91475443 | M720: 香港特别行政区, 九龙城区, 其他, 香港九龙达之路78号生产力大楼 | N720: 香港生產力促進局, Unit Head of DTD
A721: G25382400786984960 | B721: TGO鲲鹏会2025年度会员年度礼包信息收集 | C721: 45868.831 | D721: 45301 | E721: 46063.999 | F721: id=2735 | H721: 吕顺炽 | I721: 广州 | J721: M（身高：165-170cm） | K721: =86 -> 86 | L721: 18688217246 | M721: 广东省, 广州市, 天河区, 金硕四路12号平安财富大厦901云下科技 | N721: 云下科技
A722: G25383089803390976 | B722: TGO鲲鹏会2025年度会员年度礼包信息收集 | C722: 45868.892 | D722: 45301 | E722: 46063.999 | F722: id=2735 | H722: 鲍博 | I722: 北京 | J722: 2XL（身高：180-185cm） | K722: =86 -> 86 | L722: 18210088711 | M722: 北京, 北京市, 朝阳区, 华贸写字楼3座3606 | N722: 红杉资本，CIO
A723: G25383214101721088 | B723: TGO鲲鹏会2025年度会员年度礼包信息收集 | C723: 45868.903 | D723: 45301 | E723: 46063.999 | F723: id=2735 | H723: 曾庆毓 | I723: 深圳 | J723: M（身高：165-170cm） | K723: =86 -> 86 | L723: 13928468618 | M723: 广东省, 深圳市, 龙华区, 龙华区龙华民治街道办石龙路与新区大道交汇处中航阳光新苑5栋2单元7A室 | N723: 副总裁，联创
A724: G25383218130477056 | B724: TGO鲲鹏会2025年度会员年度礼包信息收集 | C724: 45868.903 | D724: 45301 | E724: 46063.999 | F724: id=2735 | H724: 孙志博 | I724: 上海 | J724: L（身高：170-175cm） | K724: =86 -> 86 | L724: 13601656241 | M724: 上海, 上海市, 宝山区, 莲花山路517弄82号1201室. | N724: 菊思网络,CTO
A725: G25383555708248064 | B725: TGO鲲鹏会2025年度会员年度礼包信息收集 | C725: 45868.933 | D725: 45301 | E725: 46063.999 | F725: id=2735 | H725: 赵健 | I725: 广州 | J725: L（身高：170-175cm） | K725: =86 -> 86 | L725: 13922112705 | M725: 广东省, 广州市, 天河区, 保利林海山庄17栋703房 | N725: 阿里云+高级项目管理专家
A726: G25383615080853504 | B726: TGO鲲鹏会2025年度会员年度礼包信息收集 | C726: 45868.939 | D726: 45301 | E726: 46063.999 | F726: id=2735 | H726: 解安亮 | I726: 上海 | J726: L（身高：170-175cm） | K726: =86 -> 86 | L726: 13761912580 | M726: 上海, 上海市, 浦东新区, 亮秀路9号408 | N726: 上海谱域科技+CEO
A727: G25383746370297856 | B727: TGO鲲鹏会2025年度会员年度礼包信息收集 | C727: 45868.95 | D727: 45301 | E727: 46063.999 | F727: id=2735 | H727: 龚北斗 | I727: 北京 | J727: M（身高：165-170cm） | K727: =86 -> 86 | L727: 18611703454 | M727: 北京, 北京市, 昌平区, 沙河镇民园小区5号楼2单元201 | N727: 基调>+研发总监
A728: G25384460276363264 | B728: TGO鲲鹏会2025年度会员年度礼包信息收集 | C728: 45869.013 | D728: 45301 | E728: 46063.999 | F728: id=2735 | H728: 张志合 | I728: 广州 | J728: 2XL（身高：180-185cm） | K728: =86 -> 86 | L728: 18926175696 | M728: 广东省, 广州市, 海珠区, 盈丰路英豪花园A1栋2206房 | N728: 卓越教育-资深IT总监
A729: G25388636228968448 | B729: TGO鲲鹏会2025年度会员年度礼包信息收集 | C729: 45869.382 | D729: 45301 | E729: 46063.999 | F729: id=2735 | H729: 鄢晓玲 | I729: 北京 | J729: M（身高：165-170cm） | K729: =86 -> 86 | L729: 18581836077 | M729: 四川省, 成都市, 其他, 成都高新区世纪城路198号会展中心商业街7区7号馆7-303号房 | N729: 北京知道创宇+总经理
A730: G25388807685038080 | B730: TGO鲲鹏会2025年度会员年度礼包信息收集 | C730: 45869.397 | D730: 45301 | E730: 46063.999 | F730: id=2735 | H730: 伍航恩 | I730: 上海 | J730: M（身高：165-170cm） | K730: =86 -> 86 | L730: 13903075572 | M730: 广东省, 广州市, 白云区, 沙太北路938号金湖花园5栋3单元101 | N730: 深圳敏捷云 CTO
A731: G25388874972819456 | B731: TGO鲲鹏会2025年度会员年度礼包信息收集 | C731: 45869.403 | D731: 45301 | E731: 46063.999 | F731: id=2735 | H731: 唐铕泽 | I731: 新加坡 | J731: L（身高：170-175cm） | K731: =86 -> 86 | L731: 19901702989 | M731: 上海, 上海市, 杨浦区, 城市概念8号楼南区B10 | N731: 1Token CTO
A732: G25389197427367936 | B732: TGO鲲鹏会2025年度会员年度礼包信息收集 | C732: 45869.431 | D732: 45301 | E732: 46063.999 | F732: id=2735 | H732: 刘昊臻 | I732: 广州 | J732: XL（身高：175-180cm） | K732: =86 -> 86 | L732: 15622735564 | M732: 广东省, 广州市, 番禺区, 亚运城运动员村一区二座 | N732: xpack ceo
... A765: G25626933031759872 | B765: TGO鲲鹏会2025年度会员年度礼包信息收集 | C765: 45890.424 | D765: 45301 | E765: 46063.999 | F765: id=2735 | H765: 翟星吉 | I765: 上海 | J765: L（身高：170-175cm） | K765: =86 -> 86 | L765: 18616546348 | M765: 上海, 上海市, 徐汇区, 古美路1528号a6号楼9楼 | N765: 语核科技，创始人&CEO
A766: G25627003110055936 | B766: TGO鲲鹏会2025年度会员年度礼包信息收集 | C766: 45890.43 | D766: 45301 | E766: 46063.999 | F766: id=2735 | H766: 和昊原 | I766: 硅谷 | J766: XL（身高：175-180cm） | K766: =1 -> 1 | L766: 6092128327 | M766: 海外, 海外, 其他, 1725 s bascom ave, apt 338, Campbell, CA, 95008 | N766: Netflix, software engineer
A767: G25627095843627008 | B767: TGO鲲鹏会2025年度会员年度礼包信息收集 | C767: 45890.439 | D767: 45301 | E767: 46063.999 | F767: id=2735 | H767: 黎雄兵 | I767: 北京 | J767: 2XL（身高：180-185cm） | K767: =86 -> 86 | L767: 13720002630 | M767: 北京, 北京市, 通州区, 梨园华业东方玫瑰D9一单元2603 | N767: 北京微吼时代科技研发中心总经理
A768: G25629056073752576 | B768: TGO鲲鹏会2025年度会员年度礼包信息收集 | C768: 45890.612 | D768: 45301 | E768: 46063.999 | F768: id=2735 | H768: 范鸣晖 | I768: 北京 | J768: 2XL（身高：180-185cm） | K768: =86 -> 86 | L768: 18252000227 | M768: 北京, 北京市, 丰台区 | N768: 帆软软件有限公司技术总监
A769: G25629439700393984 | B769: TGO鲲鹏会2025年度会员年度礼包信息收集 | C769: 45890.646 | D769: 45301 | E769: 46063.999 | F769: id=2735 | H769: 魏祥臣 | I769: 深圳 | J769: XL（身高：175-180cm） | K769: =86 -> 86 | L769: 18126308018 | M769: 广东省, 深圳市, 龙华区, 人民路日出印象A区3栋3单元404 | N769: 上海谙流科技+联合创始人
A770: G25640818448162816 | B770: TGO鲲鹏会2025年度会员年度礼包信息收集 | C770: 45891.65 | D770: 45301 | E770: 46063.999 | F770: id=2735 | H770: 杨鹤 | I770: 上海 | J770: 4XL（身高：190-195cm） | K770: =86 -> 86 | L770: 18521087652 | M770: 上海, 上海市, 浦东新区, 观海路1118弄28号402 | N770: 紫光展锐+架构师
A771: G25672513791090688 | B771: TGO鲲鹏会2025年度会员年度礼包信息收集 | C771: 45894.449 | D771: 45301 | E771: 46063.999 | F771: id=2735 | H771: 叶经纬 | I771: 北京 | J771: 2XL（身高：180-185cm） | K771: =86 -> 86 | L771: 13810334135 | M771: 北京, 北京市, 海淀区, 叶伟 13810334135 北京市北京市海淀区 科学院南路2号院3号楼融科资讯中心D座搜狐媒体大厦 | N771: 搜狐 总监
A772: G25684669059588096 | B772: TGO鲲鹏会2025年度会员年度礼包信息收集 | C772: 45895.523 | D772: 45301 | E772: 46063.999 | F772: id=2735 | H772: 李卫新 | I772: 北京 | J772: 4XL（身高：190-195cm） | K772: =86 -> 86 | L772: 18612438911 | M772: 山东省, 青岛市, 崂山区, 合肥路851号鲁信含章花园9号楼1单元1703室 | N772: 中泰信合智能科技有限公司 副总经理&CTO
A773: G25687360051372032 | B773: TGO鲲鹏会2025年度会员年度礼包信息收集 | C773: 45895.76 | D773: 45301 | E773: 46063.999 | F773: id=2735 | H773: 熊毅良 | I773: 厦门 | J773: 3XL（身高：185-190cm） | K773: =86 -> 86 | L773: 18150133335 | M773: 福建省, 厦门市, 思明区, 联发滨海名居60号2202 | N773: 厦门数宇科技，CEO
A774: G25687406473273344 | B774: TGO鲲鹏会2025年度会员年度礼包信息收集 | C774: 45895.764 | D774: 45301 | E774: 46063.999 | F774: id=2735 | H774: 李剑洪 | I774: 厦门 | J774: XL（身高：175-180cm） | K774: =86 -> 86 | L774: 13585784554 | M774: 福建省, 厦门市, 集美区, 宁海三里禹洲中央海岸二期1号楼1901 | N774: 厦门编界科技 创始人
A775: G25687410985037824 | B775: TGO鲲鹏会2025年度会员年度礼包信息收集 | C775: 45895.765 | D775: 45301 | E775: 46063.999 | F775: id=2735 | H775: 杨瑞 | I775: 厦门 | J775: XL（身高：175-180cm） | K775: =86 -> 86 | L775: 13950153082 | M775: 福建省, 厦门市, 思明区, 云顶西路70号6号楼402室 | N775: 厦门英睿信息科技有限公司CEO
A776: G25687641623261184 | B776: TGO鲲鹏会2025年度会员年度礼包信息收集 | C776: 45895.785 | D776: 45301 | E776: 46063.999 | F776: id=2735 | H776: 张长生 | I776: 厦门 | J776: L（身高：170-175cm） | K776: =86 -> 86 | L776: 18859231888 | M776: 福建省, 厦门市, 思明区, 望海路65号之二806（软件园二期）易驰软件 | N776: 厦门易驰软件有限公司CEO
A777: G25687766522814464 | B777: TGO鲲鹏会2025年度会员年度礼包信息收集 | C777: 45895.796 | D777: 45301 | E777: 46063.999 | F777: id=2735 | H777: 胡倞 | I777: 厦门 | J777: M（身高：165-170cm） | K777: =86 -> 86 | L777: 18559027105 | M777: 福建省, 厦门市, 海沧区, 融信海上城3号楼1122 | N777: Manteia数据科技有限公司，技术总监
A778: G25751836490227712 | B778: TGO鲲鹏会2025年度会员年度礼包信息收集 | C778: 45901.454 | D778: 45301 | E778: 46063.999 | F778: id=2735 | H778: 阮俊彦 | I778: 上海 | J778: M（身高：165-170cm） | K778: =86 -> 86 | L778: 18060798757 | M778: 上海, 上海市, 闵行区, 环镇南路88号苹果园58号楼505室 | N778: 亚朵集团-技术VP
... A1029: G27284037526511616 | B1029: TGO鲲鹏会2025年度会员年度礼包信息收集 | C1029: 46036.752 | D1029: 45301 | E1029: 46063.999 | F1029: id=2735 | H1029: 周峰 | I1029: 北京 | J1029: 4XL（身高：190-195cm） | K1029: =86 -> 86 | L1029: 13910051321 | M1029: 北京, 北京市, 朝阳区, 东土城路七号院2号楼510 | N1029: 内蒙古中研智达信息技术有限公司，创始人
A1030: G27360059082174464 | B1030: TGO鲲鹏会2025年度会员年度礼包信息收集 | C1030: 46043.465 | D1030: 45301 | E1030: 46063.999 | F1030: id=2735 | H1030: 解敏 | I1030: 杭州 | J1030: M（身高：165-170cm） | K1030: =86 -> 86 | L1030: 18268046890 | M1030: 浙江省, 杭州市, 西湖区, 五常港路 紫霞街 西溪华府中海西溪华府9幢 2单元102 | N1030: 111
A1031: G27383294252965888 | B1031: TGO鲲鹏会2025年度会员年度礼包信息收集 | C1031: 46045.517 | D1031: 45301 | E1031: 46063.999 | F1031: id=2735 | H1031: 李茂林 | I1031: 深圳 | J1031: 2XL（身高：180-185cm） | K1031: =86 -> 86 | L1031: 13981734846 | M1031: 广东省, 深圳市, 宝安区, 西乡街道山海御园7栋2单元3002 | N1031: 深圳市微智电子有限公司总经理
A1032: G27415861275287552 | B1032: TGO鲲鹏会2025年度会员年度礼包信息收集 | C1032: 46048.392 | D1032: 45301 | E1032: 46063.999 | F1032: id=2735 | H1032: 黄程昱 | I1032: 南京 | J1032: XL（身高：175-180cm） | K1032: =86 -> 86 | L1032: 13813919027 | M1032: 江苏省, 南京市, 鼓楼区, 南京市鼓楼区裕顺雅苑26栋106室 | N1032: 南京凯润易事软件科技有限公司+技术经理
A1033: G27421235135934464 | B1033: TGO鲲鹏会2025年度会员年度礼包信息收集 | C1033: 46048.867 | D1033: 45301 | E1033: 46063.999 | F1033: id=2735 | H1033: 李楠 | I1033: 北京 | J1033: 3XL（身高：185-190cm） | K1033: =86 -> 86 | L1033: 15633841042 | M1033: 河北省, 石家庄市, 裕华区, 维多利亚四期翠景园16号楼2单元404 | N1033: 融放科技总经理
A1034: G27421761514532864 | B1034: TGO鲲鹏会2025年度会员年度礼包信息收集 | C1034: 46048.913 | D1034: 45301 | E1034: 46063.999 | F1034: id=2735 | H1034: 高毅 | I1034: 成都 | J1034: L（身高：170-175cm） | K1034: =86 -> 86 | L1034: 15928080782 | M1034: 四川省, 成都市, 锦江区, 四海逸家蓝钻二栋 | N1034: 腾讯PM
A1035: G27422831176871936 | B1035: TGO鲲鹏会2025年度会员年度礼包信息收集 | C1035: 46049.008 | D1035: 45301 | E1035: 46063.999 | F1035: id=2735 | H1035: 郑智国 | I1035: 杭州 | J1035: XL（身高：175-180cm） | K1035: =86 -> 86 | L1035: 13777829679 | M1035: 浙江省, 杭州市, 西湖区, 杭州市西湖区文二西路66号，世纪新城西区-34幢1603 | N1035: e签宝-研发中心总监
A1036: G27439619162398720 | B1036: TGO鲲鹏会2025年度会员年度礼包信息收集 | C1036: 46050.49 | D1036: 45301 | E1036: 46063.999 | F1036: id=2735 | H1036: 陈晗琪 | I1036: 苏州 | J1036: 2XL（身高：180-185cm） | K1036: =86 -> 86 | L1036: 13706134550 | M1036: 江苏省, 苏州市, 苏州工业园区, 湖畔天城12幢1903 | N1036: 苏州英格玛服务外包股份有限公司+人工智能资深专家
A1037: G27444972165816320 | B1037: TGO鲲鹏会2025年度会员年度礼包信息收集 | C1037: 46050.963 | D1037: 45301 | E1037: 46063.999 | F1037: id=2735 | H1037: 罗立 | I1037: 成都 | J1037: M（身高：165-170cm） | K1037: =86 -> 86 | L1037: 18111673367 | M1037: 四川省, 成都市, 双流区, 华府大道三段869号万锦城 | N1037: 技术总监
A1038: G27449901640216576 | B1038: TGO鲲鹏会2025年度会员年度礼包信息收集 | C1038: 46051.398 | D1038: 45301 | E1038: 46063.999 | F1038: id=2735 | H1038: 王磊 | I1038: 杭州 | J1038: L（身高：170-175cm） | K1038: =86 -> 86 | L1038: 18258493245 | M1038: 浙江省, 杭州市, 余杭区, 中泰街道铜山溪路2号8号楼501-1室 | N1038: CEO
A1039: G27450443430522880 | B1039: TGO鲲鹏会2025年度会员年度礼包信息收集 | C1039: 46051.446 | D1039: 45301 | E1039: 46063.999 | F1039: id=2735 | H1039: 徐繁荣 | I1039: 苏州 | J1039: XL（身高：175-180cm） | K1039: =86 -> 86 | L1039: 15605159126 | M1039: 江苏省, 苏州市, 昆山市, 玉山镇兰亭御园20栋 | N1039: 胥瓷信息科技（苏州）有限公司
A1040: G27462670200107008 | B1040: TGO鲲鹏会2025年度会员年度礼包信息收集 | C1040: 46052.526 | D1040: 45301 | E1040: 46063.999 | F1040: id=2735 | H1040: 丘岳峰 | I1040: 北京 | J1040: L（身高：170-175cm） | K1040: =86 -> 86 | L1040: 18618266694 | M1040: 北京, 北京市, 西城区, 格调小区3号楼2单元1001 | N1040: 华清智言 CEO
A1041: G27497121032331264 | B1041: TGO鲲鹏会2025年度会员年度礼包信息收集 | C1041: 46055.568 | D1041: 45301 | E1041: 46063.999 | F1041: id=2735 | H1041: 黄程昱 | I1041: 南京 | J1041: XL（身高：175-180cm） | K1041: =86 -> 86 | L1041: 13813919027 | M1041: 江苏省, 南京市, 鼓楼区, 江苏省南京市鼓楼区裕顺雅苑26号106室 | N1041: 南京凯润易事软件科技有限公司+技术经理
A1042: G27499086801559552 | B1042: TGO鲲鹏会2025年度会员年度礼包信息收集 | C1042: 46055.741 | D1042: 45301 | E1042: 46063.999 | F1042: id=2735 | H1042: 黄冠明 | I1042: 北京 | J1042: L（身高：170-175cm） | K1042: =86 -> 86 | L1042: 18001301756 | M1042: 北京, 北京市, 丰台区, 玉璞家园1号楼2112 | N1042: 清控紫荆事业部总经理
... A1052: G27541852890882048 | B1052: TGO鲲鹏会2025年度会员年度礼包信息收集 | C1052: 46059.518 | D1052: 45301 | E1052: 46063.999 | F1052: id=2735 | H1052: 周彦卓 | I1052: 南京 | J1052: XL（身高：175-180cm） | K1052: =86 -> 86 | L1052: 15006152983 | M1052: 江苏省, 无锡市, 宜兴市, 环科园丝绸花园中通快递站 | N1052: shein 工程师

Sheet Sheet34
